Workbook

Sheet Cómo usar
B2: Plantilla de control de inventario
B3: Entradas, salidas, existencias, alertas de reorden y kardex por artículo. Gratis, sin macros.
B6: Cómo se usa
B7: 1. En Productos, da de alta cada artículo con una clave única, su costo, su stock mínimo (y máximo, si lo manejas) y la existencia con la que arrancas.
B8: 2. En Movimientos, captura una fila por cada entrada (compra, devolución de cliente) o salida (venta, consumo, merma), en orden de fecha.
B9: 3. Las existencias, el valor del inventario y el estado (OK, Reordenar, Agotado) se calculan solos en Productos.
B10: 4. En Resumen ves los totales del mes y la lista de compras sugerida; en Kardex, el historial completo de un artículo.
B11: 5. Los datos que trae son de ejemplo: bórralos de Productos (columnas A a I) y de Movimientos (A, B, C, F, J, K y L) antes de empezar.
B13: Colores
B14: Celdas amarillas: aquí capturas.
B15: Celdas grises: fórmulas. No las borres ni escribas encima; si se rompe una, cópiala de la fila de arriba.
B17: Buenas prácticas
... B29: Puedes usarla y compartirla libremente; si la publicas en tu sitio, enlaza a la guía de arriba.

Sheet Resumen
A1: Resumen del inventario
A2: Se actualiza solo con lo que captures en Productos y Movimientos.
B4: Mes a revisar | C4: 46296
B6: Artículos en el catálogo | C6: =COUNTA(Productos!$A$5:$A$504) -> 8
B7: Valor total del inventario | C7: =SUM(Productos!$M$5:$M$504) -> 38581
B8: Artículos por reordenar | C8: =COUNTIF(Productos!$N$5:$N$504,"Reordenar") -> 4
B9: Artículos agotados | C9: =COUNTIF(Productos!$N$5:$N$504,"Agotado") -> 1
B10: Movimientos de entrada en el mes | C10: =COUNTIFS(Movimientos!$B$5:$B$3004,"Entrada",Movimientos!$A$5:$A$3004,">="&DATE(YEAR($C$4),MONTH($C$4),1),Movimientos!$A$5:$A$3004,"<"&EDATE(DATE(YEAR($C$4),MONTH($C$4),1),1)) -> 4
B11: Movimientos de salida en el mes | C11: =COUNTIFS(Movimientos!$B$5:$B$3004,"Salida",Movimientos!$A$5:$A$3004,">="&DATE(YEAR($C$4),MONTH($C$4),1),Movimientos!$A$5:$A$3004,"<"&EDATE(DATE(YEAR($C$4),MONTH($C$4),1),1)) -> 10
B12: Valor de las entradas del mes | C12: =SUMIFS(Movimientos!$H$5:$H$3004,Movimientos!$B$5:$B$3004,"Entrada",Movimientos!$A$5:$A$3004,">="&DATE(YEAR($C$4),MONTH($C$4),1),Movimientos!$A$5:$A$3004,"<"&EDATE(DATE(YEAR($C$4),MONTH($C$4),1),1)) -> 36990
B13: Valor de las salidas del mes | C13: =SUMIFS(Movimientos!$H$5:$H$3004,Movimientos!$B$5:$B$3004,"Salida",Movimientos!$A$5:$A$3004,">="&DATE(YEAR($C$4),MONTH($C$4),1),Movimientos!$A$5:$A$3004,"<"&EDATE(DATE(YEAR($C$4),MONTH($C$4),1),1)) -> 78609
B15: Lista de compras sugerida | D15: Artículos agotados o en su mínimo. Sugerido = llevarlo al stock máximo (o al doble del mínimo si no capturaste máximo).
B16: # | C16: Clave | D16: Descripción | E16: Existencia | F16: Mínimo | G16: Estado | H16: Sugerido comprar
B17: =IF(1<=COUNTIF(Productos!$O$5:$O$504,">0"),1,"") -> 1 | C17: =IF($B17="","",INDEX(Productos!$A$5:$A$504,MATCH($B17,Productos!$O$5:$O$504,0))) -> P-002 | D17: =IF($B17="","",INDEX(Productos!$B$5:$B$504,MATCH($B17,Productos!$O$5:$O$504,0))) -> Varilla corrugada 3/8" | E17: =IF($B17="","",INDEX(Productos!$L$5:$L$504,MATCH($B17,Productos!$O$5:$O$504,0))) -> 60 | F17: =IF($B17="","",INDEX(Productos!$G$5:$G$504,MATCH($B17,Productos!$O$5:$O$504,0))) -> 100 | G17: =IF($B17="","",INDEX(Productos!$N$5:$N$504,MATCH($B17,Productos!$O$5:$O$504,0))) -> Reordenar | H17: =IF($B17="","",MAX(0,IF(N(INDEX(Productos!$H$5:$H$504,MATCH($B17,Productos!$O$5:$O$504,0)))>0,N(INDEX(Productos!$H$5:$H$504,MATCH($B17,Productos!$O$5:$O$504,0))),2*N(F17))-E17)) -> 240
B18: =IF(2<=COUNTIF(Productos!$O$5:$O$504,">0"),2,"") -> 2 | C18: =IF($B18="","",INDEX(Productos!$A$5:$A$504,MATCH($B18,Productos!$O$5:$O$504,0))) -> P-003 | D18: =IF($B18="","",INDEX(Productos!$B$5:$B$504,MATCH($B18,Productos!$O$5:$O$504,0))) -> Block de concreto 15x20x40 | E18: =IF($B18="","",INDEX(Productos!$L$5:$L$504,MATCH($B18,Productos!$O$5:$O$504,0))) -> 420 | F18: =IF($B18="","",INDEX(Productos!$G$5:$G$504,MATCH($B18,Productos!$O$5:$O$504,0))) -> 500 | G18: =IF($B18="","",INDEX(Productos!$N$5:$N$504,MATCH($B18,Productos!$O$5:$O$504,0))) -> Reordenar | H18: =IF($B18="","",MAX(0,IF(N(INDEX(Productos!$H$5:$H$504,MATCH($B18,Productos!$O$5:$O$504,0)))>0,N(INDEX(Productos!$H$5:$H$504,MATCH($B18,Productos!$O$5:$O$504,0))),2*N(F18))-E18)) -> 1580
B19: =IF(3<=COUNTIF(Productos!$O$5:$O$504,">0"),3,"") -> 3 | C19: =IF($B19="","",INDEX(Productos!$A$5:$A$504,MATCH($B19,Productos!$O$5:$O$504,0))) -> P-005 | D19: =IF($B19="","",INDEX(Productos!$B$5:$B$504,MATCH($B19,Productos!$O$5:$O$504,0))) -> Pintura vinílica blanca 19 L | E19: =IF($B19="","",INDEX(Productos!$L$5:$L$504,MATCH($B19,Productos!$O$5:$O$504,0))) -> 4 | F19: =IF($B19="","",INDEX(Productos!$G$5:$G$504,MATCH($B19,Productos!$O$5:$O$504,0))) -> 5 | G19: =IF($B19="","",INDEX(Productos!$N$5:$N$504,MATCH($B19,Productos!$O$5:$O$504,0))) -> Reordenar | H19: =IF($B19="","",MAX(0,IF(N(INDEX(Productos!$H$5:$H$504,MATCH($B19,Productos!$O$5:$O$504,0)))>0,N(INDEX(Productos!$H$5:$H$504,MATCH($B19,Productos!$O$5:$O$504,0))),2*N(F19))-E19)) -> 16
B20: =IF(4<=COUNTIF(Productos!$O$5:$O$504,">0"),4,"") -> 4 | C20: =IF($B20="","",INDEX(Productos!$A$5:$A$504,MATCH($B20,Productos!$O$5:$O$504,0))) -> P-006 | D20: =IF($B20="","",INDEX(Productos!$B$5:$B$504,MATCH($B20,Productos!$O$5:$O$504,0))) -> Alambre recocido | E20: =IF($B20="","",INDEX(Productos!$L$5:$L$504,MATCH($B20,Productos!$O$5:$O$504,0))) -> 35 | F20: =IF($B20="","",INDEX(Productos!$G$5:$G$504,MATCH($B20,Productos!$O$5:$O$504,0))) -> 50 | G20: =IF($B20="","",INDEX(Productos!$N$5:$N$504,MATCH($B20,Productos!$O$5:$O$504,0))) -> Reordenar | H20: =IF($B20="","",MAX(0,IF(N(INDEX(Productos!$H$5:$H$504,MATCH($B20,Productos!$O$5:$O$504,0)))>0,N(INDEX(Productos!$H$5:$H$504,MATCH($B20,Productos!$O$5:$O$504,0))),2*N(F20))-E20)) -> 165
B21: =IF(5<=COUNTIF(Productos!$O$5:$O$504,">0"),5,"") -> 5 | C21: =IF($B21="","",INDEX(Productos!$A$5:$A$504,MATCH($B21,Productos!$O$5:$O$504,0))) -> P-007 | D21: =IF($B21="","",INDEX(Productos!$B$5:$B$504,MATCH($B21,Productos!$O$5:$O$504,0))) -> Cable THW calibre 12 | E21: =IF($B21="","",INDEX(Productos!$L$5:$L$504,MATCH($B21,Productos!$O$5:$O$504,0))) -> 0 | F21: =IF($B21="","",INDEX(Productos!$G$5:$G$504,MATCH($B21,Productos!$O$5:$O$504,0))) -> 4 | G21: =IF($B21="","",INDEX(Productos!$N$5:$N$504,MATCH($B21,Productos!$O$5:$O$504,0))) -> Agotado | H21: =IF($B21="","",MAX(0,IF(N(INDEX(Productos!$H$5:$H$504,MATCH($B21,Productos!$O$5:$O$504,0)))>0,N(INDEX(Productos!$H$5:$H$504,MATCH($B21,Productos!$O$5:$O$504,0))),2*N(F21))-E21)) -> 12
B22: =IF(6<=COUNTIF(Productos!$O$5:$O$504,">0"),6,"") | C22: =IF($B22="","",INDEX(Productos!$A$5:$A$504,MATCH($B22,Productos!$O$5:$O$504,0))) | D22: =IF($B22="","",INDEX(Productos!$B$5:$B$504,MATCH($B22,Productos!$O$5:$O$504,0))) | E22: =IF($B22="","",INDEX(Productos!$L$5:$L$504,MATCH($B22,Productos!$O$5:$O$504,0))) | F22: =IF($B22="","",INDEX(Productos!$G$5:$G$504,MATCH($B22,Productos!$O$5:$O$504,0))) | G22: =IF($B22="","",INDEX(Productos!$N$5:$N$504,MATCH($B22,Productos!$O$5:$O$504,0))) | H22: =IF($B22="","",MAX(0,IF(N(INDEX(Productos!$H$5:$H$504,MATCH($B22,Productos!$O$5:$O$504,0)))>0,N(INDEX(Productos!$H$5:$H$504,MATCH($B22,Productos!$O$5:$O$504,0))),2*N(F22))-E22))
B23: =IF(7<=COUNTIF(Productos!$O$5:$O$504,">0"),7,"") | C23: =IF($B23="","",INDEX(Productos!$A$5:$A$504,MATCH($B23,Productos!$O$5:$O$504,0))) | D23: =IF($B23="","",INDEX(Productos!$B$5:$B$504,MATCH($B23,Productos!$O$5:$O$504,0))) | E23: =IF($B23="","",INDEX(Productos!$L$5:$L$504,MATCH($B23,Productos!$O$5:$O$504,0))) | F23: =IF($B23="","",INDEX(Productos!$G$5:$G$504,MATCH($B23,Productos!$O$5:$O$504,0))) | G23: =IF($B23="","",INDEX(Productos!$N$5:$N$504,MATCH($B23,Productos!$O$5:$O$504,0))) | H23: =IF($B23="","",MAX(0,IF(N(INDEX(Productos!$H$5:$H$504,MATCH($B23,Productos!$O$5:$O$504,0)))>0,N(INDEX(Productos!$H$5:$H$504,MATCH($B23,Productos!$O$5:$O$504,0))),2*N(F23))-E23))
B24: =IF(8<=COUNTIF(Productos!$O$5:$O$504,">0"),8,"") | C24: =IF($B24="","",INDEX(Productos!$A$5:$A$504,MATCH($B24,Productos!$O$5:$O$504,0))) | D24: =IF($B24="","",INDEX(Productos!$B$5:$B$504,MATCH($B24,Productos!$O$5:$O$504,0))) | E24: =IF($B24="","",INDEX(Productos!$L$5:$L$504,MATCH($B24,Productos!$O$5:$O$504,0))) | F24: =IF($B24="","",INDEX(Productos!$G$5:$G$504,MATCH($B24,Productos!$O$5:$O$504,0))) | G24: =IF($B24="","",INDEX(Productos!$N$5:$N$504,MATCH($B24,Productos!$O$5:$O$504,0))) | H24: =IF($B24="","",MAX(0,IF(N(INDEX(Productos!$H$5:$H$504,MATCH($B24,Productos!$O$5:$O$504,0)))>0,N(INDEX(Productos!$H$5:$H$504,MATCH($B24,Productos!$O$5:$O$504,0))),2*N(F24))-E24))
B25: =IF(9<=COUNTIF(Productos!$O$5:$O$504,">0"),9,"") | C25: =IF($B25="","",INDEX(Productos!$A$5:$A$504,MATCH($B25,Productos!$O$5:$O$504,0))) | D25: =IF($B25="","",INDEX(Productos!$B$5:$B$504,MATCH($B25,Productos!$O$5:$O$504,0))) | E25: =IF($B25="","",INDEX(Productos!$L$5:$L$504,MATCH($B25,Productos!$O$5:$O$504,0))) | F25: =IF($B25="","",INDEX(Productos!$G$5:$G$504,MATCH($B25,Productos!$O$5:$O$504,0))) | G25: =IF($B25="","",INDEX(Productos!$N$5:$N$504,MATCH($B25,Productos!$O$5:$O$504,0))) | H25: =IF($B25="","",MAX(0,IF(N(INDEX(Productos!$H$5:$H$504,MATCH($B25,Productos!$O$5:$O$504,0)))>0,N(INDEX(Productos!$H$5:$H$504,MATCH($B25,Productos!$O$5:$O$504,0))),2*N(F25))-E25))
B26: =IF(10<=COUNTIF(Productos!$O$5:$O$504,">0"),10,"") | C26: =IF($B26="","",INDEX(Productos!$A$5:$A$504,MATCH($B26,Productos!$O$5:$O$504,0))) | D26: =IF($B26="","",INDEX(Productos!$B$5:$B$504,MATCH($B26,Productos!$O$5:$O$504,0))) | E26: =IF($B26="","",INDEX(Productos!$L$5:$L$504,MATCH($B26,Productos!$O$5:$O$504,0))) | F26: =IF($B26="","",INDEX(Productos!$G$5:$G$504,MATCH($B26,Productos!$O$5:$O$504,0))) | G26: =IF($B26="","",INDEX(Productos!$N$5:$N$504,MATCH($B26,Productos!$O$5:$O$504,0))) | H26: =IF($B26="","",MAX(0,IF(N(INDEX(Productos!$H$5:$H$504,MATCH($B26,Productos!$O$5:$O$504,0)))>0,N(INDEX(Productos!$H$5:$H$504,MATCH($B26,Productos!$O$5:$O$504,0))),2*N(F26))-E26))
B27: =IF(11<=COUNTIF(Productos!$O$5:$O$504,">0"),11,"") | C27: =IF($B27="","",INDEX(Productos!$A$5:$A$504,MATCH($B27,Productos!$O$5:$O$504,0))) | D27: =IF($B27="","",INDEX(Productos!$B$5:$B$504,MATCH($B27,Productos!$O$5:$O$504,0))) | E27: =IF($B27="","",INDEX(Productos!$L$5:$L$504,MATCH($B27,Productos!$O$5:$O$504,0))) | F27: =IF($B27="","",INDEX(Productos!$G$5:$G$504,MATCH($B27,Productos!$O$5:$O$504,0))) | G27: =IF($B27="","",INDEX(Productos!$N$5:$N$504,MATCH($B27,Productos!$O$5:$O$504,0))) | H27: =IF($B27="","",MAX(0,IF(N(INDEX(Productos!$H$5:$H$504,MATCH($B27,Productos!$O$5:$O$504,0)))>0,N(INDEX(Productos!$H$5:$H$504,MATCH($B27,Productos!$O$5:$O$504,0))),2*N(F27))-E27))
B28: =IF(12<=COUNTIF(Productos!$O$5:$O$504,">0"),12,"") | C28: =IF($B28="","",INDEX(Productos!$A$5:$A$504,MATCH($B28,Productos!$O$5:$O$504,0))) | D28: =IF($B28="","",INDEX(Productos!$B$5:$B$504,MATCH($B28,Productos!$O$5:$O$504,0))) | E28: =IF($B28="","",INDEX(Productos!$L$5:$L$504,MATCH($B28,Productos!$O$5:$O$504,0))) | F28: =IF($B28="","",INDEX(Productos!$G$5:$G$504,MATCH($B28,Productos!$O$5:$O$504,0))) | G28: =IF($B28="","",INDEX(Productos!$N$5:$N$504,MATCH($B28,Productos!$O$5:$O$504,0))) | H28: =IF($B28="","",MAX(0,IF(N(INDEX(Productos!$H$5:$H$504,MATCH($B28,Productos!$O$5:$O$504,0)))>0,N(INDEX(Productos!$H$5:$H$504,MATCH($B28,Productos!$O$5:$O$504,0))),2*N(F28))-E28))
B29: =IF(13<=COUNTIF(Productos!$O$5:$O$504,">0"),13,"") | C29: =IF($B29="","",INDEX(Productos!$A$5:$A$504,MATCH($B29,Productos!$O$5:$O$504,0))) | D29: =IF($B29="","",INDEX(Productos!$B$5:$B$504,MATCH($B29,Productos!$O$5:$O$504,0))) | E29: =IF($B29="","",INDEX(Productos!$L$5:$L$504,MATCH($B29,Productos!$O$5:$O$504,0))) | F29: =IF($B29="","",INDEX(Productos!$G$5:$G$504,MATCH($B29,Productos!$O$5:$O$504,0))) | G29: =IF($B29="","",INDEX(Productos!$N$5:$N$504,MATCH($B29,Productos!$O$5:$O$504,0))) | H29: =IF($B29="","",MAX(0,IF(N(INDEX(Productos!$H$5:$H$504,MATCH($B29,Productos!$O$5:$O$504,0)))>0,N(INDEX(Productos!$H$5:$H$504,MATCH($B29,Productos!$O$5:$O$504,0))),2*N(F29))-E29))
B30: =IF(14<=COUNTIF(Productos!$O$5:$O$504,">0"),14,"") | C30: =IF($B30="","",INDEX(Productos!$A$5:$A$504,MATCH($B30,Productos!$O$5:$O$504,0))) | D30: =IF($B30="","",INDEX(Productos!$B$5:$B$504,MATCH($B30,Productos!$O$5:$O$504,0))) | E30: =IF($B30="","",INDEX(Productos!$L$5:$L$504,MATCH($B30,Productos!$O$5:$O$504,0))) | F30: =IF($B30="","",INDEX(Productos!$G$5:$G$504,MATCH($B30,Productos!$O$5:$O$504,0))) | G30: =IF($B30="","",INDEX(Productos!$N$5:$N$504,MATCH($B30,Productos!$O$5:$O$504,0))) | H30: =IF($B30="","",MAX(0,IF(N(INDEX(Productos!$H$5:$H$504,MATCH($B30,Productos!$O$5:$O$504,0)))>0,N(INDEX(Productos!$H$5:$H$504,MATCH($B30,Productos!$O$5:$O$504,0))),2*N(F30))-E30))
B31: =IF(15<=COUNTIF(Productos!$O$5:$O$504,">0"),15,"") | C31: =IF($B31="","",INDEX(Productos!$A$5:$A$504,MATCH($B31,Productos!$O$5:$O$504,0))) | D31: =IF($B31="","",INDEX(Productos!$B$5:$B$504,MATCH($B31,Productos!$O$5:$O$504,0))) | E31: =IF($B31="","",INDEX(Productos!$L$5:$L$504,MATCH($B31,Productos!$O$5:$O$504,0))) | F31: =IF($B31="","",INDEX(Productos!$G$5:$G$504,MATCH($B31,Productos!$O$5:$O$504,0))) | G31: =IF($B31="","",INDEX(Productos!$N$5:$N$504,MATCH($B31,Productos!$O$5:$O$504,0))) | H31: =IF($B31="","",MAX(0,IF(N(INDEX(Productos!$H$5:$H$504,MATCH($B31,Productos!$O$5:$O$504,0)))>0,N(INDEX(Productos!$H$5:$H$504,MATCH($B31,Productos!$O$5:$O$504,0))),2*N(F31))-E31))
B32: =IF(16<=COUNTIF(Productos!$O$5:$O$504,">0"),16,"") | C32: =IF($B32="","",INDEX(Productos!$A$5:$A$504,MATCH($B32,Productos!$O$5:$O$504,0))) | D32: =IF($B32="","",INDEX(Productos!$B$5:$B$504,MATCH($B32,Productos!$O$5:$O$504,0))) | E32: =IF($B32="","",INDEX(Productos!$L$5:$L$504,MATCH($B32,Productos!$O$5:$O$504,0))) | F32: =IF($B32="","",INDEX(Productos!$G$5:$G$504,MATCH($B32,Productos!$O$5:$O$504,0))) | G32: =IF($B32="","",INDEX(Productos!$N$5:$N$504,MATCH($B32,Productos!$O$5:$O$504,0))) | H32: =IF($B32="","",MAX(0,IF(N(INDEX(Productos!$H$5:$H$504,MATCH($B32,Productos!$O$5:$O$504,0)))>0,N(INDEX(Productos!$H$5:$H$504,MATCH($B32,Productos!$O$5:$O$504,0))),2*N(F32))-E32))
B33: =IF(17<=COUNTIF(Productos!$O$5:$O$504,">0"),17,"") | C33: =IF($B33="","",INDEX(Productos!$A$5:$A$504,MATCH($B33,Productos!$O$5:$O$504,0))) | D33: =IF($B33="","",INDEX(Productos!$B$5:$B$504,MATCH($B33,Productos!$O$5:$O$504,0))) | E33: =IF($B33="","",INDEX(Productos!$L$5:$L$504,MATCH($B33,Productos!$O$5:$O$504,0))) | F33: =IF($B33="","",INDEX(Productos!$G$5:$G$504,MATCH($B33,Productos!$O$5:$O$504,0))) | G33: =IF($B33="","",INDEX(Productos!$N$5:$N$504,MATCH($B33,Productos!$O$5:$O$504,0))) | H33: =IF($B33="","",MAX(0,IF(N(INDEX(Productos!$H$5:$H$504,MATCH($B33,Productos!$O$5:$O$504,0)))>0,N(INDEX(Productos!$H$5:$H$504,MATCH($B33,Productos!$O$5:$O$504,0))),2*N(F33))-E33))
B34: =IF(18<=COUNTIF(Productos!$O$5:$O$504,">0"),18,"") | C34: =IF($B34="","",INDEX(Productos!$A$5:$A$504,MATCH($B34,Productos!$O$5:$O$504,0))) | D34: =IF($B34="","",INDEX(Productos!$B$5:$B$504,MATCH($B34,Productos!$O$5:$O$504,0))) | E34: =IF($B34="","",INDEX(Productos!$L$5:$L$504,MATCH($B34,Productos!$O$5:$O$504,0))) | F34: =IF($B34="","",INDEX(Productos!$G$5:$G$504,MATCH($B34,Productos!$O$5:$O$504,0))) | G34: =IF($B34="","",INDEX(Productos!$N$5:$N$504,MATCH($B34,Productos!$O$5:$O$504,0))) | H34: =IF($B34="","",MAX(0,IF(N(INDEX(Productos!$H$5:$H$504,MATCH($B34,Productos!$O$5:$O$504,0)))>0,N(INDEX(Productos!$H$5:$H$504,MATCH($B34,Productos!$O$5:$O$504,0))),2*N(F34))-E34))
B35: =IF(19<=COUNTIF(Productos!$O$5:$O$504,">0"),19,"") | C35: =IF($B35="","",INDEX(Productos!$A$5:$A$504,MATCH($B35,Productos!$O$5:$O$504,0))) | D35: =IF($B35="","",INDEX(Productos!$B$5:$B$504,MATCH($B35,Productos!$O$5:$O$504,0))) | E35: =IF($B35="","",INDEX(Productos!$L$5:$L$504,MATCH($B35,Productos!$O$5:$O$504,0))) | F35: =IF($B35="","",INDEX(Productos!$G$5:$G$504,MATCH($B35,Productos!$O$5:$O$504,0))) | G35: =IF($B35="","",INDEX(Productos!$N$5:$N$504,MATCH($B35,Productos!$O$5:$O$504,0))) | H35: =IF($B35="","",MAX(0,IF(N(INDEX(Productos!$H$5:$H$504,MATCH($B35,Productos!$O$5:$O$504,0)))>0,N(INDEX(Productos!$H$5:$H$504,MATCH($B35,Productos!$O$5:$O$504,0))),2*N(F35))-E35))
B36: =IF(20<=COUNTIF(Productos!$O$5:$O$504,">0"),20,"") | C36: =IF($B36="","",INDEX(Productos!$A$5:$A$504,MATCH($B36,Productos!$O$5:$O$504,0))) | D36: =IF($B36="","",INDEX(Productos!$B$5:$B$504,MATCH($B36,Productos!$O$5:$O$504,0))) | E36: =IF($B36="","",INDEX(Productos!$L$5:$L$504,MATCH($B36,Productos!$O$5:$O$504,0))) | F36: =IF($B36="","",INDEX(Productos!$G$5:$G$504,MATCH($B36,Productos!$O$5:$O$504,0))) | G36: =IF($B36="","",INDEX(Productos!$N$5:$N$504,MATCH($B36,Productos!$O$5:$O$504,0))) | H36: =IF($B36="","",MAX(0,IF(N(INDEX(Productos!$H$5:$H$504,MATCH($B36,Productos!$O$5:$O$504,0)))>0,N(INDEX(Productos!$H$5:$H$504,MATCH($B36,Productos!$O$5:$O$504,0))),2*N(F36))-E36))
B37: =IF(21<=COUNTIF(Productos!$O$5:$O$504,">0"),21,"") | C37: =IF($B37="","",INDEX(Productos!$A$5:$A$504,MATCH($B37,Productos!$O$5:$O$504,0))) | D37: =IF($B37="","",INDEX(Productos!$B$5:$B$504,MATCH($B37,Productos!$O$5:$O$504,0))) | E37: =IF($B37="","",INDEX(Productos!$L$5:$L$504,MATCH($B37,Productos!$O$5:$O$504,0))) | F37: =IF($B37="","",INDEX(Productos!$G$5:$G$504,MATCH($B37,Productos!$O$5:$O$504,0))) | G37: =IF($B37="","",INDEX(Productos!$N$5:$N$504,MATCH($B37,Productos!$O$5:$O$504,0))) | H37: =IF($B37="","",MAX(0,IF(N(INDEX(Productos!$H$5:$H$504,MATCH($B37,Productos!$O$5:$O$504,0)))>0,N(INDEX(Productos!$H$5:$H$504,MATCH($B37,Productos!$O$5:$O$504,0))),2*N(F37))-E37))
B38: =IF(22<=COUNTIF(Productos!$O$5:$O$504,">0"),22,"") | C38: =IF($B38="","",INDEX(Productos!$A$5:$A$504,MATCH($B38,Productos!$O$5:$O$504,0))) | D38: =IF($B38="","",INDEX(Productos!$B$5:$B$504,MATCH($B38,Productos!$O$5:$O$504,0))) | E38: =IF($B38="","",INDEX(Productos!$L$5:$L$504,MATCH($B38,Productos!$O$5:$O$504,0))) | F38: =IF($B38="","",INDEX(Productos!$G$5:$G$504,MATCH($B38,Productos!$O$5:$O$504,0))) | G38: =IF($B38="","",INDEX(Productos!$N$5:$N$504,MATCH($B38,Productos!$O$5:$O$504,0))) | H38: =IF($B38="","",MAX(0,IF(N(INDEX(Productos!$H$5:$H$504,MATCH($B38,Productos!$O$5:$O$504,0)))>0,N(INDEX(Productos!$H$5:$H$504,MATCH($B38,Productos!$O$5:$O$504,0))),2*N(F38))-E38))
B39: =IF(23<=COUNTIF(Productos!$O$5:$O$504,">0"),23,"") | C39: =IF($B39="","",INDEX(Productos!$A$5:$A$504,MATCH($B39,Productos!$O$5:$O$504,0))) | D39: =IF($B39="","",INDEX(Productos!$B$5:$B$504,MATCH($B39,Productos!$O$5:$O$504,0))) | E39: =IF($B39="","",INDEX(Productos!$L$5:$L$504,MATCH($B39,Productos!$O$5:$O$504,0))) | F39: =IF($B39="","",INDEX(Productos!$G$5:$G$504,MATCH($B39,Productos!$O$5:$O$504,0))) | G39: =IF($B39="","",INDEX(Productos!$N$5:$N$504,MATCH($B39,Productos!$O$5:$O$504,0))) | H39: =IF($B39="","",MAX(0,IF(N(INDEX(Productos!$H$5:$H$504,MATCH($B39,Productos!$O$5:$O$504,0)))>0,N(INDEX(Productos!$H$5:$H$504,MATCH($B39,Productos!$O$5:$O$504,0))),2*N(F39))-E39))
B40: =IF(24<=COUNTIF(Productos!$O$5:$O$504,">0"),24,"") | C40: =IF($B40="","",INDEX(Productos!$A$5:$A$504,MATCH($B40,Productos!$O$5:$O$504,0))) | D40: =IF($B40="","",INDEX(Productos!$B$5:$B$504,MATCH($B40,Productos!$O$5:$O$504,0))) | E40: =IF($B40="","",INDEX(Productos!$L$5:$L$504,MATCH($B40,Productos!$O$5:$O$504,0))) | F40: =IF($B40="","",INDEX(Productos!$G$5:$G$504,MATCH($B40,Productos!$O$5:$O$504,0))) | G40: =IF($B40="","",INDEX(Productos!$N$5:$N$504,MATCH($B40,Productos!$O$5:$O$504,0))) | H40: =IF($B40="","",MAX(0,IF(N(INDEX(Productos!$H$5:$H$504,MATCH($B40,Productos!$O$5:$O$504,0)))>0,N(INDEX(Productos!$H$5:$H$504,MATCH($B40,Productos!$O$5:$O$504,0))),2*N(F40))-E40))
B41: =IF(25<=COUNTIF(Productos!$O$5:$O$504,">0"),25,"") | C41: =IF($B41="","",INDEX(Productos!$A$5:$A$504,MATCH($B41,Productos!$O$5:$O$504,0))) | D41: =IF($B41="","",INDEX(Productos!$B$5:$B$504,MATCH($B41,Productos!$O$5:$O$504,0))) | E41: =IF($B41="","",INDEX(Productos!$L$5:$L$504,MATCH($B41,Productos!$O$5:$O$504,0))) | F41: =IF($B41="","",INDEX(Productos!$G$5:$G$504,MATCH($B41,Productos!$O$5:$O$504,0))) | G41: =IF($B41="","",INDEX(Productos!$N$5:$N$504,MATCH($B41,Productos!$O$5:$O$504,0))) | H41: =IF($B41="","",MAX(0,IF(N(INDEX(Productos!$H$5:$H$504,MATCH($B41,Productos!$O$5:$O$504,0)))>0,N(INDEX(Productos!$H$5:$H$504,MATCH($B41,Productos!$O$5:$O$504,0))),2*N(F41))-E41))
B42: Muestra hasta 25 artículos. Si tienes más pendientes, filtra la columna Estado en la hoja Productos.

Sheet Productos
A1: Catálogo y existencias
A2: Captura tus artículos en las columnas amarillas. Las grises se calculan solas con los movimientos.
A4: Clave | B4: Descripción | C4: Categoría | D4: Unidad | E4: Ubicación | F4: Costo unitario | G4: Stock mínimo | H4: Stock máximo | I4: Existencia inicial | J4: Entradas | K4: Salidas | L4: Existencia actual | M4: Valor del inventario | N4: Estado | O4: n_compra
A5: P-001 | B5: Cemento gris 50 kg | C5: Materiales | D5: Bulto | E5: Bodega A | F5: 215 | G5: 40 | H5: 120 | I5: 80 | J5: =IF($A5="","",SUMIFS(Movimientos!$F$5:$F$3004,Movimientos!$C$5:$C$3004,$A5,Movimientos!$B$5:$B$3004,"Entrada")) -> 60 | K5: =IF($A5="","",SUMIFS(Movimientos!$F$5:$F$3004,Movimientos!$C$5:$C$3004,$A5,Movimientos!$B$5:$B$3004,"Salida")) -> 85 | L5: =IF($A5="","",N(I5)+J5-K5) -> 55 | M5: =IF($A5="","",L5*N(F5)) -> 11825 | N5: =IF($A5="","",IF(L5<=0,"Agotado",IF(AND(N(G5)>0,L5<=G5),"Reordenar","OK"))) -> OK | O5: =IF(OR(N5="Reordenar",N5="Agotado"),COUNTIF($N$5:N5,"Reordenar")+COUNTIF($N$5:N5,"Agotado"),"")
A6: P-002 | B6: Varilla corrugada 3/8" | C6: Acero | D6: Pieza | E6: Patio | F6: 168 | G6: 100 | H6: 300 | I6: 150 | J6: =IF($A6="","",SUMIFS(Movimientos!$F$5:$F$3004,Movimientos!$C$5:$C$3004,$A6,Movimientos!$B$5:$B$3004,"Entrada")) -> 120 | K6: =IF($A6="","",SUMIFS(Movimientos!$F$5:$F$3004,Movimientos!$C$5:$C$3004,$A6,Movimientos!$B$5:$B$3004,"Salida")) -> 210 | L6: =IF($A6="","",N(I6)+J6-K6) -> 60 | M6: =IF($A6="","",L6*N(F6)) -> 10080 | N6: =IF($A6="","",IF(L6<=0,"Agotado",IF(AND(N(G6)>0,L6<=G6),"Reordenar","OK"))) -> Reordenar | O6: =IF(OR(N6="Reordenar",N6="Agotado"),COUNTIF($N$5:N6,"Reordenar")+COUNTIF($N$5:N6,"Agotado"),"") -> 1
A7: P-003 | B7: Block de concreto 15x20x40 | C7: Materiales | D7: Pieza | E7: Patio | F7: 14.5 | G7: 500 | H7: 2000 | I7: 1200 | J7: =IF($A7="","",SUMIFS(Movimientos!$F$5:$F$3004,Movimientos!$C$5:$C$3004,$A7,Movimientos!$B$5:$B$3004,"Entrada")) -> 0 | K7: =IF($A7="","",SUMIFS(Movimientos!$F$5:$F$3004,Movimientos!$C$5:$C$3004,$A7,Movimientos!$B$5:$B$3004,"Salida")) -> 780 | L7: =IF($A7="","",N(I7)+J7-K7) -> 420 | M7: =IF($A7="","",L7*N(F7)) -> 6090 | N7: =IF($A7="","",IF(L7<=0,"Agotado",IF(AND(N(G7)>0,L7<=G7),"Reordenar","OK"))) -> Reordenar | O7: =IF(OR(N7="Reordenar",N7="Agotado"),COUNTIF($N$5:N7,"Reordenar")+COUNTIF($N$5:N7,"Agotado"),"") -> 2
A8: P-004 | B8: Tubo PVC hidráulico 1/2" | C8: Plomería | D8: Tramo | E8: Bodega B | F8: 62 | G8: 30 | H8: 100 | I8: 45 | J8: =IF($A8="","",SUMIFS(Movimientos!$F$5:$F$3004,Movimientos!$C$5:$C$3004,$A8,Movimientos!$B$5:$B$3004,"Entrada")) -> 40 | K8: =IF($A8="","",SUMIFS(Movimientos!$F$5:$F$3004,Movimientos!$C$5:$C$3004,$A8,Movimientos!$B$5:$B$3004,"Salida")) -> 52 | L8: =IF($A8="","",N(I8)+J8-K8) -> 33 | M8: =IF($A8="","",L8*N(F8)) -> 2046 | N8: =IF($A8="","",IF(L8<=0,"Agotado",IF(AND(N(G8)>0,L8<=G8),"Reordenar","OK"))) -> OK | O8: =IF(OR(N8="Reordenar",N8="Agotado"),COUNTIF($N$5:N8,"Reordenar")+COUNTIF($N$5:N8,"Agotado"),"")
A9: P-005 | B9: Pintura vinílica blanca 19 L | C9: Pinturas | D9: Cubeta | E9: Bodega B | F9: 1150 | G9: 5 | H9: 20 | I9: 8 | J9: =IF($A9="","",SUMIFS(Movimientos!$F$5:$F$3004,Movimientos!$C$5:$C$3004,$A9,Movimientos!$B$5:$B$3004,"Entrada")) -> 0 | K9: =IF($A9="","",SUMIFS(Movimientos!$F$5:$F$3004,Movimientos!$C$5:$C$3004,$A9,Movimientos!$B$5:$B$3004,"Salida")) -> 4 | L9: =IF($A9="","",N(I9)+J9-K9) -> 4 | M9: =IF($A9="","",L9*N(F9)) -> 4600 | N9: =IF($A9="","",IF(L9<=0,"Agotado",IF(AND(N(G9)>0,L9<=G9),"Reordenar","OK"))) -> Reordenar | O9: =IF(OR(N9="Reordenar",N9="Agotado"),COUNTIF($N$5:N9,"Reordenar")+COUNTIF($N$5:N9,"Agotado"),"") -> 3
A10: P-006 | B10: Alambre recocido | C10: Acero | D10: Kg | E10: Bodega A | F10: 38 | G10: 50 | H10: 200 | I10: 60 | J10: =IF($A10="","",SUMIFS(Movimientos!$F$5:$F$3004,Movimientos!$C$5:$C$3004,$A10,Movimientos!$B$5:$B$3004,"Entrada")) -> 0 | K10: =IF($A10="","",SUMIFS(Movimientos!$F$5:$F$3004,Movimientos!$C$5:$C$3004,$A10,Movimientos!$B$5:$B$3004,"Salida")) -> 25 | L10: =IF($A10="","",N(I10)+J10-K10) -> 35 | M10: =IF($A10="","",L10*N(F10)) -> 1330 | N10: =IF($A10="","",IF(L10<=0,"Agotado",IF(AND(N(G10)>0,L10<=G10),"Reordenar","OK"))) -> Reordenar | O10: =IF(OR(N10="Reordenar",N10="Agotado"),COUNTIF($N$5:N10,"Reordenar")+COUNTIF($N$5:N10,"Agotado"),"") -> 4
A11: P-007 | B11: Cable THW calibre 12 | C11: Eléctrico | D11: Rollo 100 m | E11: Bodega B | F11: 980 | G11: 4 | H11: 12 | I11: 3 | J11: =IF($A11="","",SUMIFS(Movimientos!$F$5:$F$3004,Movimientos!$C$5:$C$3004,$A11,Movimientos!$B$5:$B$3004,"Entrada")) -> 0 | K11: =IF($A11="","",SUMIFS(Movimientos!$F$5:$F$3004,Movimientos!$C$5:$C$3004,$A11,Movimientos!$B$5:$B$3004,"Salida")) -> 3 | L11: =IF($A11="","",N(I11)+J11-K11) -> 0 | M11: =IF($A11="","",L11*N(F11)) -> 0 | N11: =IF($A11="","",IF(L11<=0,"Agotado",IF(AND(N(G11)>0,L11<=G11),"Reordenar","OK"))) -> Agotado | O11: =IF(OR(N11="Reordenar",N11="Agotado"),COUNTIF($N$5:N11,"Reordenar")+COUNTIF($N$5:N11,"Agotado"),"") -> 5
A12: P-008 | B12: Tornillo para tablaroca 1" | C12: Ferretería | D12: Caja 1000 | E12: Bodega A | F12: 145 | G12: 10 | H12: 40 | I12: 22 | J12: =IF($A12="","",SUMIFS(Movimientos!$F$5:$F$3004,Movimientos!$C$5:$C$3004,$A12,Movimientos!$B$5:$B$3004,"Entrada")) -> 10 | K12: =IF($A12="","",SUMIFS(Movimientos!$F$5:$F$3004,Movimientos!$C$5:$C$3004,$A12,Movimientos!$B$5:$B$3004,"Salida")) -> 14 | L12: =IF($A12="","",N(I12)+J12-K12) -> 18 | M12: =IF($A12="","",L12*N(F12)) -> 2610 | N12: =IF($A12="","",IF(L12<=0,"Agotado",IF(AND(N(G12)>0,L12<=G12),"Reordenar","OK"))) -> OK | O12: =IF(OR(N12="Reordenar",N12="Agotado"),COUNTIF($N$5:N12,"Reordenar")+COUNTIF($N$5:N12,"Agotado"),"")
J13: =IF($A13="","",SUMIFS(Movimientos!$F$5:$F$3004,Movimientos!$C$5:$C$3004,$A13,Movimientos!$B$5:$B$3004,"Entrada")) | K13: =IF($A13="","",SUMIFS(Movimientos!$F$5:$F$3004,Movimientos!$C$5:$C$3004,$A13,Movimientos!$B$5:$B$3004,"Salida")) | L13: =IF($A13="","",N(I13)+J13-K13) | M13: =IF($A13="","",L13*N(F13)) | N13: =IF($A13="","",IF(L13<=0,"Agotado",IF(AND(N(G13)>0,L13<=G13),"Reordenar","OK"))) | O13: =IF(OR(N13="Reordenar",N13="Agotado"),COUNTIF($N$5:N13,"Reordenar")+COUNTIF($N$5:N13,"Agotado"),"")
J14: =IF($A14="","",SUMIFS(Movimientos!$F$5:$F$3004,Movimientos!$C$5:$C$3004,$A14,Movimientos!$B$5:$B$3004,"Entrada")) | K14: =IF($A14="","",SUMIFS(Movimientos!$F$5:$F$3004,Movimientos!$C$5:$C$3004,$A14,Movimientos!$B$5:$B$3004,"Salida")) | L14: =IF($A14="","",N(I14)+J14-K14) | M14: =IF($A14="","",L14*N(F14)) | N14: =IF($A14="","",IF(L14<=0,"Agotado",IF(AND(N(G14)>0,L14<=G14),"Reordenar","OK"))) | O14: =IF(OR(N14="Reordenar",N14="Agotado"),COUNTIF($N$5:N14,"Reordenar")+COUNTIF($N$5:N14,"Agotado"),"")
J15: =IF($A15="","",SUMIFS(Movimientos!$F$5:$F$3004,Movimientos!$C$5:$C$3004,$A15,Movimientos!$B$5:$B$3004,"Entrada")) | K15: =IF($A15="","",SUMIFS(Movimientos!$F$5:$F$3004,Movimientos!$C$5:$C$3004,$A15,Movimientos!$B$5:$B$3004,"Salida")) | L15: =IF($A15="","",N(I15)+J15-K15) | M15: =IF($A15="","",L15*N(F15)) | N15: =IF($A15="","",IF(L15<=0,"Agotado",IF(AND(N(G15)>0,L15<=G15),"Reordenar","OK"))) | O15: =IF(OR(N15="Reordenar",N15="Agotado"),COUNTIF($N$5:N15,"Reordenar")+COUNTIF($N$5:N15,"Agotado"),"")
J16: =IF($A16="","",SUMIFS(Movimientos!$F$5:$F$3004,Movimientos!$C$5:$C$3004,$A16,Movimientos!$B$5:$B$3004,"Entrada")) | K16: =IF($A16="","",SUMIFS(Movimientos!$F$5:$F$3004,Movimientos!$C$5:$C$3004,$A16,Movimientos!$B$5:$B$3004,"Salida")) | L16: =IF($A16="","",N(I16)+J16-K16) | M16: =IF($A16="","",L16*N(F16)) | N16: =IF($A16="","",IF(L16<=0,"Agotado",IF(AND(N(G16)>0,L16<=G16),"Reordenar","OK"))) | O16: =IF(OR(N16="Reordenar",N16="Agotado"),COUNTIF($N$5:N16,"Reordenar")+COUNTIF($N$5:N16,"Agotado"),"")
J17: =IF($A17="","",SUMIFS(Movimientos!$F$5:$F$3004,Movimientos!$C$5:$C$3004,$A17,Movimientos!$B$5:$B$3004,"Entrada")) | K17: =IF($A17="","",SUMIFS(Movimientos!$F$5:$F$3004,Movimientos!$C$5:$C$3004,$A17,Movimientos!$B$5:$B$3004,"Salida")) | L17: =IF($A17="","",N(I17)+J17-K17) | M17: =IF($A17="","",L17*N(F17)) | N17: =IF($A17="","",IF(L17<=0,"Agotado",IF(AND(N(G17)>0,L17<=G17),"Reordenar","OK"))) | O17: =IF(OR(N17="Reordenar",N17="Agotado"),COUNTIF($N$5:N17,"Reordenar")+COUNTIF($N$5:N17,"Agotado"),"")
J18: =IF($A18="","",SUMIFS(Movimientos!$F$5:$F$3004,Movimientos!$C$5:$C$3004,$A18,Movimientos!$B$5:$B$3004,"Entrada")) | K18: =IF($A18="","",SUMIFS(Movimientos!$F$5:$F$3004,Movimientos!$C$5:$C$3004,$A18,Movimientos!$B$5:$B$3004,"Salida")) | L18: =IF($A18="","",N(I18)+J18-K18) | M18: =IF($A18="","",L18*N(F18)) | N18: =IF($A18="","",IF(L18<=0,"Agotado",IF(AND(N(G18)>0,L18<=G18),"Reordenar","OK"))) | O18: =IF(OR(N18="Reordenar",N18="Agotado"),COUNTIF($N$5:N18,"Reordenar")+COUNTIF($N$5:N18,"Agotado"),"")
J19: =IF($A19="","",SUMIFS(Movimientos!$F$5:$F$3004,Movimientos!$C$5:$C$3004,$A19,Movimientos!$B$5:$B$3004,"Entrada")) | K19: =IF($A19="","",SUMIFS(Movimientos!$F$5:$F$3004,Movimientos!$C$5:$C$3004,$A19,Movimientos!$B$5:$B$3004,"Salida")) | L19: =IF($A19="","",N(I19)+J19-K19) | M19: =IF($A19="","",L19*N(F19)) | N19: =IF($A19="","",IF(L19<=0,"Agotado",IF(AND(N(G19)>0,L19<=G19),"Reordenar","OK"))) | O19: =IF(OR(N19="Reordenar",N19="Agotado"),COUNTIF($N$5:N19,"Reordenar")+COUNTIF($N$5:N19,"Agotado"),"")
J20: =IF($A20="","",SUMIFS(Movimientos!$F$5:$F$3004,Movimientos!$C$5:$C$3004,$A20,Movimientos!$B$5:$B$3004,"Entrada")) | K20: =IF($A20="","",SUMIFS(Movimientos!$F$5:$F$3004,Movimientos!$C$5:$C$3004,$A20,Movimientos!$B$5:$B$3004,"Salida")) | L20: =IF($A20="","",N(I20)+J20-K20) | M20: =IF($A20="","",L20*N(F20)) | N20: =IF($A20="","",IF(L20<=0,"Agotado",IF(AND(N(G20)>0,L20<=G20),"Reordenar","OK"))) | O20: =IF(OR(N20="Reordenar",N20="Agotado"),COUNTIF($N$5:N20,"Reordenar")+COUNTIF($N$5:N20,"Agotado"),"")
J21: =IF($A21="","",SUMIFS(Movimientos!$F$5:$F$3004,Movimientos!$C$5:$C$3004,$A21,Movimientos!$B$5:$B$3004,"Entrada")) | K21: =IF($A21="","",SUMIFS(Movimientos!$F$5:$F$3004,Movimientos!$C$5:$C$3004,$A21,Movimientos!$B$5:$B$3004,"Salida")) | L21: =IF($A21="","",N(I21)+J21-K21) | M21: =IF($A21="","",L21*N(F21)) | N21: =IF($A21="","",IF(L21<=0,"Agotado",IF(AND(N(G21)>0,L21<=G21),"Reordenar","OK"))) | O21: =IF(OR(N21="Reordenar",N21="Agotado"),COUNTIF($N$5:N21,"Reordenar")+COUNTIF($N$5:N21,"Agotado"),"")
J22: =IF($A22="","",SUMIFS(Movimientos!$F$5:$F$3004,Movimientos!$C$5:$C$3004,$A22,Movimientos!$B$5:$B$3004,"Entrada")) | K22: =IF($A22="","",SUMIFS(Movimientos!$F$5:$F$3004,Movimientos!$C$5:$C$3004,$A22,Movimientos!$B$5:$B$3004,"Salida")) | L22: =IF($A22="","",N(I22)+J22-K22) | M22: =IF($A22="","",L22*N(F22)) | N22: =IF($A22="","",IF(L22<=0,"Agotado",IF(AND(N(G22)>0,L22<=G22),"Reordenar","OK"))) | O22: =IF(OR(N22="Reordenar",N22="Agotado"),COUNTIF($N$5:N22,"Reordenar")+COUNTIF($N$5:N22,"Agotado"),"")
J23: =IF($A23="","",SUMIFS(Movimientos!$F$5:$F$3004,Movimientos!$C$5:$C$3004,$A23,Movimientos!$B$5:$B$3004,"Entrada")) | K23: =IF($A23="","",SUMIFS(Movimientos!$F$5:$F$3004,Movimientos!$C$5:$C$3004,$A23,Movimientos!$B$5:$B$3004,"Salida")) | L23: =IF($A23="","",N(I23)+J23-K23) | M23: =IF($A23="","",L23*N(F23)) | N23: =IF($A23="","",IF(L23<=0,"Agotado",IF(AND(N(G23)>0,L23<=G23),"Reordenar","OK"))) | O23: =IF(OR(N23="Reordenar",N23="Agotado"),COUNTIF($N$5:N23,"Reordenar")+COUNTIF($N$5:N23,"Agotado"),"")
J24: =IF($A24="","",SUMIFS(Movimientos!$F$5:$F$3004,Movimientos!$C$5:$C$3004,$A24,Movimientos!$B$5:$B$3004,"Entrada")) | K24: =IF($A24="","",SUMIFS(Movimientos!$F$5:$F$3004,Movimientos!$C$5:$C$3004,$A24,Movimientos!$B$5:$B$3004,"Salida")) | L24: =IF($A24="","",N(I24)+J24-K24) | M24: =IF($A24="","",L24*N(F24)) | N24: =IF($A24="","",IF(L24<=0,"Agotado",IF(AND(N(G24)>0,L24<=G24),"Reordenar","OK"))) | O24: =IF(OR(N24="Reordenar",N24="Agotado"),COUNTIF($N$5:N24,"Reordenar")+COUNTIF($N$5:N24,"Agotado"),"")
... J504: =IF($A504="","",SUMIFS(Movimientos!$F$5:$F$3004,Movimientos!$C$5:$C$3004,$A504,Movimientos!$B$5:$B$3004,"Entrada")) | K504: =IF($A504="","",SUMIFS(Movimientos!$F$5:$F$3004,Movimientos!$C$5:$C$3004,$A504,Movimientos!$B$5:$B$3004,"Salida")) | L504: =IF($A504="","",N(I504)+J504-K504) | M504: =IF($A504="","",L504*N(F504)) | N504: =IF($A504="","",IF(L504<=0,"Agotado",IF(AND(N(G504)>0,L504<=G504),"Reordenar","OK"))) | O504: =IF(OR(N504="Reordenar",N504="Agotado"),COUNTIF($N$5:N504,"Reordenar")+COUNTIF($N$5:N504,"Agotado"),"")

Sheet Movimientos
A1: Entradas y salidas
A2: Una fila por movimiento, en orden de fecha. Tipo: Entrada o Salida. La clave debe existir en Productos.
A4: Fecha | B4: Tipo | C4: Clave | D4: Descripción | E4: Unidad | F4: Cantidad | G4: Costo unitario | H4: Importe | I4: Existencia después | J4: Referencia | K4: Responsable | L4: Notas | M4: n_kardex
A5: 46296 | B5: Entrada | C5: P-001 | D5: =IF($C5="","",IFERROR(INDEX(Productos!$B$5:$B$504,MATCH($C5,Productos!$A$5:$A$504,0)),"Clave no existe")) -> Cemento gris 50 kg | E5: =IF($C5="","",IFERROR(INDEX(Productos!$D$5:$D$504,MATCH($C5,Productos!$A$5:$A$504,0)),"")) -> Bulto | F5: 60 | G5: =IF($C5="","",IFERROR(INDEX(Productos!$F$5:$F$504,MATCH($C5,Productos!$A$5:$A$504,0)),0)) -> 215 | H5: =IF(OR($C5="",$F5=""),"",F5*G5) -> 12900 | I5: =IF(OR($C5="",$F5=""),"",IFERROR(INDEX(Productos!$I$5:$I$504,MATCH($C5,Productos!$A$5:$A$504,0)),0)+SUMIFS($F$5:$F5,$C$5:$C5,$C5,$B$5:$B5,"Entrada")-SUMIFS($F$5:$F5,$C$5:$C5,$C5,$B$5:$B5,"Salida")) -> 140 | J5: Factura A-1182 | K5: Almacén | M5: =IF(AND($C5<>"",$C5=Kardex!$C$4),COUNTIF($C$5:$C5,Kardex!$C$4),"") -> 1
A6: 46297 | B6: Salida | C6: P-001 | D6: =IF($C6="","",IFERROR(INDEX(Productos!$B$5:$B$504,MATCH($C6,Productos!$A$5:$A$504,0)),"Clave no existe")) -> Cemento gris 50 kg | E6: =IF($C6="","",IFERROR(INDEX(Productos!$D$5:$D$504,MATCH($C6,Productos!$A$5:$A$504,0)),"")) -> Bulto | F6: 35 | G6: =IF($C6="","",IFERROR(INDEX(Productos!$F$5:$F$504,MATCH($C6,Productos!$A$5:$A$504,0)),0)) -> 215 | H6: =IF(OR($C6="",$F6=""),"",F6*G6) -> 7525 | I6: =IF(OR($C6="",$F6=""),"",IFERROR(INDEX(Productos!$I$5:$I$504,MATCH($C6,Productos!$A$5:$A$504,0)),0)+SUMIFS($F$5:$F6,$C$5:$C6,$C6,$B$5:$B6,"Entrada")-SUMIFS($F$5:$F6,$C$5:$C6,$C6,$B$5:$B6,"Salida")) -> 105 | J6: Pedido 0451 | K6: Ventas | M6: =IF(AND($C6<>"",$C6=Kardex!$C$4),COUNTIF($C$5:$C6,Kardex!$C$4),"") -> 2
A7: 46298 | B7: Salida | C7: P-003 | D7: =IF($C7="","",IFERROR(INDEX(Productos!$B$5:$B$504,MATCH($C7,Productos!$A$5:$A$504,0)),"Clave no existe")) -> Block de concreto 15x20x40 | E7: =IF($C7="","",IFERROR(INDEX(Productos!$D$5:$D$504,MATCH($C7,Productos!$A$5:$A$504,0)),"")) -> Pieza | F7: 400 | G7: =IF($C7="","",IFERROR(INDEX(Productos!$F$5:$F$504,MATCH($C7,Productos!$A$5:$A$504,0)),0)) -> 14.5 | H7: =IF(OR($C7="",$F7=""),"",F7*G7) -> 5800 | I7: =IF(OR($C7="",$F7=""),"",IFERROR(INDEX(Productos!$I$5:$I$504,MATCH($C7,Productos!$A$5:$A$504,0)),0)+SUMIFS($F$5:$F7,$C$5:$C7,$C7,$B$5:$B7,"Entrada")-SUMIFS($F$5:$F7,$C$5:$C7,$C7,$B$5:$B7,"Salida")) -> 800 | J7: Pedido 0452 | K7: Ventas | M7: =IF(AND($C7<>"",$C7=Kardex!$C$4),COUNTIF($C$5:$C7,Kardex!$C$4),"")
A8: 46301 | B8: Entrada | C8: P-002 | D8: =IF($C8="","",IFERROR(INDEX(Productos!$B$5:$B$504,MATCH($C8,Productos!$A$5:$A$504,0)),"Clave no existe")) -> Varilla corrugada 3/8" | E8: =IF($C8="","",IFERROR(INDEX(Productos!$D$5:$D$504,MATCH($C8,Productos!$A$5:$A$504,0)),"")) -> Pieza | F8: 120 | G8: =IF($C8="","",IFERROR(INDEX(Productos!$F$5:$F$504,MATCH($C8,Productos!$A$5:$A$504,0)),0)) -> 168 | H8: =IF(OR($C8="",$F8=""),"",F8*G8) -> 20160 | I8: =IF(OR($C8="",$F8=""),"",IFERROR(INDEX(Productos!$I$5:$I$504,MATCH($C8,Productos!$A$5:$A$504,0)),0)+SUMIFS($F$5:$F8,$C$5:$C8,$C8,$B$5:$B8,"Entrada")-SUMIFS($F$5:$F8,$C$5:$C8,$C8,$B$5:$B8,"Salida")) -> 270 | J8: Factura B-0907 | K8: Almacén | M8: =IF(AND($C8<>"",$C8=Kardex!$C$4),COUNTIF($C$5:$C8,Kardex!$C$4),"")
A9: 46302 | B9: Salida | C9: P-002 | D9: =IF($C9="","",IFERROR(INDEX(Productos!$B$5:$B$504,MATCH($C9,Productos!$A$5:$A$504,0)),"Clave no existe")) -> Varilla corrugada 3/8" | E9: =IF($C9="","",IFERROR(INDEX(Productos!$D$5:$D$504,MATCH($C9,Productos!$A$5:$A$504,0)),"")) -> Pieza | F9: 210 | G9: =IF($C9="","",IFERROR(INDEX(Productos!$F$5:$F$504,MATCH($C9,Productos!$A$5:$A$504,0)),0)) -> 168 | H9: =IF(OR($C9="",$F9=""),"",F9*G9) -> 35280 | I9: =IF(OR($C9="",$F9=""),"",IFERROR(INDEX(Productos!$I$5:$I$504,MATCH($C9,Productos!$A$5:$A$504,0)),0)+SUMIFS($F$5:$F9,$C$5:$C9,$C9,$B$5:$B9,"Entrada")-SUMIFS($F$5:$F9,$C$5:$C9,$C9,$B$5:$B9,"Salida")) -> 60 | J9: Pedido 0458 | K9: Ventas | M9: =IF(AND($C9<>"",$C9=Kardex!$C$4),COUNTIF($C$5:$C9,Kardex!$C$4),"")
A10: 46304 | B10: Salida | C10: P-005 | D10: =IF($C10="","",IFERROR(INDEX(Productos!$B$5:$B$504,MATCH($C10,Productos!$A$5:$A$504,0)),"Clave no existe")) -> Pintura vinílica blanca 19 L | E10: =IF($C10="","",IFERROR(INDEX(Productos!$D$5:$D$504,MATCH($C10,Productos!$A$5:$A$504,0)),"")) -> Cubeta | F10: 4 | G10: =IF($C10="","",IFERROR(INDEX(Productos!$F$5:$F$504,MATCH($C10,Productos!$A$5:$A$504,0)),0)) -> 1150 | H10: =IF(OR($C10="",$F10=""),"",F10*G10) -> 4600 | I10: =IF(OR($C10="",$F10=""),"",IFERROR(INDEX(Productos!$I$5:$I$504,MATCH($C10,Productos!$A$5:$A$504,0)),0)+SUMIFS($F$5:$F10,$C$5:$C10,$C10,$B$5:$B10,"Entrada")-SUMIFS($F$5:$F10,$C$5:$C10,$C10,$B$5:$B10,"Salida")) -> 4 | J10: Pedido 0461 | K10: Ventas | M10: =IF(AND($C10<>"",$C10=Kardex!$C$4),COUNTIF($C$5:$C10,Kardex!$C$4),"")
A11: 46305 | B11: Salida | C11: P-001 | D11: =IF($C11="","",IFERROR(INDEX(Productos!$B$5:$B$504,MATCH($C11,Productos!$A$5:$A$504,0)),"Clave no existe")) -> Cemento gris 50 kg | E11: =IF($C11="","",IFERROR(INDEX(Productos!$D$5:$D$504,MATCH($C11,Productos!$A$5:$A$504,0)),"")) -> Bulto | F11: 50 | G11: =IF($C11="","",IFERROR(INDEX(Productos!$F$5:$F$504,MATCH($C11,Productos!$A$5:$A$504,0)),0)) -> 215 | H11: =IF(OR($C11="",$F11=""),"",F11*G11) -> 10750 | I11: =IF(OR($C11="",$F11=""),"",IFERROR(INDEX(Productos!$I$5:$I$504,MATCH($C11,Productos!$A$5:$A$504,0)),0)+SUMIFS($F$5:$F11,$C$5:$C11,$C11,$B$5:$B11,"Entrada")-SUMIFS($F$5:$F11,$C$5:$C11,$C11,$B$5:$B11,"Salida")) -> 55 | J11: Pedido 0463 | K11: Ventas | M11: =IF(AND($C11<>"",$C11=Kardex!$C$4),COUNTIF($C$5:$C11,Kardex!$C$4),"") -> 3
A12: 46308 | B12: Entrada | C12: P-004 | D12: =IF($C12="","",IFERROR(INDEX(Productos!$B$5:$B$504,MATCH($C12,Productos!$A$5:$A$504,0)),"Clave no existe")) -> Tubo PVC hidráulico 1/2" | E12: =IF($C12="","",IFERROR(INDEX(Productos!$D$5:$D$504,MATCH($C12,Productos!$A$5:$A$504,0)),"")) -> Tramo | F12: 40 | G12: =IF($C12="","",IFERROR(INDEX(Productos!$F$5:$F$504,MATCH($C12,Productos!$A$5:$A$504,0)),0)) -> 62 | H12: =IF(OR($C12="",$F12=""),"",F12*G12) -> 2480 | I12: =IF(OR($C12="",$F12=""),"",IFERROR(INDEX(Productos!$I$5:$I$504,MATCH($C12,Productos!$A$5:$A$504,0)),0)+SUMIFS($F$5:$F12,$C$5:$C12,$C12,$B$5:$B12,"Entrada")-SUMIFS($F$5:$F12,$C$5:$C12,$C12,$B$5:$B12,"Salida")) -> 85 | J12: Factura C-2210 | K12: Almacén | M12: =IF(AND($C12<>"",$C12=Kardex!$C$4),COUNTIF($C$5:$C12,Kardex!$C$4),"")
A13: 46309 | B13: Salida | C13: P-004 | D13: =IF($C13="","",IFERROR(INDEX(Productos!$B$5:$B$504,MATCH($C13,Productos!$A$5:$A$504,0)),"Clave no existe")) -> Tubo PVC hidráulico 1/2" | E13: =IF($C13="","",IFERROR(INDEX(Productos!$D$5:$D$504,MATCH($C13,Productos!$A$5:$A$504,0)),"")) -> Tramo | F13: 52 | G13: =IF($C13="","",IFERROR(INDEX(Productos!$F$5:$F$504,MATCH($C13,Productos!$A$5:$A$504,0)),0)) -> 62 | H13: =IF(OR($C13="",$F13=""),"",F13*G13) -> 3224 | I13: =IF(OR($C13="",$F13=""),"",IFERROR(INDEX(Productos!$I$5:$I$504,MATCH($C13,Productos!$A$5:$A$504,0)),0)+SUMIFS($F$5:$F13,$C$5:$C13,$C13,$B$5:$B13,"Entrada")-SUMIFS($F$5:$F13,$C$5:$C13,$C13,$B$5:$B13,"Salida")) -> 33 | J13: Pedido 0470 | K13: Ventas | M13: =IF(AND($C13<>"",$C13=Kardex!$C$4),COUNTIF($C$5:$C13,Kardex!$C$4),"")
A14: 46311 | B14: Salida | C14: P-007 | D14: =IF($C14="","",IFERROR(INDEX(Productos!$B$5:$B$504,MATCH($C14,Productos!$A$5:$A$504,0)),"Clave no existe")) -> Cable THW calibre 12 | E14: =IF($C14="","",IFERROR(INDEX(Productos!$D$5:$D$504,MATCH($C14,Productos!$A$5:$A$504,0)),"")) -> Rollo 100 m | F14: 3 | G14: =IF($C14="","",IFERROR(INDEX(Productos!$F$5:$F$504,MATCH($C14,Productos!$A$5:$A$504,0)),0)) -> 980 | H14: =IF(OR($C14="",$F14=""),"",F14*G14) -> 2940 | I14: =IF(OR($C14="",$F14=""),"",IFERROR(INDEX(Productos!$I$5:$I$504,MATCH($C14,Productos!$A$5:$A$504,0)),0)+SUMIFS($F$5:$F14,$C$5:$C14,$C14,$B$5:$B14,"Entrada")-SUMIFS($F$5:$F14,$C$5:$C14,$C14,$B$5:$B14,"Salida")) -> 0 | J14: Pedido 0474 | K14: Ventas | M14: =IF(AND($C14<>"",$C14=Kardex!$C$4),COUNTIF($C$5:$C14,Kardex!$C$4),"")
A15: 46315 | B15: Salida | C15: P-006 | D15: =IF($C15="","",IFERROR(INDEX(Productos!$B$5:$B$504,MATCH($C15,Productos!$A$5:$A$504,0)),"Clave no existe")) -> Alambre recocido | E15: =IF($C15="","",IFERROR(INDEX(Productos!$D$5:$D$504,MATCH($C15,Productos!$A$5:$A$504,0)),"")) -> Kg | F15: 25 | G15: =IF($C15="","",IFERROR(INDEX(Productos!$F$5:$F$504,MATCH($C15,Productos!$A$5:$A$504,0)),0)) -> 38 | H15: =IF(OR($C15="",$F15=""),"",F15*G15) -> 950 | I15: =IF(OR($C15="",$F15=""),"",IFERROR(INDEX(Productos!$I$5:$I$504,MATCH($C15,Productos!$A$5:$A$504,0)),0)+SUMIFS($F$5:$F15,$C$5:$C15,$C15,$B$5:$B15,"Entrada")-SUMIFS($F$5:$F15,$C$5:$C15,$C15,$B$5:$B15,"Salida")) -> 35 | J15: Pedido 0480 | K15: Ventas | M15: =IF(AND($C15<>"",$C15=Kardex!$C$4),COUNTIF($C$5:$C15,Kardex!$C$4),"")
A16: 46316 | B16: Entrada | C16: P-008 | D16: =IF($C16="","",IFERROR(INDEX(Productos!$B$5:$B$504,MATCH($C16,Productos!$A$5:$A$504,0)),"Clave no existe")) -> Tornillo para tablaroca 1" | E16: =IF($C16="","",IFERROR(INDEX(Productos!$D$5:$D$504,MATCH($C16,Productos!$A$5:$A$504,0)),"")) -> Caja 1000 | F16: 10 | G16: =IF($C16="","",IFERROR(INDEX(Productos!$F$5:$F$504,MATCH($C16,Productos!$A$5:$A$504,0)),0)) -> 145 | H16: =IF(OR($C16="",$F16=""),"",F16*G16) -> 1450 | I16: =IF(OR($C16="",$F16=""),"",IFERROR(INDEX(Productos!$I$5:$I$504,MATCH($C16,Productos!$A$5:$A$504,0)),0)+SUMIFS($F$5:$F16,$C$5:$C16,$C16,$B$5:$B16,"Entrada")-SUMIFS($F$5:$F16,$C$5:$C16,$C16,$B$5:$B16,"Salida")) -> 32 | J16: Factura A-1240 | K16: Almacén | M16: =IF(AND($C16<>"",$C16=Kardex!$C$4),COUNTIF($C$5:$C16,Kardex!$C$4),"")
... A18: 46322 | B18: Salida | C18: P-003 | D18: =IF($C18="","",IFERROR(INDEX(Productos!$B$5:$B$504,MATCH($C18,Productos!$A$5:$A$504,0)),"Clave no existe")) -> Block de concreto 15x20x40 | E18: =IF($C18="","",IFERROR(INDEX(Productos!$D$5:$D$504,MATCH($C18,Productos!$A$5:$A$504,0)),"")) -> Pieza | F18: 380 | G18: =IF($C18="","",IFERROR(INDEX(Productos!$F$5:$F$504,MATCH($C18,Productos!$A$5:$A$504,0)),0)) -> 14.5 | H18: =IF(OR($C18="",$F18=""),"",F18*G18) -> 5510 | I18: =IF(OR($C18="",$F18=""),"",IFERROR(INDEX(Productos!$I$5:$I$504,MATCH($C18,Productos!$A$5:$A$504,0)),0)+SUMIFS($F$5:$F18,$C$5:$C18,$C18,$B$5:$B18,"Entrada")-SUMIFS($F$5:$F18,$C$5:$C18,$C18,$B$5:$B18,"Salida")) -> 420 | J18: Pedido 0491 | K18: Ventas | M18: =IF(AND($C18<>"",$C18=Kardex!$C$4),COUNTIF($C$5:$C18,Kardex!$C$4),"")
D19: =IF($C19="","",IFERROR(INDEX(Productos!$B$5:$B$504,MATCH($C19,Productos!$A$5:$A$504,0)),"Clave no existe")) | E19: =IF($C19="","",IFERROR(INDEX(Productos!$D$5:$D$504,MATCH($C19,Productos!$A$5:$A$504,0)),"")) | G19: =IF($C19="","",IFERROR(INDEX(Productos!$F$5:$F$504,MATCH($C19,Productos!$A$5:$A$504,0)),0)) | H19: =IF(OR($C19="",$F19=""),"",F19*G19) | I19: =IF(OR($C19="",$F19=""),"",IFERROR(INDEX(Productos!$I$5:$I$504,MATCH($C19,Productos!$A$5:$A$504,0)),0)+SUMIFS($F$5:$F19,$C$5:$C19,$C19,$B$5:$B19,"Entrada")-SUMIFS($F$5:$F19,$C$5:$C19,$C19,$B$5:$B19,"Salida")) | M19: =IF(AND($C19<>"",$C19=Kardex!$C$4),COUNTIF($C$5:$C19,Kardex!$C$4),"")
D20: =IF($C20="","",IFERROR(INDEX(Productos!$B$5:$B$504,MATCH($C20,Productos!$A$5:$A$504,0)),"Clave no existe")) | E20: =IF($C20="","",IFERROR(INDEX(Productos!$D$5:$D$504,MATCH($C20,Productos!$A$5:$A$504,0)),"")) | G20: =IF($C20="","",IFERROR(INDEX(Productos!$F$5:$F$504,MATCH($C20,Productos!$A$5:$A$504,0)),0)) | H20: =IF(OR($C20="",$F20=""),"",F20*G20) | I20: =IF(OR($C20="",$F20=""),"",IFERROR(INDEX(Productos!$I$5:$I$504,MATCH($C20,Productos!$A$5:$A$504,0)),0)+SUMIFS($F$5:$F20,$C$5:$C20,$C20,$B$5:$B20,"Entrada")-SUMIFS($F$5:$F20,$C$5:$C20,$C20,$B$5:$B20,"Salida")) | M20: =IF(AND($C20<>"",$C20=Kardex!$C$4),COUNTIF($C$5:$C20,Kardex!$C$4),"")
D21: =IF($C21="","",IFERROR(INDEX(Productos!$B$5:$B$504,MATCH($C21,Productos!$A$5:$A$504,0)),"Clave no existe")) | E21: =IF($C21="","",IFERROR(INDEX(Productos!$D$5:$D$504,MATCH($C21,Productos!$A$5:$A$504,0)),"")) | G21: =IF($C21="","",IFERROR(INDEX(Productos!$F$5:$F$504,MATCH($C21,Productos!$A$5:$A$504,0)),0)) | H21: =IF(OR($C21="",$F21=""),"",F21*G21) | I21: =IF(OR($C21="",$F21=""),"",IFERROR(INDEX(Productos!$I$5:$I$504,MATCH($C21,Productos!$A$5:$A$504,0)),0)+SUMIFS($F$5:$F21,$C$5:$C21,$C21,$B$5:$B21,"Entrada")-SUMIFS($F$5:$F21,$C$5:$C21,$C21,$B$5:$B21,"Salida")) | M21: =IF(AND($C21<>"",$C21=Kardex!$C$4),COUNTIF($C$5:$C21,Kardex!$C$4),"")
D22: =IF($C22="","",IFERROR(INDEX(Productos!$B$5:$B$504,MATCH($C22,Productos!$A$5:$A$504,0)),"Clave no existe")) | E22: =IF($C22="","",IFERROR(INDEX(Productos!$D$5:$D$504,MATCH($C22,Productos!$A$5:$A$504,0)),"")) | G22: =IF($C22="","",IFERROR(INDEX(Productos!$F$5:$F$504,MATCH($C22,Productos!$A$5:$A$504,0)),0)) | H22: =IF(OR($C22="",$F22=""),"",F22*G22) | I22: =IF(OR($C22="",$F22=""),"",IFERROR(INDEX(Productos!$I$5:$I$504,MATCH($C22,Productos!$A$5:$A$504,0)),0)+SUMIFS($F$5:$F22,$C$5:$C22,$C22,$B$5:$B22,"Entrada")-SUMIFS($F$5:$F22,$C$5:$C22,$C22,$B$5:$B22,"Salida")) | M22: =IF(AND($C22<>"",$C22=Kardex!$C$4),COUNTIF($C$5:$C22,Kardex!$C$4),"")
D23: =IF($C23="","",IFERROR(INDEX(Productos!$B$5:$B$504,MATCH($C23,Productos!$A$5:$A$504,0)),"Clave no existe")) | E23: =IF($C23="","",IFERROR(INDEX(Productos!$D$5:$D$504,MATCH($C23,Productos!$A$5:$A$504,0)),"")) | G23: =IF($C23="","",IFERROR(INDEX(Productos!$F$5:$F$504,MATCH($C23,Productos!$A$5:$A$504,0)),0)) | H23: =IF(OR($C23="",$F23=""),"",F23*G23) | I23: =IF(OR($C23="",$F23=""),"",IFERROR(INDEX(Productos!$I$5:$I$504,MATCH($C23,Productos!$A$5:$A$504,0)),0)+SUMIFS($F$5:$F23,$C$5:$C23,$C23,$B$5:$B23,"Entrada")-SUMIFS($F$5:$F23,$C$5:$C23,$C23,$B$5:$B23,"Salida")) | M23: =IF(AND($C23<>"",$C23=Kardex!$C$4),COUNTIF($C$5:$C23,Kardex!$C$4),"")
D24: =IF($C24="","",IFERROR(INDEX(Productos!$B$5:$B$504,MATCH($C24,Productos!$A$5:$A$504,0)),"Clave no existe")) | E24: =IF($C24="","",IFERROR(INDEX(Productos!$D$5:$D$504,MATCH($C24,Productos!$A$5:$A$504,0)),"")) | G24: =IF($C24="","",IFERROR(INDEX(Productos!$F$5:$F$504,MATCH($C24,Productos!$A$5:$A$504,0)),0)) | H24: =IF(OR($C24="",$F24=""),"",F24*G24) | I24: =IF(OR($C24="",$F24=""),"",IFERROR(INDEX(Productos!$I$5:$I$504,MATCH($C24,Productos!$A$5:$A$504,0)),0)+SUMIFS($F$5:$F24,$C$5:$C24,$C24,$B$5:$B24,"Entrada")-SUMIFS($F$5:$F24,$C$5:$C24,$C24,$B$5:$B24,"Salida")) | M24: =IF(AND($C24<>"",$C24=Kardex!$C$4),COUNTIF($C$5:$C24,Kardex!$C$4),"")
D25: =IF($C25="","",IFERROR(INDEX(Productos!$B$5:$B$504,MATCH($C25,Productos!$A$5:$A$504,0)),"Clave no existe")) | E25: =IF($C25="","",IFERROR(INDEX(Productos!$D$5:$D$504,MATCH($C25,Productos!$A$5:$A$504,0)),"")) | G25: =IF($C25="","",IFERROR(INDEX(Productos!$F$5:$F$504,MATCH($C25,Productos!$A$5:$A$504,0)),0)) | H25: =IF(OR($C25="",$F25=""),"",F25*G25) | I25: =IF(OR($C25="",$F25=""),"",IFERROR(INDEX(Productos!$I$5:$I$504,MATCH($C25,Productos!$A$5:$A$504,0)),0)+SUMIFS($F$5:$F25,$C$5:$C25,$C25,$B$5:$B25,"Entrada")-SUMIFS($F$5:$F25,$C$5:$C25,$C25,$B$5:$B25,"Salida")) | M25: =IF(AND($C25<>"",$C25=Kardex!$C$4),COUNTIF($C$5:$C25,Kardex!$C$4),"")
D26: =IF($C26="","",IFERROR(INDEX(Productos!$B$5:$B$504,MATCH($C26,Productos!$A$5:$A$504,0)),"Clave no existe")) | E26: =IF($C26="","",IFERROR(INDEX(Productos!$D$5:$D$504,MATCH($C26,Productos!$A$5:$A$504,0)),"")) | G26: =IF($C26="","",IFERROR(INDEX(Productos!$F$5:$F$504,MATCH($C26,Productos!$A$5:$A$504,0)),0)) | H26: =IF(OR($C26="",$F26=""),"",F26*G26) | I26: =IF(OR($C26="",$F26=""),"",IFERROR(INDEX(Productos!$I$5:$I$504,MATCH($C26,Productos!$A$5:$A$504,0)),0)+SUMIFS($F$5:$F26,$C$5:$C26,$C26,$B$5:$B26,"Entrada")-SUMIFS($F$5:$F26,$C$5:$C26,$C26,$B$5:$B26,"Salida")) | M26: =IF(AND($C26<>"",$C26=Kardex!$C$4),COUNTIF($C$5:$C26,Kardex!$C$4),"")
D27: =IF($C27="","",IFERROR(INDEX(Productos!$B$5:$B$504,MATCH($C27,Productos!$A$5:$A$504,0)),"Clave no existe")) | E27: =IF($C27="","",IFERROR(INDEX(Productos!$D$5:$D$504,MATCH($C27,Productos!$A$5:$A$504,0)),"")) | G27: =IF($C27="","",IFERROR(INDEX(Productos!$F$5:$F$504,MATCH($C27,Productos!$A$5:$A$504,0)),0)) | H27: =IF(OR($C27="",$F27=""),"",F27*G27) | I27: =IF(OR($C27="",$F27=""),"",IFERROR(INDEX(Productos!$I$5:$I$504,MATCH($C27,Productos!$A$5:$A$504,0)),0)+SUMIFS($F$5:$F27,$C$5:$C27,$C27,$B$5:$B27,"Entrada")-SUMIFS($F$5:$F27,$C$5:$C27,$C27,$B$5:$B27,"Salida")) | M27: =IF(AND($C27<>"",$C27=Kardex!$C$4),COUNTIF($C$5:$C27,Kardex!$C$4),"")
D28: =IF($C28="","",IFERROR(INDEX(Productos!$B$5:$B$504,MATCH($C28,Productos!$A$5:$A$504,0)),"Clave no existe")) | E28: =IF($C28="","",IFERROR(INDEX(Productos!$D$5:$D$504,MATCH($C28,Productos!$A$5:$A$504,0)),"")) | G28: =IF($C28="","",IFERROR(INDEX(Productos!$F$5:$F$504,MATCH($C28,Productos!$A$5:$A$504,0)),0)) | H28: =IF(OR($C28="",$F28=""),"",F28*G28) | I28: =IF(OR($C28="",$F28=""),"",IFERROR(INDEX(Productos!$I$5:$I$504,MATCH($C28,Productos!$A$5:$A$504,0)),0)+SUMIFS($F$5:$F28,$C$5:$C28,$C28,$B$5:$B28,"Entrada")-SUMIFS($F$5:$F28,$C$5:$C28,$C28,$B$5:$B28,"Salida")) | M28: =IF(AND($C28<>"",$C28=Kardex!$C$4),COUNTIF($C$5:$C28,Kardex!$C$4),"")
D29: =IF($C29="","",IFERROR(INDEX(Productos!$B$5:$B$504,MATCH($C29,Productos!$A$5:$A$504,0)),"Clave no existe")) | E29: =IF($C29="","",IFERROR(INDEX(Productos!$D$5:$D$504,MATCH($C29,Productos!$A$5:$A$504,0)),"")) | G29: =IF($C29="","",IFERROR(INDEX(Productos!$F$5:$F$504,MATCH($C29,Productos!$A$5:$A$504,0)),0)) | H29: =IF(OR($C29="",$F29=""),"",F29*G29) | I29: =IF(OR($C29="",$F29=""),"",IFERROR(INDEX(Productos!$I$5:$I$504,MATCH($C29,Productos!$A$5:$A$504,0)),0)+SUMIFS($F$5:$F29,$C$5:$C29,$C29,$B$5:$B29,"Entrada")-SUMIFS($F$5:$F29,$C$5:$C29,$C29,$B$5:$B29,"Salida")) | M29: =IF(AND($C29<>"",$C29=Kardex!$C$4),COUNTIF($C$5:$C29,Kardex!$C$4),"")
D30: =IF($C30="","",IFERROR(INDEX(Productos!$B$5:$B$504,MATCH($C30,Productos!$A$5:$A$504,0)),"Clave no existe")) | E30: =IF($C30="","",IFERROR(INDEX(Productos!$D$5:$D$504,MATCH($C30,Productos!$A$5:$A$504,0)),"")) | G30: =IF($C30="","",IFERROR(INDEX(Productos!$F$5:$F$504,MATCH($C30,Productos!$A$5:$A$504,0)),0)) | H30: =IF(OR($C30="",$F30=""),"",F30*G30) | I30: =IF(OR($C30="",$F30=""),"",IFERROR(INDEX(Productos!$I$5:$I$504,MATCH($C30,Productos!$A$5:$A$504,0)),0)+SUMIFS($F$5:$F30,$C$5:$C30,$C30,$B$5:$B30,"Entrada")-SUMIFS($F$5:$F30,$C$5:$C30,$C30,$B$5:$B30,"Salida")) | M30: =IF(AND($C30<>"",$C30=Kardex!$C$4),COUNTIF($C$5:$C30,Kardex!$C$4),"")
... D3004: =IF($C3004="","",IFERROR(INDEX(Productos!$B$5:$B$504,MATCH($C3004,Productos!$A$5:$A$504,0)),"Clave no existe")) | E3004: =IF($C3004="","",IFERROR(INDEX(Productos!$D$5:$D$504,MATCH($C3004,Productos!$A$5:$A$504,0)),"")) | G3004: =IF($C3004="","",IFERROR(INDEX(Productos!$F$5:$F$504,MATCH($C3004,Productos!$A$5:$A$504,0)),0)) | H3004: =IF(OR($C3004="",$F3004=""),"",F3004*G3004) | I3004: =IF(OR($C3004="",$F3004=""),"",IFERROR(INDEX(Productos!$I$5:$I$504,MATCH($C3004,Productos!$A$5:$A$504,0)),0)+SUMIFS($F$5:$F3004,$C$5:$C3004,$C3004,$B$5:$B3004,"Entrada")-SUMIFS($F$5:$F3004,$C$5:$C3004,$C3004,$B$5:$B3004,"Salida")) | M3004: =IF(AND($C3004<>"",$C3004=Kardex!$C$4),COUNTIF($C$5:$C3004,Kardex!$C$4),"")

Sheet Kardex
A1: Kardex por artículo
A2: Elige una clave en la celda amarilla y verás todos sus movimientos con la existencia después de cada uno.
B4: Clave: | C4: P-001 | D4: =IF($C$4="","",IFERROR(INDEX(Productos!$B$5:$B$504,MATCH($C$4,Productos!$A$5:$A$504,0)),"Clave no existe")) -> Cemento gris 50 kg
B5: Existencia inicial: | C5: =IF($C$4="","",IFERROR(INDEX(Productos!$I$5:$I$504,MATCH($C$4,Productos!$A$5:$A$504,0)),0)) -> 80
B6: Existencia actual: | C6: =IF($C$4="","",IFERROR(INDEX(Productos!$L$5:$L$504,MATCH($C$4,Productos!$A$5:$A$504,0)),0)) -> 55
A8: # | B8: Fecha | C8: Tipo | D8: Referencia | E8: Entrada | F8: Salida | G8: Existencia | H8: Costo unitario | I8: Importe | J8: Responsable
A9: =IF(1<=COUNTIF(Movimientos!$M$5:$M$3004,">0"),1,"") -> 1 | B9: =IF($A9="","",INDEX(Movimientos!$A$5:$A$3004,MATCH($A9,Movimientos!$M$5:$M$3004,0))) -> 46296 | C9: =IF($A9="","",INDEX(Movimientos!$B$5:$B$3004,MATCH($A9,Movimientos!$M$5:$M$3004,0))) -> Entrada | D9: =IF($A9="","",INDEX(Movimientos!$J$5:$J$3004,MATCH($A9,Movimientos!$M$5:$M$3004,0))&"") -> Factura A-1182 | E9: =IF($A9="","",IF(C9="Entrada",INDEX(Movimientos!$F$5:$F$3004,MATCH($A9,Movimientos!$M$5:$M$3004,0)),"")) -> 60 | F9: =IF($A9="","",IF(C9="Salida",INDEX(Movimientos!$F$5:$F$3004,MATCH($A9,Movimientos!$M$5:$M$3004,0)),"")) | G9: =IF($A9="","",INDEX(Movimientos!$I$5:$I$3004,MATCH($A9,Movimientos!$M$5:$M$3004,0))) -> 140 | H9: =IF($A9="","",INDEX(Movimientos!$G$5:$G$3004,MATCH($A9,Movimientos!$M$5:$M$3004,0))) -> 215 | I9: =IF($A9="","",INDEX(Movimientos!$H$5:$H$3004,MATCH($A9,Movimientos!$M$5:$M$3004,0))) -> 12900 | J9: =IF($A9="","",INDEX(Movimientos!$K$5:$K$3004,MATCH($A9,Movimientos!$M$5:$M$3004,0))&"") -> Almacén
A10: =IF(2<=COUNTIF(Movimientos!$M$5:$M$3004,">0"),2,"") -> 2 | B10: =IF($A10="","",INDEX(Movimientos!$A$5:$A$3004,MATCH($A10,Movimientos!$M$5:$M$3004,0))) -> 46297 | C10: =IF($A10="","",INDEX(Movimientos!$B$5:$B$3004,MATCH($A10,Movimientos!$M$5:$M$3004,0))) -> Salida | D10: =IF($A10="","",INDEX(Movimientos!$J$5:$J$3004,MATCH($A10,Movimientos!$M$5:$M$3004,0))&"") -> Pedido 0451 | E10: =IF($A10="","",IF(C10="Entrada",INDEX(Movimientos!$F$5:$F$3004,MATCH($A10,Movimientos!$M$5:$M$3004,0)),"")) | F10: =IF($A10="","",IF(C10="Salida",INDEX(Movimientos!$F$5:$F$3004,MATCH($A10,Movimientos!$M$5:$M$3004,0)),"")) -> 35 | G10: =IF($A10="","",INDEX(Movimientos!$I$5:$I$3004,MATCH($A10,Movimientos!$M$5:$M$3004,0))) -> 105 | H10: =IF($A10="","",INDEX(Movimientos!$G$5:$G$3004,MATCH($A10,Movimientos!$M$5:$M$3004,0))) -> 215 | I10: =IF($A10="","",INDEX(Movimientos!$H$5:$H$3004,MATCH($A10,Movimientos!$M$5:$M$3004,0))) -> 7525 | J10: =IF($A10="","",INDEX(Movimientos!$K$5:$K$3004,MATCH($A10,Movimientos!$M$5:$M$3004,0))&"") -> Ventas
A11: =IF(3<=COUNTIF(Movimientos!$M$5:$M$3004,">0"),3,"") -> 3 | B11: =IF($A11="","",INDEX(Movimientos!$A$5:$A$3004,MATCH($A11,Movimientos!$M$5:$M$3004,0))) -> 46305 | C11: =IF($A11="","",INDEX(Movimientos!$B$5:$B$3004,MATCH($A11,Movimientos!$M$5:$M$3004,0))) -> Salida | D11: =IF($A11="","",INDEX(Movimientos!$J$5:$J$3004,MATCH($A11,Movimientos!$M$5:$M$3004,0))&"") -> Pedido 0463 | E11: =IF($A11="","",IF(C11="Entrada",INDEX(Movimientos!$F$5:$F$3004,MATCH($A11,Movimientos!$M$5:$M$3004,0)),"")) | F11: =IF($A11="","",IF(C11="Salida",INDEX(Movimientos!$F$5:$F$3004,MATCH($A11,Movimientos!$M$5:$M$3004,0)),"")) -> 50 | G11: =IF($A11="","",INDEX(Movimientos!$I$5:$I$3004,MATCH($A11,Movimientos!$M$5:$M$3004,0))) -> 55 | H11: =IF($A11="","",INDEX(Movimientos!$G$5:$G$3004,MATCH($A11,Movimientos!$M$5:$M$3004,0))) -> 215 | I11: =IF($A11="","",INDEX(Movimientos!$H$5:$H$3004,MATCH($A11,Movimientos!$M$5:$M$3004,0))) -> 10750 | J11: =IF($A11="","",INDEX(Movimientos!$K$5:$K$3004,MATCH($A11,Movimientos!$M$5:$M$3004,0))&"") -> Ventas
A12: =IF(4<=COUNTIF(Movimientos!$M$5:$M$3004,">0"),4,"") | B12: =IF($A12="","",INDEX(Movimientos!$A$5:$A$3004,MATCH($A12,Movimientos!$M$5:$M$3004,0))) | C12: =IF($A12="","",INDEX(Movimientos!$B$5:$B$3004,MATCH($A12,Movimientos!$M$5:$M$3004,0))) | D12: =IF($A12="","",INDEX(Movimientos!$J$5:$J$3004,MATCH($A12,Movimientos!$M$5:$M$3004,0))&"") | E12: =IF($A12="","",IF(C12="Entrada",INDEX(Movimientos!$F$5:$F$3004,MATCH($A12,Movimientos!$M$5:$M$3004,0)),"")) | F12: =IF($A12="","",IF(C12="Salida",INDEX(Movimientos!$F$5:$F$3004,MATCH($A12,Movimientos!$M$5:$M$3004,0)),"")) | G12: =IF($A12="","",INDEX(Movimientos!$I$5:$I$3004,MATCH($A12,Movimientos!$M$5:$M$3004,0))) | H12: =IF($A12="","",INDEX(Movimientos!$G$5:$G$3004,MATCH($A12,Movimientos!$M$5:$M$3004,0))) | I12: =IF($A12="","",INDEX(Movimientos!$H$5:$H$3004,MATCH($A12,Movimientos!$M$5:$M$3004,0))) | J12: =IF($A12="","",INDEX(Movimientos!$K$5:$K$3004,MATCH($A12,Movimientos!$M$5:$M$3004,0))&"")
A13: =IF(5<=COUNTIF(Movimientos!$M$5:$M$3004,">0"),5,"") | B13: =IF($A13="","",INDEX(Movimientos!$A$5:$A$3004,MATCH($A13,Movimientos!$M$5:$M$3004,0))) | C13: =IF($A13="","",INDEX(Movimientos!$B$5:$B$3004,MATCH($A13,Movimientos!$M$5:$M$3004,0))) | D13: =IF($A13="","",INDEX(Movimientos!$J$5:$J$3004,MATCH($A13,Movimientos!$M$5:$M$3004,0))&"") | E13: =IF($A13="","",IF(C13="Entrada",INDEX(Movimientos!$F$5:$F$3004,MATCH($A13,Movimientos!$M$5:$M$3004,0)),"")) | F13: =IF($A13="","",IF(C13="Salida",INDEX(Movimientos!$F$5:$F$3004,MATCH($A13,Movimientos!$M$5:$M$3004,0)),"")) | G13: =IF($A13="","",INDEX(Movimientos!$I$5:$I$3004,MATCH($A13,Movimientos!$M$5:$M$3004,0))) | H13: =IF($A13="","",INDEX(Movimientos!$G$5:$G$3004,MATCH($A13,Movimientos!$M$5:$M$3004,0))) | I13: =IF($A13="","",INDEX(Movimientos!$H$5:$H$3004,MATCH($A13,Movimientos!$M$5:$M$3004,0))) | J13: =IF($A13="","",INDEX(Movimientos!$K$5:$K$3004,MATCH($A13,Movimientos!$M$5:$M$3004,0))&"")
A14: =IF(6<=COUNTIF(Movimientos!$M$5:$M$3004,">0"),6,"") | B14: =IF($A14="","",INDEX(Movimientos!$A$5:$A$3004,MATCH($A14,Movimientos!$M$5:$M$3004,0))) | C14: =IF($A14="","",INDEX(Movimientos!$B$5:$B$3004,MATCH($A14,Movimientos!$M$5:$M$3004,0))) | D14: =IF($A14="","",INDEX(Movimientos!$J$5:$J$3004,MATCH($A14,Movimientos!$M$5:$M$3004,0))&"") | E14: =IF($A14="","",IF(C14="Entrada",INDEX(Movimientos!$F$5:$F$3004,MATCH($A14,Movimientos!$M$5:$M$3004,0)),"")) | F14: =IF($A14="","",IF(C14="Salida",INDEX(Movimientos!$F$5:$F$3004,MATCH($A14,Movimientos!$M$5:$M$3004,0)),"")) | G14: =IF($A14="","",INDEX(Movimientos!$I$5:$I$3004,MATCH($A14,Movimientos!$M$5:$M$3004,0))) | H14: =IF($A14="","",INDEX(Movimientos!$G$5:$G$3004,MATCH($A14,Movimientos!$M$5:$M$3004,0))) | I14: =IF($A14="","",INDEX(Movimientos!$H$5:$H$3004,MATCH($A14,Movimientos!$M$5:$M$3004,0))) | J14: =IF($A14="","",INDEX(Movimientos!$K$5:$K$3004,MATCH($A14,Movimientos!$M$5:$M$3004,0))&"")
A15: =IF(7<=COUNTIF(Movimientos!$M$5:$M$3004,">0"),7,"") | B15: =IF($A15="","",INDEX(Movimientos!$A$5:$A$3004,MATCH($A15,Movimientos!$M$5:$M$3004,0))) | C15: =IF($A15="","",INDEX(Movimientos!$B$5:$B$3004,MATCH($A15,Movimientos!$M$5:$M$3004,0))) | D15: =IF($A15="","",INDEX(Movimientos!$J$5:$J$3004,MATCH($A15,Movimientos!$M$5:$M$3004,0))&"") | E15: =IF($A15="","",IF(C15="Entrada",INDEX(Movimientos!$F$5:$F$3004,MATCH($A15,Movimientos!$M$5:$M$3004,0)),"")) | F15: =IF($A15="","",IF(C15="Salida",INDEX(Movimientos!$F$5:$F$3004,MATCH($A15,Movimientos!$M$5:$M$3004,0)),"")) | G15: =IF($A15="","",INDEX(Movimientos!$I$5:$I$3004,MATCH($A15,Movimientos!$M$5:$M$3004,0))) | H15: =IF($A15="","",INDEX(Movimientos!$G$5:$G$3004,MATCH($A15,Movimientos!$M$5:$M$3004,0))) | I15: =IF($A15="","",INDEX(Movimientos!$H$5:$H$3004,MATCH($A15,Movimientos!$M$5:$M$3004,0))) | J15: =IF($A15="","",INDEX(Movimientos!$K$5:$K$3004,MATCH($A15,Movimientos!$M$5:$M$3004,0))&"")
A16: =IF(8<=COUNTIF(Movimientos!$M$5:$M$3004,">0"),8,"") | B16: =IF($A16="","",INDEX(Movimientos!$A$5:$A$3004,MATCH($A16,Movimientos!$M$5:$M$3004,0))) | C16: =IF($A16="","",INDEX(Movimientos!$B$5:$B$3004,MATCH($A16,Movimientos!$M$5:$M$3004,0))) | D16: =IF($A16="","",INDEX(Movimientos!$J$5:$J$3004,MATCH($A16,Movimientos!$M$5:$M$3004,0))&"") | E16: =IF($A16="","",IF(C16="Entrada",INDEX(Movimientos!$F$5:$F$3004,MATCH($A16,Movimientos!$M$5:$M$3004,0)),"")) | F16: =IF($A16="","",IF(C16="Salida",INDEX(Movimientos!$F$5:$F$3004,MATCH($A16,Movimientos!$M$5:$M$3004,0)),"")) | G16: =IF($A16="","",INDEX(Movimientos!$I$5:$I$3004,MATCH($A16,Movimientos!$M$5:$M$3004,0))) | H16: =IF($A16="","",INDEX(Movimientos!$G$5:$G$3004,MATCH($A16,Movimientos!$M$5:$M$3004,0))) | I16: =IF($A16="","",INDEX(Movimientos!$H$5:$H$3004,MATCH($A16,Movimientos!$M$5:$M$3004,0))) | J16: =IF($A16="","",INDEX(Movimientos!$K$5:$K$3004,MATCH($A16,Movimientos!$M$5:$M$3004,0))&"")
A17: =IF(9<=COUNTIF(Movimientos!$M$5:$M$3004,">0"),9,"") | B17: =IF($A17="","",INDEX(Movimientos!$A$5:$A$3004,MATCH($A17,Movimientos!$M$5:$M$3004,0))) | C17: =IF($A17="","",INDEX(Movimientos!$B$5:$B$3004,MATCH($A17,Movimientos!$M$5:$M$3004,0))) | D17: =IF($A17="","",INDEX(Movimientos!$J$5:$J$3004,MATCH($A17,Movimientos!$M$5:$M$3004,0))&"") | E17: =IF($A17="","",IF(C17="Entrada",INDEX(Movimientos!$F$5:$F$3004,MATCH($A17,Movimientos!$M$5:$M$3004,0)),"")) | F17: =IF($A17="","",IF(C17="Salida",INDEX(Movimientos!$F$5:$F$3004,MATCH($A17,Movimientos!$M$5:$M$3004,0)),"")) | G17: =IF($A17="","",INDEX(Movimientos!$I$5:$I$3004,MATCH($A17,Movimientos!$M$5:$M$3004,0))) | H17: =IF($A17="","",INDEX(Movimientos!$G$5:$G$3004,MATCH($A17,Movimientos!$M$5:$M$3004,0))) | I17: =IF($A17="","",INDEX(Movimientos!$H$5:$H$3004,MATCH($A17,Movimientos!$M$5:$M$3004,0))) | J17: =IF($A17="","",INDEX(Movimientos!$K$5:$K$3004,MATCH($A17,Movimientos!$M$5:$M$3004,0))&"")
A18: =IF(10<=COUNTIF(Movimientos!$M$5:$M$3004,">0"),10,"") | B18: =IF($A18="","",INDEX(Movimientos!$A$5:$A$3004,MATCH($A18,Movimientos!$M$5:$M$3004,0))) | C18: =IF($A18="","",INDEX(Movimientos!$B$5:$B$3004,MATCH($A18,Movimientos!$M$5:$M$3004,0))) | D18: =IF($A18="","",INDEX(Movimientos!$J$5:$J$3004,MATCH($A18,Movimientos!$M$5:$M$3004,0))&"") | E18: =IF($A18="","",IF(C18="Entrada",INDEX(Movimientos!$F$5:$F$3004,MATCH($A18,Movimientos!$M$5:$M$3004,0)),"")) | F18: =IF($A18="","",IF(C18="Salida",INDEX(Movimientos!$F$5:$F$3004,MATCH($A18,Movimientos!$M$5:$M$3004,0)),"")) | G18: =IF($A18="","",INDEX(Movimientos!$I$5:$I$3004,MATCH($A18,Movimientos!$M$5:$M$3004,0))) | H18: =IF($A18="","",INDEX(Movimientos!$G$5:$G$3004,MATCH($A18,Movimientos!$M$5:$M$3004,0))) | I18: =IF($A18="","",INDEX(Movimientos!$H$5:$H$3004,MATCH($A18,Movimientos!$M$5:$M$3004,0))) | J18: =IF($A18="","",INDEX(Movimientos!$K$5:$K$3004,MATCH($A18,Movimientos!$M$5:$M$3004,0))&"")
A19: =IF(11<=COUNTIF(Movimientos!$M$5:$M$3004,">0"),11,"") | B19: =IF($A19="","",INDEX(Movimientos!$A$5:$A$3004,MATCH($A19,Movimientos!$M$5:$M$3004,0))) | C19: =IF($A19="","",INDEX(Movimientos!$B$5:$B$3004,MATCH($A19,Movimientos!$M$5:$M$3004,0))) | D19: =IF($A19="","",INDEX(Movimientos!$J$5:$J$3004,MATCH($A19,Movimientos!$M$5:$M$3004,0))&"") | E19: =IF($A19="","",IF(C19="Entrada",INDEX(Movimientos!$F$5:$F$3004,MATCH($A19,Movimientos!$M$5:$M$3004,0)),"")) | F19: =IF($A19="","",IF(C19="Salida",INDEX(Movimientos!$F$5:$F$3004,MATCH($A19,Movimientos!$M$5:$M$3004,0)),"")) | G19: =IF($A19="","",INDEX(Movimientos!$I$5:$I$3004,MATCH($A19,Movimientos!$M$5:$M$3004,0))) | H19: =IF($A19="","",INDEX(Movimientos!$G$5:$G$3004,MATCH($A19,Movimientos!$M$5:$M$3004,0))) | I19: =IF($A19="","",INDEX(Movimientos!$H$5:$H$3004,MATCH($A19,Movimientos!$M$5:$M$3004,0))) | J19: =IF($A19="","",INDEX(Movimientos!$K$5:$K$3004,MATCH($A19,Movimientos!$M$5:$M$3004,0))&"")
A20: =IF(12<=COUNTIF(Movimientos!$M$5:$M$3004,">0"),12,"") | B20: =IF($A20="","",INDEX(Movimientos!$A$5:$A$3004,MATCH($A20,Movimientos!$M$5:$M$3004,0))) | C20: =IF($A20="","",INDEX(Movimientos!$B$5:$B$3004,MATCH($A20,Movimientos!$M$5:$M$3004,0))) | D20: =IF($A20="","",INDEX(Movimientos!$J$5:$J$3004,MATCH($A20,Movimientos!$M$5:$M$3004,0))&"") | E20: =IF($A20="","",IF(C20="Entrada",INDEX(Movimientos!$F$5:$F$3004,MATCH($A20,Movimientos!$M$5:$M$3004,0)),"")) | F20: =IF($A20="","",IF(C20="Salida",INDEX(Movimientos!$F$5:$F$3004,MATCH($A20,Movimientos!$M$5:$M$3004,0)),"")) | G20: =IF($A20="","",INDEX(Movimientos!$I$5:$I$3004,MATCH($A20,Movimientos!$M$5:$M$3004,0))) | H20: =IF($A20="","",INDEX(Movimientos!$G$5:$G$3004,MATCH($A20,Movimientos!$M$5:$M$3004,0))) | I20: =IF($A20="","",INDEX(Movimientos!$H$5:$H$3004,MATCH($A20,Movimientos!$M$5:$M$3004,0))) | J20: =IF($A20="","",INDEX(Movimientos!$K$5:$K$3004,MATCH($A20,Movimientos!$M$5:$M$3004,0))&"")
A21: =IF(13<=COUNTIF(Movimientos!$M$5:$M$3004,">0"),13,"") | B21: =IF($A21="","",INDEX(Movimientos!$A$5:$A$3004,MATCH($A21,Movimientos!$M$5:$M$3004,0))) | C21: =IF($A21="","",INDEX(Movimientos!$B$5:$B$3004,MATCH($A21,Movimientos!$M$5:$M$3004,0))) | D21: =IF($A21="","",INDEX(Movimientos!$J$5:$J$3004,MATCH($A21,Movimientos!$M$5:$M$3004,0))&"") | E21: =IF($A21="","",IF(C21="Entrada",INDEX(Movimientos!$F$5:$F$3004,MATCH($A21,Movimientos!$M$5:$M$3004,0)),"")) | F21: =IF($A21="","",IF(C21="Salida",INDEX(Movimientos!$F$5:$F$3004,MATCH($A21,Movimientos!$M$5:$M$3004,0)),"")) | G21: =IF($A21="","",INDEX(Movimientos!$I$5:$I$3004,MATCH($A21,Movimientos!$M$5:$M$3004,0))) | H21: =IF($A21="","",INDEX(Movimientos!$G$5:$G$3004,MATCH($A21,Movimientos!$M$5:$M$3004,0))) | I21: =IF($A21="","",INDEX(Movimientos!$H$5:$H$3004,MATCH($A21,Movimientos!$M$5:$M$3004,0))) | J21: =IF($A21="","",INDEX(Movimientos!$K$5:$K$3004,MATCH($A21,Movimientos!$M$5:$M$3004,0))&"")
A22: =IF(14<=COUNTIF(Movimientos!$M$5:$M$3004,">0"),14,"") | B22: =IF($A22="","",INDEX(Movimientos!$A$5:$A$3004,MATCH($A22,Movimientos!$M$5:$M$3004,0))) | C22: =IF($A22="","",INDEX(Movimientos!$B$5:$B$3004,MATCH($A22,Movimientos!$M$5:$M$3004,0))) | D22: =IF($A22="","",INDEX(Movimientos!$J$5:$J$3004,MATCH($A22,Movimientos!$M$5:$M$3004,0))&"") | E22: =IF($A22="","",IF(C22="Entrada",INDEX(Movimientos!$F$5:$F$3004,MATCH($A22,Movimientos!$M$5:$M$3004,0)),"")) | F22: =IF($A22="","",IF(C22="Salida",INDEX(Movimientos!$F$5:$F$3004,MATCH($A22,Movimientos!$M$5:$M$3004,0)),"")) | G22: =IF($A22="","",INDEX(Movimientos!$I$5:$I$3004,MATCH($A22,Movimientos!$M$5:$M$3004,0))) | H22: =IF($A22="","",INDEX(Movimientos!$G$5:$G$3004,MATCH($A22,Movimientos!$M$5:$M$3004,0))) | I22: =IF($A22="","",INDEX(Movimientos!$H$5:$H$3004,MATCH($A22,Movimientos!$M$5:$M$3004,0))) | J22: =IF($A22="","",INDEX(Movimientos!$K$5:$K$3004,MATCH($A22,Movimientos!$M$5:$M$3004,0))&"")
A23: =IF(15<=COUNTIF(Movimientos!$M$5:$M$3004,">0"),15,"") | B23: =IF($A23="","",INDEX(Movimientos!$A$5:$A$3004,MATCH($A23,Movimientos!$M$5:$M$3004,0))) | C23: =IF($A23="","",INDEX(Movimientos!$B$5:$B$3004,MATCH($A23,Movimientos!$M$5:$M$3004,0))) | D23: =IF($A23="","",INDEX(Movimientos!$J$5:$J$3004,MATCH($A23,Movimientos!$M$5:$M$3004,0))&"") | E23: =IF($A23="","",IF(C23="Entrada",INDEX(Movimientos!$F$5:$F$3004,MATCH($A23,Movimientos!$M$5:$M$3004,0)),"")) | F23: =IF($A23="","",IF(C23="Salida",INDEX(Movimientos!$F$5:$F$3004,MATCH($A23,Movimientos!$M$5:$M$3004,0)),"")) | G23: =IF($A23="","",INDEX(Movimientos!$I$5:$I$3004,MATCH($A23,Movimientos!$M$5:$M$3004,0))) | H23: =IF($A23="","",INDEX(Movimientos!$G$5:$G$3004,MATCH($A23,Movimientos!$M$5:$M$3004,0))) | I23: =IF($A23="","",INDEX(Movimientos!$H$5:$H$3004,MATCH($A23,Movimientos!$M$5:$M$3004,0))) | J23: =IF($A23="","",INDEX(Movimientos!$K$5:$K$3004,MATCH($A23,Movimientos!$M$5:$M$3004,0))&"")
A24: =IF(16<=COUNTIF(Movimientos!$M$5:$M$3004,">0"),16,"") | B24: =IF($A24="","",INDEX(Movimientos!$A$5:$A$3004,MATCH($A24,Movimientos!$M$5:$M$3004,0))) | C24: =IF($A24="","",INDEX(Movimientos!$B$5:$B$3004,MATCH($A24,Movimientos!$M$5:$M$3004,0))) | D24: =IF($A24="","",INDEX(Movimientos!$J$5:$J$3004,MATCH($A24,Movimientos!$M$5:$M$3004,0))&"") | E24: =IF($A24="","",IF(C24="Entrada",INDEX(Movimientos!$F$5:$F$3004,MATCH($A24,Movimientos!$M$5:$M$3004,0)),"")) | F24: =IF($A24="","",IF(C24="Salida",INDEX(Movimientos!$F$5:$F$3004,MATCH($A24,Movimientos!$M$5:$M$3004,0)),"")) | G24: =IF($A24="","",INDEX(Movimientos!$I$5:$I$3004,MATCH($A24,Movimientos!$M$5:$M$3004,0))) | H24: =IF($A24="","",INDEX(Movimientos!$G$5:$G$3004,MATCH($A24,Movimientos!$M$5:$M$3004,0))) | I24: =IF($A24="","",INDEX(Movimientos!$H$5:$H$3004,MATCH($A24,Movimientos!$M$5:$M$3004,0))) | J24: =IF($A24="","",INDEX(Movimientos!$K$5:$K$3004,MATCH($A24,Movimientos!$M$5:$M$3004,0))&"")
A25: =IF(17<=COUNTIF(Movimientos!$M$5:$M$3004,">0"),17,"") | B25: =IF($A25="","",INDEX(Movimientos!$A$5:$A$3004,MATCH($A25,Movimientos!$M$5:$M$3004,0))) | C25: =IF($A25="","",INDEX(Movimientos!$B$5:$B$3004,MATCH($A25,Movimientos!$M$5:$M$3004,0))) | D25: =IF($A25="","",INDEX(Movimientos!$J$5:$J$3004,MATCH($A25,Movimientos!$M$5:$M$3004,0))&"") | E25: =IF($A25="","",IF(C25="Entrada",INDEX(Movimientos!$F$5:$F$3004,MATCH($A25,Movimientos!$M$5:$M$3004,0)),"")) | F25: =IF($A25="","",IF(C25="Salida",INDEX(Movimientos!$F$5:$F$3004,MATCH($A25,Movimientos!$M$5:$M$3004,0)),"")) | G25: =IF($A25="","",INDEX(Movimientos!$I$5:$I$3004,MATCH($A25,Movimientos!$M$5:$M$3004,0))) | H25: =IF($A25="","",INDEX(Movimientos!$G$5:$G$3004,MATCH($A25,Movimientos!$M$5:$M$3004,0))) | I25: =IF($A25="","",INDEX(Movimientos!$H$5:$H$3004,MATCH($A25,Movimientos!$M$5:$M$3004,0))) | J25: =IF($A25="","",INDEX(Movimientos!$K$5:$K$3004,MATCH($A25,Movimientos!$M$5:$M$3004,0))&"")
A26: =IF(18<=COUNTIF(Movimientos!$M$5:$M$3004,">0"),18,"") | B26: =IF($A26="","",INDEX(Movimientos!$A$5:$A$3004,MATCH($A26,Movimientos!$M$5:$M$3004,0))) | C26: =IF($A26="","",INDEX(Movimientos!$B$5:$B$3004,MATCH($A26,Movimientos!$M$5:$M$3004,0))) | D26: =IF($A26="","",INDEX(Movimientos!$J$5:$J$3004,MATCH($A26,Movimientos!$M$5:$M$3004,0))&"") | E26: =IF($A26="","",IF(C26="Entrada",INDEX(Movimientos!$F$5:$F$3004,MATCH($A26,Movimientos!$M$5:$M$3004,0)),"")) | F26: =IF($A26="","",IF(C26="Salida",INDEX(Movimientos!$F$5:$F$3004,MATCH($A26,Movimientos!$M$5:$M$3004,0)),"")) | G26: =IF($A26="","",INDEX(Movimientos!$I$5:$I$3004,MATCH($A26,Movimientos!$M$5:$M$3004,0))) | H26: =IF($A26="","",INDEX(Movimientos!$G$5:$G$3004,MATCH($A26,Movimientos!$M$5:$M$3004,0))) | I26: =IF($A26="","",INDEX(Movimientos!$H$5:$H$3004,MATCH($A26,Movimientos!$M$5:$M$3004,0))) | J26: =IF($A26="","",INDEX(Movimientos!$K$5:$K$3004,MATCH($A26,Movimientos!$M$5:$M$3004,0))&"")
A27: =IF(19<=COUNTIF(Movimientos!$M$5:$M$3004,">0"),19,"") | B27: =IF($A27="","",INDEX(Movimientos!$A$5:$A$3004,MATCH($A27,Movimientos!$M$5:$M$3004,0))) | C27: =IF($A27="","",INDEX(Movimientos!$B$5:$B$3004,MATCH($A27,Movimientos!$M$5:$M$3004,0))) | D27: =IF($A27="","",INDEX(Movimientos!$J$5:$J$3004,MATCH($A27,Movimientos!$M$5:$M$3004,0))&"") | E27: =IF($A27="","",IF(C27="Entrada",INDEX(Movimientos!$F$5:$F$3004,MATCH($A27,Movimientos!$M$5:$M$3004,0)),"")) | F27: =IF($A27="","",IF(C27="Salida",INDEX(Movimientos!$F$5:$F$3004,MATCH($A27,Movimientos!$M$5:$M$3004,0)),"")) | G27: =IF($A27="","",INDEX(Movimientos!$I$5:$I$3004,MATCH($A27,Movimientos!$M$5:$M$3004,0))) | H27: =IF($A27="","",INDEX(Movimientos!$G$5:$G$3004,MATCH($A27,Movimientos!$M$5:$M$3004,0))) | I27: =IF($A27="","",INDEX(Movimientos!$H$5:$H$3004,MATCH($A27,Movimientos!$M$5:$M$3004,0))) | J27: =IF($A27="","",INDEX(Movimientos!$K$5:$K$3004,MATCH($A27,Movimientos!$M$5:$M$3004,0))&"")
A28: =IF(20<=COUNTIF(Movimientos!$M$5:$M$3004,">0"),20,"") | B28: =IF($A28="","",INDEX(Movimientos!$A$5:$A$3004,MATCH($A28,Movimientos!$M$5:$M$3004,0))) | C28: =IF($A28="","",INDEX(Movimientos!$B$5:$B$3004,MATCH($A28,Movimientos!$M$5:$M$3004,0))) | D28: =IF($A28="","",INDEX(Movimientos!$J$5:$J$3004,MATCH($A28,Movimientos!$M$5:$M$3004,0))&"") | E28: =IF($A28="","",IF(C28="Entrada",INDEX(Movimientos!$F$5:$F$3004,MATCH($A28,Movimientos!$M$5:$M$3004,0)),"")) | F28: =IF($A28="","",IF(C28="Salida",INDEX(Movimientos!$F$5:$F$3004,MATCH($A28,Movimientos!$M$5:$M$3004,0)),"")) | G28: =IF($A28="","",INDEX(Movimientos!$I$5:$I$3004,MATCH($A28,Movimientos!$M$5:$M$3004,0))) | H28: =IF($A28="","",INDEX(Movimientos!$G$5:$G$3004,MATCH($A28,Movimientos!$M$5:$M$3004,0))) | I28: =IF($A28="","",INDEX(Movimientos!$H$5:$H$3004,MATCH($A28,Movimientos!$M$5:$M$3004,0))) | J28: =IF($A28="","",INDEX(Movimientos!$K$5:$K$3004,MATCH($A28,Movimientos!$M$5:$M$3004,0))&"")
A29: =IF(21<=COUNTIF(Movimientos!$M$5:$M$3004,">0"),21,"") | B29: =IF($A29="","",INDEX(Movimientos!$A$5:$A$3004,MATCH($A29,Movimientos!$M$5:$M$3004,0))) | C29: =IF($A29="","",INDEX(Movimientos!$B$5:$B$3004,MATCH($A29,Movimientos!$M$5:$M$3004,0))) | D29: =IF($A29="","",INDEX(Movimientos!$J$5:$J$3004,MATCH($A29,Movimientos!$M$5:$M$3004,0))&"") | E29: =IF($A29="","",IF(C29="Entrada",INDEX(Movimientos!$F$5:$F$3004,MATCH($A29,Movimientos!$M$5:$M$3004,0)),"")) | F29: =IF($A29="","",IF(C29="Salida",INDEX(Movimientos!$F$5:$F$3004,MATCH($A29,Movimientos!$M$5:$M$3004,0)),"")) | G29: =IF($A29="","",INDEX(Movimientos!$I$5:$I$3004,MATCH($A29,Movimientos!$M$5:$M$3004,0))) | H29: =IF($A29="","",INDEX(Movimientos!$G$5:$G$3004,MATCH($A29,Movimientos!$M$5:$M$3004,0))) | I29: =IF($A29="","",INDEX(Movimientos!$H$5:$H$3004,MATCH($A29,Movimientos!$M$5:$M$3004,0))) | J29: =IF($A29="","",INDEX(Movimientos!$K$5:$K$3004,MATCH($A29,Movimientos!$M$5:$M$3004,0))&"")
A30: =IF(22<=COUNTIF(Movimientos!$M$5:$M$3004,">0"),22,"") | B30: =IF($A30="","",INDEX(Movimientos!$A$5:$A$3004,MATCH($A30,Movimientos!$M$5:$M$3004,0))) | C30: =IF($A30="","",INDEX(Movimientos!$B$5:$B$3004,MATCH($A30,Movimientos!$M$5:$M$3004,0))) | D30: =IF($A30="","",INDEX(Movimientos!$J$5:$J$3004,MATCH($A30,Movimientos!$M$5:$M$3004,0))&"") | E30: =IF($A30="","",IF(C30="Entrada",INDEX(Movimientos!$F$5:$F$3004,MATCH($A30,Movimientos!$M$5:$M$3004,0)),"")) | F30: =IF($A30="","",IF(C30="Salida",INDEX(Movimientos!$F$5:$F$3004,MATCH($A30,Movimientos!$M$5:$M$3004,0)),"")) | G30: =IF($A30="","",INDEX(Movimientos!$I$5:$I$3004,MATCH($A30,Movimientos!$M$5:$M$3004,0))) | H30: =IF($A30="","",INDEX(Movimientos!$G$5:$G$3004,MATCH($A30,Movimientos!$M$5:$M$3004,0))) | I30: =IF($A30="","",INDEX(Movimientos!$H$5:$H$3004,MATCH($A30,Movimientos!$M$5:$M$3004,0))) | J30: =IF($A30="","",INDEX(Movimientos!$K$5:$K$3004,MATCH($A30,Movimientos!$M$5:$M$3004,0))&"")
A31: =IF(23<=COUNTIF(Movimientos!$M$5:$M$3004,">0"),23,"") | B31: =IF($A31="","",INDEX(Movimientos!$A$5:$A$3004,MATCH($A31,Movimientos!$M$5:$M$3004,0))) | C31: =IF($A31="","",INDEX(Movimientos!$B$5:$B$3004,MATCH($A31,Movimientos!$M$5:$M$3004,0))) | D31: =IF($A31="","",INDEX(Movimientos!$J$5:$J$3004,MATCH($A31,Movimientos!$M$5:$M$3004,0))&"") | E31: =IF($A31="","",IF(C31="Entrada",INDEX(Movimientos!$F$5:$F$3004,MATCH($A31,Movimientos!$M$5:$M$3004,0)),"")) | F31: =IF($A31="","",IF(C31="Salida",INDEX(Movimientos!$F$5:$F$3004,MATCH($A31,Movimientos!$M$5:$M$3004,0)),"")) | G31: =IF($A31="","",INDEX(Movimientos!$I$5:$I$3004,MATCH($A31,Movimientos!$M$5:$M$3004,0))) | H31: =IF($A31="","",INDEX(Movimientos!$G$5:$G$3004,MATCH($A31,Movimientos!$M$5:$M$3004,0))) | I31: =IF($A31="","",INDEX(Movimientos!$H$5:$H$3004,MATCH($A31,Movimientos!$M$5:$M$3004,0))) | J31: =IF($A31="","",INDEX(Movimientos!$K$5:$K$3004,MATCH($A31,Movimientos!$M$5:$M$3004,0))&"")
A32: =IF(24<=COUNTIF(Movimientos!$M$5:$M$3004,">0"),24,"") | B32: =IF($A32="","",INDEX(Movimientos!$A$5:$A$3004,MATCH($A32,Movimientos!$M$5:$M$3004,0))) | C32: =IF($A32="","",INDEX(Movimientos!$B$5:$B$3004,MATCH($A32,Movimientos!$M$5:$M$3004,0))) | D32: =IF($A32="","",INDEX(Movimientos!$J$5:$J$3004,MATCH($A32,Movimientos!$M$5:$M$3004,0))&"") | E32: =IF($A32="","",IF(C32="Entrada",INDEX(Movimientos!$F$5:$F$3004,MATCH($A32,Movimientos!$M$5:$M$3004,0)),"")) | F32: =IF($A32="","",IF(C32="Salida",INDEX(Movimientos!$F$5:$F$3004,MATCH($A32,Movimientos!$M$5:$M$3004,0)),"")) | G32: =IF($A32="","",INDEX(Movimientos!$I$5:$I$3004,MATCH($A32,Movimientos!$M$5:$M$3004,0))) | H32: =IF($A32="","",INDEX(Movimientos!$G$5:$G$3004,MATCH($A32,Movimientos!$M$5:$M$3004,0))) | I32: =IF($A32="","",INDEX(Movimientos!$H$5:$H$3004,MATCH($A32,Movimientos!$M$5:$M$3004,0))) | J32: =IF($A32="","",INDEX(Movimientos!$K$5:$K$3004,MATCH($A32,Movimientos!$M$5:$M$3004,0))&"")
A33: =IF(25<=COUNTIF(Movimientos!$M$5:$M$3004,">0"),25,"") | B33: =IF($A33="","",INDEX(Movimientos!$A$5:$A$3004,MATCH($A33,Movimientos!$M$5:$M$3004,0))) | C33: =IF($A33="","",INDEX(Movimientos!$B$5:$B$3004,MATCH($A33,Movimientos!$M$5:$M$3004,0))) | D33: =IF($A33="","",INDEX(Movimientos!$J$5:$J$3004,MATCH($A33,Movimientos!$M$5:$M$3004,0))&"") | E33: =IF($A33="","",IF(C33="Entrada",INDEX(Movimientos!$F$5:$F$3004,MATCH($A33,Movimientos!$M$5:$M$3004,0)),"")) | F33: =IF($A33="","",IF(C33="Salida",INDEX(Movimientos!$F$5:$F$3004,MATCH($A33,Movimientos!$M$5:$M$3004,0)),"")) | G33: =IF($A33="","",INDEX(Movimientos!$I$5:$I$3004,MATCH($A33,Movimientos!$M$5:$M$3004,0))) | H33: =IF($A33="","",INDEX(Movimientos!$G$5:$G$3004,MATCH($A33,Movimientos!$M$5:$M$3004,0))) | I33: =IF($A33="","",INDEX(Movimientos!$H$5:$H$3004,MATCH($A33,Movimientos!$M$5:$M$3004,0))) | J33: =IF($A33="","",INDEX(Movimientos!$K$5:$K$3004,MATCH($A33,Movimientos!$M$5:$M$3004,0))&"")
A34: =IF(26<=COUNTIF(Movimientos!$M$5:$M$3004,">0"),26,"") | B34: =IF($A34="","",INDEX(Movimientos!$A$5:$A$3004,MATCH($A34,Movimientos!$M$5:$M$3004,0))) | C34: =IF($A34="","",INDEX(Movimientos!$B$5:$B$3004,MATCH($A34,Movimientos!$M$5:$M$3004,0))) | D34: =IF($A34="","",INDEX(Movimientos!$J$5:$J$3004,MATCH($A34,Movimientos!$M$5:$M$3004,0))&"") | E34: =IF($A34="","",IF(C34="Entrada",INDEX(Movimientos!$F$5:$F$3004,MATCH($A34,Movimientos!$M$5:$M$3004,0)),"")) | F34: =IF($A34="","",IF(C34="Salida",INDEX(Movimientos!$F$5:$F$3004,MATCH($A34,Movimientos!$M$5:$M$3004,0)),"")) | G34: =IF($A34="","",INDEX(Movimientos!$I$5:$I$3004,MATCH($A34,Movimientos!$M$5:$M$3004,0))) | H34: =IF($A34="","",INDEX(Movimientos!$G$5:$G$3004,MATCH($A34,Movimientos!$M$5:$M$3004,0))) | I34: =IF($A34="","",INDEX(Movimientos!$H$5:$H$3004,MATCH($A34,Movimientos!$M$5:$M$3004,0))) | J34: =IF($A34="","",INDEX(Movimientos!$K$5:$K$3004,MATCH($A34,Movimientos!$M$5:$M$3004,0))&"")
A35: =IF(27<=COUNTIF(Movimientos!$M$5:$M$3004,">0"),27,"") | B35: =IF($A35="","",INDEX(Movimientos!$A$5:$A$3004,MATCH($A35,Movimientos!$M$5:$M$3004,0))) | C35: =IF($A35="","",INDEX(Movimientos!$B$5:$B$3004,MATCH($A35,Movimientos!$M$5:$M$3004,0))) | D35: =IF($A35="","",INDEX(Movimientos!$J$5:$J$3004,MATCH($A35,Movimientos!$M$5:$M$3004,0))&"") | E35: =IF($A35="","",IF(C35="Entrada",INDEX(Movimientos!$F$5:$F$3004,MATCH($A35,Movimientos!$M$5:$M$3004,0)),"")) | F35: =IF($A35="","",IF(C35="Salida",INDEX(Movimientos!$F$5:$F$3004,MATCH($A35,Movimientos!$M$5:$M$3004,0)),"")) | G35: =IF($A35="","",INDEX(Movimientos!$I$5:$I$3004,MATCH($A35,Movimientos!$M$5:$M$3004,0))) | H35: =IF($A35="","",INDEX(Movimientos!$G$5:$G$3004,MATCH($A35,Movimientos!$M$5:$M$3004,0))) | I35: =IF($A35="","",INDEX(Movimientos!$H$5:$H$3004,MATCH($A35,Movimientos!$M$5:$M$3004,0))) | J35: =IF($A35="","",INDEX(Movimientos!$K$5:$K$3004,MATCH($A35,Movimientos!$M$5:$M$3004,0))&"")
A36: =IF(28<=COUNTIF(Movimientos!$M$5:$M$3004,">0"),28,"") | B36: =IF($A36="","",INDEX(Movimientos!$A$5:$A$3004,MATCH($A36,Movimientos!$M$5:$M$3004,0))) | C36: =IF($A36="","",INDEX(Movimientos!$B$5:$B$3004,MATCH($A36,Movimientos!$M$5:$M$3004,0))) | D36: =IF($A36="","",INDEX(Movimientos!$J$5:$J$3004,MATCH($A36,Movimientos!$M$5:$M$3004,0))&"") | E36: =IF($A36="","",IF(C36="Entrada",INDEX(Movimientos!$F$5:$F$3004,MATCH($A36,Movimientos!$M$5:$M$3004,0)),"")) | F36: =IF($A36="","",IF(C36="Salida",INDEX(Movimientos!$F$5:$F$3004,MATCH($A36,Movimientos!$M$5:$M$3004,0)),"")) | G36: =IF($A36="","",INDEX(Movimientos!$I$5:$I$3004,MATCH($A36,Movimientos!$M$5:$M$3004,0))) | H36: =IF($A36="","",INDEX(Movimientos!$G$5:$G$3004,MATCH($A36,Movimientos!$M$5:$M$3004,0))) | I36: =IF($A36="","",INDEX(Movimientos!$H$5:$H$3004,MATCH($A36,Movimientos!$M$5:$M$3004,0))) | J36: =IF($A36="","",INDEX(Movimientos!$K$5:$K$3004,MATCH($A36,Movimientos!$M$5:$M$3004,0))&"")
A37: =IF(29<=COUNTIF(Movimientos!$M$5:$M$3004,">0"),29,"") | B37: =IF($A37="","",INDEX(Movimientos!$A$5:$A$3004,MATCH($A37,Movimientos!$M$5:$M$3004,0))) | C37: =IF($A37="","",INDEX(Movimientos!$B$5:$B$3004,MATCH($A37,Movimientos!$M$5:$M$3004,0))) | D37: =IF($A37="","",INDEX(Movimientos!$J$5:$J$3004,MATCH($A37,Movimientos!$M$5:$M$3004,0))&"") | E37: =IF($A37="","",IF(C37="Entrada",INDEX(Movimientos!$F$5:$F$3004,MATCH($A37,Movimientos!$M$5:$M$3004,0)),"")) | F37: =IF($A37="","",IF(C37="Salida",INDEX(Movimientos!$F$5:$F$3004,MATCH($A37,Movimientos!$M$5:$M$3004,0)),"")) | G37: =IF($A37="","",INDEX(Movimientos!$I$5:$I$3004,MATCH($A37,Movimientos!$M$5:$M$3004,0))) | H37: =IF($A37="","",INDEX(Movimientos!$G$5:$G$3004,MATCH($A37,Movimientos!$M$5:$M$3004,0))) | I37: =IF($A37="","",INDEX(Movimientos!$H$5:$H$3004,MATCH($A37,Movimientos!$M$5:$M$3004,0))) | J37: =IF($A37="","",INDEX(Movimientos!$K$5:$K$3004,MATCH($A37,Movimientos!$M$5:$M$3004,0))&"")
A38: =IF(30<=COUNTIF(Movimientos!$M$5:$M$3004,">0"),30,"") | B38: =IF($A38="","",INDEX(Movimientos!$A$5:$A$3004,MATCH($A38,Movimientos!$M$5:$M$3004,0))) | C38: =IF($A38="","",INDEX(Movimientos!$B$5:$B$3004,MATCH($A38,Movimientos!$M$5:$M$3004,0))) | D38: =IF($A38="","",INDEX(Movimientos!$J$5:$J$3004,MATCH($A38,Movimientos!$M$5:$M$3004,0))&"") | E38: =IF($A38="","",IF(C38="Entrada",INDEX(Movimientos!$F$5:$F$3004,MATCH($A38,Movimientos!$M$5:$M$3004,0)),"")) | F38: =IF($A38="","",IF(C38="Salida",INDEX(Movimientos!$F$5:$F$3004,MATCH($A38,Movimientos!$M$5:$M$3004,0)),"")) | G38: =IF($A38="","",INDEX(Movimientos!$I$5:$I$3004,MATCH($A38,Movimientos!$M$5:$M$3004,0))) | H38: =IF($A38="","",INDEX(Movimientos!$G$5:$G$3004,MATCH($A38,Movimientos!$M$5:$M$3004,0))) | I38: =IF($A38="","",INDEX(Movimientos!$H$5:$H$3004,MATCH($A38,Movimientos!$M$5:$M$3004,0))) | J38: =IF($A38="","",INDEX(Movimientos!$K$5:$K$3004,MATCH($A38,Movimientos!$M$5:$M$3004,0))&"")
A39: =IF(31<=COUNTIF(Movimientos!$M$5:$M$3004,">0"),31,"") | B39: =IF($A39="","",INDEX(Movimientos!$A$5:$A$3004,MATCH($A39,Movimientos!$M$5:$M$3004,0))) | C39: =IF($A39="","",INDEX(Movimientos!$B$5:$B$3004,MATCH($A39,Movimientos!$M$5:$M$3004,0))) | D39: =IF($A39="","",INDEX(Movimientos!$J$5:$J$3004,MATCH($A39,Movimientos!$M$5:$M$3004,0))&"") | E39: =IF($A39="","",IF(C39="Entrada",INDEX(Movimientos!$F$5:$F$3004,MATCH($A39,Movimientos!$M$5:$M$3004,0)),"")) | F39: =IF($A39="","",IF(C39="Salida",INDEX(Movimientos!$F$5:$F$3004,MATCH($A39,Movimientos!$M$5:$M$3004,0)),"")) | G39: =IF($A39="","",INDEX(Movimientos!$I$5:$I$3004,MATCH($A39,Movimientos!$M$5:$M$3004,0))) | H39: =IF($A39="","",INDEX(Movimientos!$G$5:$G$3004,MATCH($A39,Movimientos!$M$5:$M$3004,0))) | I39: =IF($A39="","",INDEX(Movimientos!$H$5:$H$3004,MATCH($A39,Movimientos!$M$5:$M$3004,0))) | J39: =IF($A39="","",INDEX(Movimientos!$K$5:$K$3004,MATCH($A39,Movimientos!$M$5:$M$3004,0))&"")
A40: =IF(32<=COUNTIF(Movimientos!$M$5:$M$3004,">0"),32,"") | B40: =IF($A40="","",INDEX(Movimientos!$A$5:$A$3004,MATCH($A40,Movimientos!$M$5:$M$3004,0))) | C40: =IF($A40="","",INDEX(Movimientos!$B$5:$B$3004,MATCH($A40,Movimientos!$M$5:$M$3004,0))) | D40: =IF($A40="","",INDEX(Movimientos!$J$5:$J$3004,MATCH($A40,Movimientos!$M$5:$M$3004,0))&"") | E40: =IF($A40="","",IF(C40="Entrada",INDEX(Movimientos!$F$5:$F$3004,MATCH($A40,Movimientos!$M$5:$M$3004,0)),"")) | F40: =IF($A40="","",IF(C40="Salida",INDEX(Movimientos!$F$5:$F$3004,MATCH($A40,Movimientos!$M$5:$M$3004,0)),"")) | G40: =IF($A40="","",INDEX(Movimientos!$I$5:$I$3004,MATCH($A40,Movimientos!$M$5:$M$3004,0))) | H40: =IF($A40="","",INDEX(Movimientos!$G$5:$G$3004,MATCH($A40,Movimientos!$M$5:$M$3004,0))) | I40: =IF($A40="","",INDEX(Movimientos!$H$5:$H$3004,MATCH($A40,Movimientos!$M$5:$M$3004,0))) | J40: =IF($A40="","",INDEX(Movimientos!$K$5:$K$3004,MATCH($A40,Movimientos!$M$5:$M$3004,0))&"")
A41: =IF(33<=COUNTIF(Movimientos!$M$5:$M$3004,">0"),33,"") | B41: =IF($A41="","",INDEX(Movimientos!$A$5:$A$3004,MATCH($A41,Movimientos!$M$5:$M$3004,0))) | C41: =IF($A41="","",INDEX(Movimientos!$B$5:$B$3004,MATCH($A41,Movimientos!$M$5:$M$3004,0))) | D41: =IF($A41="","",INDEX(Movimientos!$J$5:$J$3004,MATCH($A41,Movimientos!$M$5:$M$3004,0))&"") | E41: =IF($A41="","",IF(C41="Entrada",INDEX(Movimientos!$F$5:$F$3004,MATCH($A41,Movimientos!$M$5:$M$3004,0)),"")) | F41: =IF($A41="","",IF(C41="Salida",INDEX(Movimientos!$F$5:$F$3004,MATCH($A41,Movimientos!$M$5:$M$3004,0)),"")) | G41: =IF($A41="","",INDEX(Movimientos!$I$5:$I$3004,MATCH($A41,Movimientos!$M$5:$M$3004,0))) | H41: =IF($A41="","",INDEX(Movimientos!$G$5:$G$3004,MATCH($A41,Movimientos!$M$5:$M$3004,0))) | I41: =IF($A41="","",INDEX(Movimientos!$H$5:$H$3004,MATCH($A41,Movimientos!$M$5:$M$3004,0))) | J41: =IF($A41="","",INDEX(Movimientos!$K$5:$K$3004,MATCH($A41,Movimientos!$M$5:$M$3004,0))&"")
A42: =IF(34<=COUNTIF(Movimientos!$M$5:$M$3004,">0"),34,"") | B42: =IF($A42="","",INDEX(Movimientos!$A$5:$A$3004,MATCH($A42,Movimientos!$M$5:$M$3004,0))) | C42: =IF($A42="","",INDEX(Movimientos!$B$5:$B$3004,MATCH($A42,Movimientos!$M$5:$M$3004,0))) | D42: =IF($A42="","",INDEX(Movimientos!$J$5:$J$3004,MATCH($A42,Movimientos!$M$5:$M$3004,0))&"") | E42: =IF($A42="","",IF(C42="Entrada",INDEX(Movimientos!$F$5:$F$3004,MATCH($A42,Movimientos!$M$5:$M$3004,0)),"")) | F42: =IF($A42="","",IF(C42="Salida",INDEX(Movimientos!$F$5:$F$3004,MATCH($A42,Movimientos!$M$5:$M$3004,0)),"")) | G42: =IF($A42="","",INDEX(Movimientos!$I$5:$I$3004,MATCH($A42,Movimientos!$M$5:$M$3004,0))) | H42: =IF($A42="","",INDEX(Movimientos!$G$5:$G$3004,MATCH($A42,Movimientos!$M$5:$M$3004,0))) | I42: =IF($A42="","",INDEX(Movimientos!$H$5:$H$3004,MATCH($A42,Movimientos!$M$5:$M$3004,0))) | J42: =IF($A42="","",INDEX(Movimientos!$K$5:$K$3004,MATCH($A42,Movimientos!$M$5:$M$3004,0))&"")
A43: =IF(35<=COUNTIF(Movimientos!$M$5:$M$3004,">0"),35,"") | B43: =IF($A43="","",INDEX(Movimientos!$A$5:$A$3004,MATCH($A43,Movimientos!$M$5:$M$3004,0))) | C43: =IF($A43="","",INDEX(Movimientos!$B$5:$B$3004,MATCH($A43,Movimientos!$M$5:$M$3004,0))) | D43: =IF($A43="","",INDEX(Movimientos!$J$5:$J$3004,MATCH($A43,Movimientos!$M$5:$M$3004,0))&"") | E43: =IF($A43="","",IF(C43="Entrada",INDEX(Movimientos!$F$5:$F$3004,MATCH($A43,Movimientos!$M$5:$M$3004,0)),"")) | F43: =IF($A43="","",IF(C43="Salida",INDEX(Movimientos!$F$5:$F$3004,MATCH($A43,Movimientos!$M$5:$M$3004,0)),"")) | G43: =IF($A43="","",INDEX(Movimientos!$I$5:$I$3004,MATCH($A43,Movimientos!$M$5:$M$3004,0))) | H43: =IF($A43="","",INDEX(Movimientos!$G$5:$G$3004,MATCH($A43,Movimientos!$M$5:$M$3004,0))) | I43: =IF($A43="","",INDEX(Movimientos!$H$5:$H$3004,MATCH($A43,Movimientos!$M$5:$M$3004,0))) | J43: =IF($A43="","",INDEX(Movimientos!$K$5:$K$3004,MATCH($A43,Movimientos!$M$5:$M$3004,0))&"")
A44: =IF(36<=COUNTIF(Movimientos!$M$5:$M$3004,">0"),36,"") | B44: =IF($A44="","",INDEX(Movimientos!$A$5:$A$3004,MATCH($A44,Movimientos!$M$5:$M$3004,0))) | C44: =IF($A44="","",INDEX(Movimientos!$B$5:$B$3004,MATCH($A44,Movimientos!$M$5:$M$3004,0))) | D44: =IF($A44="","",INDEX(Movimientos!$J$5:$J$3004,MATCH($A44,Movimientos!$M$5:$M$3004,0))&"") | E44: =IF($A44="","",IF(C44="Entrada",INDEX(Movimientos!$F$5:$F$3004,MATCH($A44,Movimientos!$M$5:$M$3004,0)),"")) | F44: =IF($A44="","",IF(C44="Salida",INDEX(Movimientos!$F$5:$F$3004,MATCH($A44,Movimientos!$M$5:$M$3004,0)),"")) | G44: =IF($A44="","",INDEX(Movimientos!$I$5:$I$3004,MATCH($A44,Movimientos!$M$5:$M$3004,0))) | H44: =IF($A44="","",INDEX(Movimientos!$G$5:$G$3004,MATCH($A44,Movimientos!$M$5:$M$3004,0))) | I44: =IF($A44="","",INDEX(Movimientos!$H$5:$H$3004,MATCH($A44,Movimientos!$M$5:$M$3004,0))) | J44: =IF($A44="","",INDEX(Movimientos!$K$5:$K$3004,MATCH($A44,Movimientos!$M$5:$M$3004,0))&"")
A45: =IF(37<=COUNTIF(Movimientos!$M$5:$M$3004,">0"),37,"") | B45: =IF($A45="","",INDEX(Movimientos!$A$5:$A$3004,MATCH($A45,Movimientos!$M$5:$M$3004,0))) | C45: =IF($A45="","",INDEX(Movimientos!$B$5:$B$3004,MATCH($A45,Movimientos!$M$5:$M$3004,0))) | D45: =IF($A45="","",INDEX(Movimientos!$J$5:$J$3004,MATCH($A45,Movimientos!$M$5:$M$3004,0))&"") | E45: =IF($A45="","",IF(C45="Entrada",INDEX(Movimientos!$F$5:$F$3004,MATCH($A45,Movimientos!$M$5:$M$3004,0)),"")) | F45: =IF($A45="","",IF(C45="Salida",INDEX(Movimientos!$F$5:$F$3004,MATCH($A45,Movimientos!$M$5:$M$3004,0)),"")) | G45: =IF($A45="","",INDEX(Movimientos!$I$5:$I$3004,MATCH($A45,Movimientos!$M$5:$M$3004,0))) | H45: =IF($A45="","",INDEX(Movimientos!$G$5:$G$3004,MATCH($A45,Movimientos!$M$5:$M$3004,0))) | I45: =IF($A45="","",INDEX(Movimientos!$H$5:$H$3004,MATCH($A45,Movimientos!$M$5:$M$3004,0))) | J45: =IF($A45="","",INDEX(Movimientos!$K$5:$K$3004,MATCH($A45,Movimientos!$M$5:$M$3004,0))&"")
A46: =IF(38<=COUNTIF(Movimientos!$M$5:$M$3004,">0"),38,"") | B46: =IF($A46="","",INDEX(Movimientos!$A$5:$A$3004,MATCH($A46,Movimientos!$M$5:$M$3004,0))) | C46: =IF($A46="","",INDEX(Movimientos!$B$5:$B$3004,MATCH($A46,Movimientos!$M$5:$M$3004,0))) | D46: =IF($A46="","",INDEX(Movimientos!$J$5:$J$3004,MATCH($A46,Movimientos!$M$5:$M$3004,0))&"") | E46: =IF($A46="","",IF(C46="Entrada",INDEX(Movimientos!$F$5:$F$3004,MATCH($A46,Movimientos!$M$5:$M$3004,0)),"")) | F46: =IF($A46="","",IF(C46="Salida",INDEX(Movimientos!$F$5:$F$3004,MATCH($A46,Movimientos!$M$5:$M$3004,0)),"")) | G46: =IF($A46="","",INDEX(Movimientos!$I$5:$I$3004,MATCH($A46,Movimientos!$M$5:$M$3004,0))) | H46: =IF($A46="","",INDEX(Movimientos!$G$5:$G$3004,MATCH($A46,Movimientos!$M$5:$M$3004,0))) | I46: =IF($A46="","",INDEX(Movimientos!$H$5:$H$3004,MATCH($A46,Movimientos!$M$5:$M$3004,0))) | J46: =IF($A46="","",INDEX(Movimientos!$K$5:$K$3004,MATCH($A46,Movimientos!$M$5:$M$3004,0))&"")
A47: =IF(39<=COUNTIF(Movimientos!$M$5:$M$3004,">0"),39,"") | B47: =IF($A47="","",INDEX(Movimientos!$A$5:$A$3004,MATCH($A47,Movimientos!$M$5:$M$3004,0))) | C47: =IF($A47="","",INDEX(Movimientos!$B$5:$B$3004,MATCH($A47,Movimientos!$M$5:$M$3004,0))) | D47: =IF($A47="","",INDEX(Movimientos!$J$5:$J$3004,MATCH($A47,Movimientos!$M$5:$M$3004,0))&"") | E47: =IF($A47="","",IF(C47="Entrada",INDEX(Movimientos!$F$5:$F$3004,MATCH($A47,Movimientos!$M$5:$M$3004,0)),"")) | F47: =IF($A47="","",IF(C47="Salida",INDEX(Movimientos!$F$5:$F$3004,MATCH($A47,Movimientos!$M$5:$M$3004,0)),"")) | G47: =IF($A47="","",INDEX(Movimientos!$I$5:$I$3004,MATCH($A47,Movimientos!$M$5:$M$3004,0))) | H47: =IF($A47="","",INDEX(Movimientos!$G$5:$G$3004,MATCH($A47,Movimientos!$M$5:$M$3004,0))) | I47: =IF($A47="","",INDEX(Movimientos!$H$5:$H$3004,MATCH($A47,Movimientos!$M$5:$M$3004,0))) | J47: =IF($A47="","",INDEX(Movimientos!$K$5:$K$3004,MATCH($A47,Movimientos!$M$5:$M$3004,0))&"")
A48: =IF(40<=COUNTIF(Movimientos!$M$5:$M$3004,">0"),40,"") | B48: =IF($A48="","",INDEX(Movimientos!$A$5:$A$3004,MATCH($A48,Movimientos!$M$5:$M$3004,0))) | C48: =IF($A48="","",INDEX(Movimientos!$B$5:$B$3004,MATCH($A48,Movimientos!$M$5:$M$3004,0))) | D48: =IF($A48="","",INDEX(Movimientos!$J$5:$J$3004,MATCH($A48,Movimientos!$M$5:$M$3004,0))&"") | E48: =IF($A48="","",IF(C48="Entrada",INDEX(Movimientos!$F$5:$F$3004,MATCH($A48,Movimientos!$M$5:$M$3004,0)),"")) | F48: =IF($A48="","",IF(C48="Salida",INDEX(Movimientos!$F$5:$F$3004,MATCH($A48,Movimientos!$M$5:$M$3004,0)),"")) | G48: =IF($A48="","",INDEX(Movimientos!$I$5:$I$3004,MATCH($A48,Movimientos!$M$5:$M$3004,0))) | H48: =IF($A48="","",INDEX(Movimientos!$G$5:$G$3004,MATCH($A48,Movimientos!$M$5:$M$3004,0))) | I48: =IF($A48="","",INDEX(Movimientos!$H$5:$H$3004,MATCH($A48,Movimientos!$M$5:$M$3004,0))) | J48: =IF($A48="","",INDEX(Movimientos!$K$5:$K$3004,MATCH($A48,Movimientos!$M$5:$M$3004,0))&"")
A49: =IF(41<=COUNTIF(Movimientos!$M$5:$M$3004,">0"),41,"") | B49: =IF($A49="","",INDEX(Movimientos!$A$5:$A$3004,MATCH($A49,Movimientos!$M$5:$M$3004,0))) | C49: =IF($A49="","",INDEX(Movimientos!$B$5:$B$3004,MATCH($A49,Movimientos!$M$5:$M$3004,0))) | D49: =IF($A49="","",INDEX(Movimientos!$J$5:$J$3004,MATCH($A49,Movimientos!$M$5:$M$3004,0))&"") | E49: =IF($A49="","",IF(C49="Entrada",INDEX(Movimientos!$F$5:$F$3004,MATCH($A49,Movimientos!$M$5:$M$3004,0)),"")) | F49: =IF($A49="","",IF(C49="Salida",INDEX(Movimientos!$F$5:$F$3004,MATCH($A49,Movimientos!$M$5:$M$3004,0)),"")) | G49: =IF($A49="","",INDEX(Movimientos!$I$5:$I$3004,MATCH($A49,Movimientos!$M$5:$M$3004,0))) | H49: =IF($A49="","",INDEX(Movimientos!$G$5:$G$3004,MATCH($A49,Movimientos!$M$5:$M$3004,0))) | I49: =IF($A49="","",INDEX(Movimientos!$H$5:$H$3004,MATCH($A49,Movimientos!$M$5:$M$3004,0))) | J49: =IF($A49="","",INDEX(Movimientos!$K$5:$K$3004,MATCH($A49,Movimientos!$M$5:$M$3004,0))&"")
A50: =IF(42<=COUNTIF(Movimientos!$M$5:$M$3004,">0"),42,"") | B50: =IF($A50="","",INDEX(Movimientos!$A$5:$A$3004,MATCH($A50,Movimientos!$M$5:$M$3004,0))) | C50: =IF($A50="","",INDEX(Movimientos!$B$5:$B$3004,MATCH($A50,Movimientos!$M$5:$M$3004,0))) | D50: =IF($A50="","",INDEX(Movimientos!$J$5:$J$3004,MATCH($A50,Movimientos!$M$5:$M$3004,0))&"") | E50: =IF($A50="","",IF(C50="Entrada",INDEX(Movimientos!$F$5:$F$3004,MATCH($A50,Movimientos!$M$5:$M$3004,0)),"")) | F50: =IF($A50="","",IF(C50="Salida",INDEX(Movimientos!$F$5:$F$3004,MATCH($A50,Movimientos!$M$5:$M$3004,0)),"")) | G50: =IF($A50="","",INDEX(Movimientos!$I$5:$I$3004,MATCH($A50,Movimientos!$M$5:$M$3004,0))) | H50: =IF($A50="","",INDEX(Movimientos!$G$5:$G$3004,MATCH($A50,Movimientos!$M$5:$M$3004,0))) | I50: =IF($A50="","",INDEX(Movimientos!$H$5:$H$3004,MATCH($A50,Movimientos!$M$5:$M$3004,0))) | J50: =IF($A50="","",INDEX(Movimientos!$K$5:$K$3004,MATCH($A50,Movimientos!$M$5:$M$3004,0))&"")
A51: =IF(43<=COUNTIF(Movimientos!$M$5:$M$3004,">0"),43,"") | B51: =IF($A51="","",INDEX(Movimientos!$A$5:$A$3004,MATCH($A51,Movimientos!$M$5:$M$3004,0))) | C51: =IF($A51="","",INDEX(Movimientos!$B$5:$B$3004,MATCH($A51,Movimientos!$M$5:$M$3004,0))) | D51: =IF($A51="","",INDEX(Movimientos!$J$5:$J$3004,MATCH($A51,Movimientos!$M$5:$M$3004,0))&"") | E51: =IF($A51="","",IF(C51="Entrada",INDEX(Movimientos!$F$5:$F$3004,MATCH($A51,Movimientos!$M$5:$M$3004,0)),"")) | F51: =IF($A51="","",IF(C51="Salida",INDEX(Movimientos!$F$5:$F$3004,MATCH($A51,Movimientos!$M$5:$M$3004,0)),"")) | G51: =IF($A51="","",INDEX(Movimientos!$I$5:$I$3004,MATCH($A51,Movimientos!$M$5:$M$3004,0))) | H51: =IF($A51="","",INDEX(Movimientos!$G$5:$G$3004,MATCH($A51,Movimientos!$M$5:$M$3004,0))) | I51: =IF($A51="","",INDEX(Movimientos!$H$5:$H$3004,MATCH($A51,Movimientos!$M$5:$M$3004,0))) | J51: =IF($A51="","",INDEX(Movimientos!$K$5:$K$3004,MATCH($A51,Movimientos!$M$5:$M$3004,0))&"")
A52: =IF(44<=COUNTIF(Movimientos!$M$5:$M$3004,">0"),44,"") | B52: =IF($A52="","",INDEX(Movimientos!$A$5:$A$3004,MATCH($A52,Movimientos!$M$5:$M$3004,0))) | C52: =IF($A52="","",INDEX(Movimientos!$B$5:$B$3004,MATCH($A52,Movimientos!$M$5:$M$3004,0))) | D52: =IF($A52="","",INDEX(Movimientos!$J$5:$J$3004,MATCH($A52,Movimientos!$M$5:$M$3004,0))&"") | E52: =IF($A52="","",IF(C52="Entrada",INDEX(Movimientos!$F$5:$F$3004,MATCH($A52,Movimientos!$M$5:$M$3004,0)),"")) | F52: =IF($A52="","",IF(C52="Salida",INDEX(Movimientos!$F$5:$F$3004,MATCH($A52,Movimientos!$M$5:$M$3004,0)),"")) | G52: =IF($A52="","",INDEX(Movimientos!$I$5:$I$3004,MATCH($A52,Movimientos!$M$5:$M$3004,0))) | H52: =IF($A52="","",INDEX(Movimientos!$G$5:$G$3004,MATCH($A52,Movimientos!$M$5:$M$3004,0))) | I52: =IF($A52="","",INDEX(Movimientos!$H$5:$H$3004,MATCH($A52,Movimientos!$M$5:$M$3004,0))) | J52: =IF($A52="","",INDEX(Movimientos!$K$5:$K$3004,MATCH($A52,Movimientos!$M$5:$M$3004,0))&"")
A53: =IF(45<=COUNTIF(Movimientos!$M$5:$M$3004,">0"),45,"") | B53: =IF($A53="","",INDEX(Movimientos!$A$5:$A$3004,MATCH($A53,Movimientos!$M$5:$M$3004,0))) | C53: =IF($A53="","",INDEX(Movimientos!$B$5:$B$3004,MATCH($A53,Movimientos!$M$5:$M$3004,0))) | D53: =IF($A53="","",INDEX(Movimientos!$J$5:$J$3004,MATCH($A53,Movimientos!$M$5:$M$3004,0))&"") | E53: =IF($A53="","",IF(C53="Entrada",INDEX(Movimientos!$F$5:$F$3004,MATCH($A53,Movimientos!$M$5:$M$3004,0)),"")) | F53: =IF($A53="","",IF(C53="Salida",INDEX(Movimientos!$F$5:$F$3004,MATCH($A53,Movimientos!$M$5:$M$3004,0)),"")) | G53: =IF($A53="","",INDEX(Movimientos!$I$5:$I$3004,MATCH($A53,Movimientos!$M$5:$M$3004,0))) | H53: =IF($A53="","",INDEX(Movimientos!$G$5:$G$3004,MATCH($A53,Movimientos!$M$5:$M$3004,0))) | I53: =IF($A53="","",INDEX(Movimientos!$H$5:$H$3004,MATCH($A53,Movimientos!$M$5:$M$3004,0))) | J53: =IF($A53="","",INDEX(Movimientos!$K$5:$K$3004,MATCH($A53,Movimientos!$M$5:$M$3004,0))&"")
A54: =IF(46<=COUNTIF(Movimientos!$M$5:$M$3004,">0"),46,"") | B54: =IF($A54="","",INDEX(Movimientos!$A$5:$A$3004,MATCH($A54,Movimientos!$M$5:$M$3004,0))) | C54: =IF($A54="","",INDEX(Movimientos!$B$5:$B$3004,MATCH($A54,Movimientos!$M$5:$M$3004,0))) | D54: =IF($A54="","",INDEX(Movimientos!$J$5:$J$3004,MATCH($A54,Movimientos!$M$5:$M$3004,0))&"") | E54: =IF($A54="","",IF(C54="Entrada",INDEX(Movimientos!$F$5:$F$3004,MATCH($A54,Movimientos!$M$5:$M$3004,0)),"")) | F54: =IF($A54="","",IF(C54="Salida",INDEX(Movimientos!$F$5:$F$3004,MATCH($A54,Movimientos!$M$5:$M$3004,0)),"")) | G54: =IF($A54="","",INDEX(Movimientos!$I$5:$I$3004,MATCH($A54,Movimientos!$M$5:$M$3004,0))) | H54: =IF($A54="","",INDEX(Movimientos!$G$5:$G$3004,MATCH($A54,Movimientos!$M$5:$M$3004,0))) | I54: =IF($A54="","",INDEX(Movimientos!$H$5:$H$3004,MATCH($A54,Movimientos!$M$5:$M$3004,0))) | J54: =IF($A54="","",INDEX(Movimientos!$K$5:$K$3004,MATCH($A54,Movimientos!$M$5:$M$3004,0))&"")
A55: =IF(47<=COUNTIF(Movimientos!$M$5:$M$3004,">0"),47,"") | B55: =IF($A55="","",INDEX(Movimientos!$A$5:$A$3004,MATCH($A55,Movimientos!$M$5:$M$3004,0))) | C55: =IF($A55="","",INDEX(Movimientos!$B$5:$B$3004,MATCH($A55,Movimientos!$M$5:$M$3004,0))) | D55: =IF($A55="","",INDEX(Movimientos!$J$5:$J$3004,MATCH($A55,Movimientos!$M$5:$M$3004,0))&"") | E55: =IF($A55="","",IF(C55="Entrada",INDEX(Movimientos!$F$5:$F$3004,MATCH($A55,Movimientos!$M$5:$M$3004,0)),"")) | F55: =IF($A55="","",IF(C55="Salida",INDEX(Movimientos!$F$5:$F$3004,MATCH($A55,Movimientos!$M$5:$M$3004,0)),"")) | G55: =IF($A55="","",INDEX(Movimientos!$I$5:$I$3004,MATCH($A55,Movimientos!$M$5:$M$3004,0))) | H55: =IF($A55="","",INDEX(Movimientos!$G$5:$G$3004,MATCH($A55,Movimientos!$M$5:$M$3004,0))) | I55: =IF($A55="","",INDEX(Movimientos!$H$5:$H$3004,MATCH($A55,Movimientos!$M$5:$M$3004,0))) | J55: =IF($A55="","",INDEX(Movimientos!$K$5:$K$3004,MATCH($A55,Movimientos!$M$5:$M$3004,0))&"")
A56: =IF(48<=COUNTIF(Movimientos!$M$5:$M$3004,">0"),48,"") | B56: =IF($A56="","",INDEX(Movimientos!$A$5:$A$3004,MATCH($A56,Movimientos!$M$5:$M$3004,0))) | C56: =IF($A56="","",INDEX(Movimientos!$B$5:$B$3004,MATCH($A56,Movimientos!$M$5:$M$3004,0))) | D56: =IF($A56="","",INDEX(Movimientos!$J$5:$J$3004,MATCH($A56,Movimientos!$M$5:$M$3004,0))&"") | E56: =IF($A56="","",IF(C56="Entrada",INDEX(Movimientos!$F$5:$F$3004,MATCH($A56,Movimientos!$M$5:$M$3004,0)),"")) | F56: =IF($A56="","",IF(C56="Salida",INDEX(Movimientos!$F$5:$F$3004,MATCH($A56,Movimientos!$M$5:$M$3004,0)),"")) | G56: =IF($A56="","",INDEX(Movimientos!$I$5:$I$3004,MATCH($A56,Movimientos!$M$5:$M$3004,0))) | H56: =IF($A56="","",INDEX(Movimientos!$G$5:$G$3004,MATCH($A56,Movimientos!$M$5:$M$3004,0))) | I56: =IF($A56="","",INDEX(Movimientos!$H$5:$H$3004,MATCH($A56,Movimientos!$M$5:$M$3004,0))) | J56: =IF($A56="","",INDEX(Movimientos!$K$5:$K$3004,MATCH($A56,Movimientos!$M$5:$M$3004,0))&"")
A57: =IF(49<=COUNTIF(Movimientos!$M$5:$M$3004,">0"),49,"") | B57: =IF($A57="","",INDEX(Movimientos!$A$5:$A$3004,MATCH($A57,Movimientos!$M$5:$M$3004,0))) | C57: =IF($A57="","",INDEX(Movimientos!$B$5:$B$3004,MATCH($A57,Movimientos!$M$5:$M$3004,0))) | D57: =IF($A57="","",INDEX(Movimientos!$J$5:$J$3004,MATCH($A57,Movimientos!$M$5:$M$3004,0))&"") | E57: =IF($A57="","",IF(C57="Entrada",INDEX(Movimientos!$F$5:$F$3004,MATCH($A57,Movimientos!$M$5:$M$3004,0)),"")) | F57: =IF($A57="","",IF(C57="Salida",INDEX(Movimientos!$F$5:$F$3004,MATCH($A57,Movimientos!$M$5:$M$3004,0)),"")) | G57: =IF($A57="","",INDEX(Movimientos!$I$5:$I$3004,MATCH($A57,Movimientos!$M$5:$M$3004,0))) | H57: =IF($A57="","",INDEX(Movimientos!$G$5:$G$3004,MATCH($A57,Movimientos!$M$5:$M$3004,0))) | I57: =IF($A57="","",INDEX(Movimientos!$H$5:$H$3004,MATCH($A57,Movimientos!$M$5:$M$3004,0))) | J57: =IF($A57="","",INDEX(Movimientos!$K$5:$K$3004,MATCH($A57,Movimientos!$M$5:$M$3004,0))&"")
A58: =IF(50<=COUNTIF(Movimientos!$M$5:$M$3004,">0"),50,"") | B58: =IF($A58="","",INDEX(Movimientos!$A$5:$A$3004,MATCH($A58,Movimientos!$M$5:$M$3004,0))) | C58: =IF($A58="","",INDEX(Movimientos!$B$5:$B$3004,MATCH($A58,Movimientos!$M$5:$M$3004,0))) | D58: =IF($A58="","",INDEX(Movimientos!$J$5:$J$3004,MATCH($A58,Movimientos!$M$5:$M$3004,0))&"") | E58: =IF($A58="","",IF(C58="Entrada",INDEX(Movimientos!$F$5:$F$3004,MATCH($A58,Movimientos!$M$5:$M$3004,0)),"")) | F58: =IF($A58="","",IF(C58="Salida",INDEX(Movimientos!$F$5:$F$3004,MATCH($A58,Movimientos!$M$5:$M$3004,0)),"")) | G58: =IF($A58="","",INDEX(Movimientos!$I$5:$I$3004,MATCH($A58,Movimientos!$M$5:$M$3004,0))) | H58: =IF($A58="","",INDEX(Movimientos!$G$5:$G$3004,MATCH($A58,Movimientos!$M$5:$M$3004,0))) | I58: =IF($A58="","",INDEX(Movimientos!$H$5:$H$3004,MATCH($A58,Movimientos!$M$5:$M$3004,0))) | J58: =IF($A58="","",INDEX(Movimientos!$K$5:$K$3004,MATCH($A58,Movimientos!$M$5:$M$3004,0))&"")
A59: =IF(51<=COUNTIF(Movimientos!$M$5:$M$3004,">0"),51,"") | B59: =IF($A59="","",INDEX(Movimientos!$A$5:$A$3004,MATCH($A59,Movimientos!$M$5:$M$3004,0))) | C59: =IF($A59="","",INDEX(Movimientos!$B$5:$B$3004,MATCH($A59,Movimientos!$M$5:$M$3004,0))) | D59: =IF($A59="","",INDEX(Movimientos!$J$5:$J$3004,MATCH($A59,Movimientos!$M$5:$M$3004,0))&"") | E59: =IF($A59="","",IF(C59="Entrada",INDEX(Movimientos!$F$5:$F$3004,MATCH($A59,Movimientos!$M$5:$M$3004,0)),"")) | F59: =IF($A59="","",IF(C59="Salida",INDEX(Movimientos!$F$5:$F$3004,MATCH($A59,Movimientos!$M$5:$M$3004,0)),"")) | G59: =IF($A59="","",INDEX(Movimientos!$I$5:$I$3004,MATCH($A59,Movimientos!$M$5:$M$3004,0))) | H59: =IF($A59="","",INDEX(Movimientos!$G$5:$G$3004,MATCH($A59,Movimientos!$M$5:$M$3004,0))) | I59: =IF($A59="","",INDEX(Movimientos!$H$5:$H$3004,MATCH($A59,Movimientos!$M$5:$M$3004,0))) | J59: =IF($A59="","",INDEX(Movimientos!$K$5:$K$3004,MATCH($A59,Movimientos!$M$5:$M$3004,0))&"")
A60: =IF(52<=COUNTIF(Movimientos!$M$5:$M$3004,">0"),52,"") | B60: =IF($A60="","",INDEX(Movimientos!$A$5:$A$3004,MATCH($A60,Movimientos!$M$5:$M$3004,0))) | C60: =IF($A60="","",INDEX(Movimientos!$B$5:$B$3004,MATCH($A60,Movimientos!$M$5:$M$3004,0))) | D60: =IF($A60="","",INDEX(Movimientos!$J$5:$J$3004,MATCH($A60,Movimientos!$M$5:$M$3004,0))&"") | E60: =IF($A60="","",IF(C60="Entrada",INDEX(Movimientos!$F$5:$F$3004,MATCH($A60,Movimientos!$M$5:$M$3004,0)),"")) | F60: =IF($A60="","",IF(C60="Salida",INDEX(Movimientos!$F$5:$F$3004,MATCH($A60,Movimientos!$M$5:$M$3004,0)),"")) | G60: =IF($A60="","",INDEX(Movimientos!$I$5:$I$3004,MATCH($A60,Movimientos!$M$5:$M$3004,0))) | H60: =IF($A60="","",INDEX(Movimientos!$G$5:$G$3004,MATCH($A60,Movimientos!$M$5:$M$3004,0))) | I60: =IF($A60="","",INDEX(Movimientos!$H$5:$H$3004,MATCH($A60,Movimientos!$M$5:$M$3004,0))) | J60: =IF($A60="","",INDEX(Movimientos!$K$5:$K$3004,MATCH($A60,Movimientos!$M$5:$M$3004,0))&"")
A61: =IF(53<=COUNTIF(Movimientos!$M$5:$M$3004,">0"),53,"") | B61: =IF($A61="","",INDEX(Movimientos!$A$5:$A$3004,MATCH($A61,Movimientos!$M$5:$M$3004,0))) | C61: =IF($A61="","",INDEX(Movimientos!$B$5:$B$3004,MATCH($A61,Movimientos!$M$5:$M$3004,0))) | D61: =IF($A61="","",INDEX(Movimientos!$J$5:$J$3004,MATCH($A61,Movimientos!$M$5:$M$3004,0))&"") | E61: =IF($A61="","",IF(C61="Entrada",INDEX(Movimientos!$F$5:$F$3004,MATCH($A61,Movimientos!$M$5:$M$3004,0)),"")) | F61: =IF($A61="","",IF(C61="Salida",INDEX(Movimientos!$F$5:$F$3004,MATCH($A61,Movimientos!$M$5:$M$3004,0)),"")) | G61: =IF($A61="","",INDEX(Movimientos!$I$5:$I$3004,MATCH($A61,Movimientos!$M$5:$M$3004,0))) | H61: =IF($A61="","",INDEX(Movimientos!$G$5:$G$3004,MATCH($A61,Movimientos!$M$5:$M$3004,0))) | I61: =IF($A61="","",INDEX(Movimientos!$H$5:$H$3004,MATCH($A61,Movimientos!$M$5:$M$3004,0))) | J61: =IF($A61="","",INDEX(Movimientos!$K$5:$K$3004,MATCH($A61,Movimientos!$M$5:$M$3004,0))&"")
A62: =IF(54<=COUNTIF(Movimientos!$M$5:$M$3004,">0"),54,"") | B62: =IF($A62="","",INDEX(Movimientos!$A$5:$A$3004,MATCH($A62,Movimientos!$M$5:$M$3004,0))) | C62: =IF($A62="","",INDEX(Movimientos!$B$5:$B$3004,MATCH($A62,Movimientos!$M$5:$M$3004,0))) | D62: =IF($A62="","",INDEX(Movimientos!$J$5:$J$3004,MATCH($A62,Movimientos!$M$5:$M$3004,0))&"") | E62: =IF($A62="","",IF(C62="Entrada",INDEX(Movimientos!$F$5:$F$3004,MATCH($A62,Movimientos!$M$5:$M$3004,0)),"")) | F62: =IF($A62="","",IF(C62="Salida",INDEX(Movimientos!$F$5:$F$3004,MATCH($A62,Movimientos!$M$5:$M$3004,0)),"")) | G62: =IF($A62="","",INDEX(Movimientos!$I$5:$I$3004,MATCH($A62,Movimientos!$M$5:$M$3004,0))) | H62: =IF($A62="","",INDEX(Movimientos!$G$5:$G$3004,MATCH($A62,Movimientos!$M$5:$M$3004,0))) | I62: =IF($A62="","",INDEX(Movimientos!$H$5:$H$3004,MATCH($A62,Movimientos!$M$5:$M$3004,0))) | J62: =IF($A62="","",INDEX(Movimientos!$K$5:$K$3004,MATCH($A62,Movimientos!$M$5:$M$3004,0))&"")
A63: =IF(55<=COUNTIF(Movimientos!$M$5:$M$3004,">0"),55,"") | B63: =IF($A63="","",INDEX(Movimientos!$A$5:$A$3004,MATCH($A63,Movimientos!$M$5:$M$3004,0))) | C63: =IF($A63="","",INDEX(Movimientos!$B$5:$B$3004,MATCH($A63,Movimientos!$M$5:$M$3004,0))) | D63: =IF($A63="","",INDEX(Movimientos!$J$5:$J$3004,MATCH($A63,Movimientos!$M$5:$M$3004,0))&"") | E63: =IF($A63="","",IF(C63="Entrada",INDEX(Movimientos!$F$5:$F$3004,MATCH($A63,Movimientos!$M$5:$M$3004,0)),"")) | F63: =IF($A63="","",IF(C63="Salida",INDEX(Movimientos!$F$5:$F$3004,MATCH($A63,Movimientos!$M$5:$M$3004,0)),"")) | G63: =IF($A63="","",INDEX(Movimientos!$I$5:$I$3004,MATCH($A63,Movimientos!$M$5:$M$3004,0))) | H63: =IF($A63="","",INDEX(Movimientos!$G$5:$G$3004,MATCH($A63,Movimientos!$M$5:$M$3004,0))) | I63: =IF($A63="","",INDEX(Movimientos!$H$5:$H$3004,MATCH($A63,Movimientos!$M$5:$M$3004,0))) | J63: =IF($A63="","",INDEX(Movimientos!$K$5:$K$3004,MATCH($A63,Movimientos!$M$5:$M$3004,0))&"")
A64: =IF(56<=COUNTIF(Movimientos!$M$5:$M$3004,">0"),56,"") | B64: =IF($A64="","",INDEX(Movimientos!$A$5:$A$3004,MATCH($A64,Movimientos!$M$5:$M$3004,0))) | C64: =IF($A64="","",INDEX(Movimientos!$B$5:$B$3004,MATCH($A64,Movimientos!$M$5:$M$3004,0))) | D64: =IF($A64="","",INDEX(Movimientos!$J$5:$J$3004,MATCH($A64,Movimientos!$M$5:$M$3004,0))&"") | E64: =IF($A64="","",IF(C64="Entrada",INDEX(Movimientos!$F$5:$F$3004,MATCH($A64,Movimientos!$M$5:$M$3004,0)),"")) | F64: =IF($A64="","",IF(C64="Salida",INDEX(Movimientos!$F$5:$F$3004,MATCH($A64,Movimientos!$M$5:$M$3004,0)),"")) | G64: =IF($A64="","",INDEX(Movimientos!$I$5:$I$3004,MATCH($A64,Movimientos!$M$5:$M$3004,0))) | H64: =IF($A64="","",INDEX(Movimientos!$G$5:$G$3004,MATCH($A64,Movimientos!$M$5:$M$3004,0))) | I64: =IF($A64="","",INDEX(Movimientos!$H$5:$H$3004,MATCH($A64,Movimientos!$M$5:$M$3004,0))) | J64: =IF($A64="","",INDEX(Movimientos!$K$5:$K$3004,MATCH($A64,Movimientos!$M$5:$M$3004,0))&"")
A65: =IF(57<=COUNTIF(Movimientos!$M$5:$M$3004,">0"),57,"") | B65: =IF($A65="","",INDEX(Movimientos!$A$5:$A$3004,MATCH($A65,Movimientos!$M$5:$M$3004,0))) | C65: =IF($A65="","",INDEX(Movimientos!$B$5:$B$3004,MATCH($A65,Movimientos!$M$5:$M$3004,0))) | D65: =IF($A65="","",INDEX(Movimientos!$J$5:$J$3004,MATCH($A65,Movimientos!$M$5:$M$3004,0))&"") | E65: =IF($A65="","",IF(C65="Entrada",INDEX(Movimientos!$F$5:$F$3004,MATCH($A65,Movimientos!$M$5:$M$3004,0)),"")) | F65: =IF($A65="","",IF(C65="Salida",INDEX(Movimientos!$F$5:$F$3004,MATCH($A65,Movimientos!$M$5:$M$3004,0)),"")) | G65: =IF($A65="","",INDEX(Movimientos!$I$5:$I$3004,MATCH($A65,Movimientos!$M$5:$M$3004,0))) | H65: =IF($A65="","",INDEX(Movimientos!$G$5:$G$3004,MATCH($A65,Movimientos!$M$5:$M$3004,0))) | I65: =IF($A65="","",INDEX(Movimientos!$H$5:$H$3004,MATCH($A65,Movimientos!$M$5:$M$3004,0))) | J65: =IF($A65="","",INDEX(Movimientos!$K$5:$K$3004,MATCH($A65,Movimientos!$M$5:$M$3004,0))&"")
A66: =IF(58<=COUNTIF(Movimientos!$M$5:$M$3004,">0"),58,"") | B66: =IF($A66="","",INDEX(Movimientos!$A$5:$A$3004,MATCH($A66,Movimientos!$M$5:$M$3004,0))) | C66: =IF($A66="","",INDEX(Movimientos!$B$5:$B$3004,MATCH($A66,Movimientos!$M$5:$M$3004,0))) | D66: =IF($A66="","",INDEX(Movimientos!$J$5:$J$3004,MATCH($A66,Movimientos!$M$5:$M$3004,0))&"") | E66: =IF($A66="","",IF(C66="Entrada",INDEX(Movimientos!$F$5:$F$3004,MATCH($A66,Movimientos!$M$5:$M$3004,0)),"")) | F66: =IF($A66="","",IF(C66="Salida",INDEX(Movimientos!$F$5:$F$3004,MATCH($A66,Movimientos!$M$5:$M$3004,0)),"")) | G66: =IF($A66="","",INDEX(Movimientos!$I$5:$I$3004,MATCH($A66,Movimientos!$M$5:$M$3004,0))) | H66: =IF($A66="","",INDEX(Movimientos!$G$5:$G$3004,MATCH($A66,Movimientos!$M$5:$M$3004,0))) | I66: =IF($A66="","",INDEX(Movimientos!$H$5:$H$3004,MATCH($A66,Movimientos!$M$5:$M$3004,0))) | J66: =IF($A66="","",INDEX(Movimientos!$K$5:$K$3004,MATCH($A66,Movimientos!$M$5:$M$3004,0))&"")
A67: =IF(59<=COUNTIF(Movimientos!$M$5:$M$3004,">0"),59,"") | B67: =IF($A67="","",INDEX(Movimientos!$A$5:$A$3004,MATCH($A67,Movimientos!$M$5:$M$3004,0))) | C67: =IF($A67="","",INDEX(Movimientos!$B$5:$B$3004,MATCH($A67,Movimientos!$M$5:$M$3004,0))) | D67: =IF($A67="","",INDEX(Movimientos!$J$5:$J$3004,MATCH($A67,Movimientos!$M$5:$M$3004,0))&"") | E67: =IF($A67="","",IF(C67="Entrada",INDEX(Movimientos!$F$5:$F$3004,MATCH($A67,Movimientos!$M$5:$M$3004,0)),"")) | F67: =IF($A67="","",IF(C67="Salida",INDEX(Movimientos!$F$5:$F$3004,MATCH($A67,Movimientos!$M$5:$M$3004,0)),"")) | G67: =IF($A67="","",INDEX(Movimientos!$I$5:$I$3004,MATCH($A67,Movimientos!$M$5:$M$3004,0))) | H67: =IF($A67="","",INDEX(Movimientos!$G$5:$G$3004,MATCH($A67,Movimientos!$M$5:$M$3004,0))) | I67: =IF($A67="","",INDEX(Movimientos!$H$5:$H$3004,MATCH($A67,Movimientos!$M$5:$M$3004,0))) | J67: =IF($A67="","",INDEX(Movimientos!$K$5:$K$3004,MATCH($A67,Movimientos!$M$5:$M$3004,0))&"")
A68: =IF(60<=COUNTIF(Movimientos!$M$5:$M$3004,">0"),60,"") | B68: =IF($A68="","",INDEX(Movimientos!$A$5:$A$3004,MATCH($A68,Movimientos!$M$5:$M$3004,0))) | C68: =IF($A68="","",INDEX(Movimientos!$B$5:$B$3004,MATCH($A68,Movimientos!$M$5:$M$3004,0))) | D68: =IF($A68="","",INDEX(Movimientos!$J$5:$J$3004,MATCH($A68,Movimientos!$M$5:$M$3004,0))&"") | E68: =IF($A68="","",IF(C68="Entrada",INDEX(Movimientos!$F$5:$F$3004,MATCH($A68,Movimientos!$M$5:$M$3004,0)),"")) | F68: =IF($A68="","",IF(C68="Salida",INDEX(Movimientos!$F$5:$F$3004,MATCH($A68,Movimientos!$M$5:$M$3004,0)),"")) | G68: =IF($A68="","",INDEX(Movimientos!$I$5:$I$3004,MATCH($A68,Movimientos!$M$5:$M$3004,0))) | H68: =IF($A68="","",INDEX(Movimientos!$G$5:$G$3004,MATCH($A68,Movimientos!$M$5:$M$3004,0))) | I68: =IF($A68="","",INDEX(Movimientos!$H$5:$H$3004,MATCH($A68,Movimientos!$M$5:$M$3004,0))) | J68: =IF($A68="","",INDEX(Movimientos!$K$5:$K$3004,MATCH($A68,Movimientos!$M$5:$M$3004,0))&"")
A69: =IF(61<=COUNTIF(Movimientos!$M$5:$M$3004,">0"),61,"") | B69: =IF($A69="","",INDEX(Movimientos!$A$5:$A$3004,MATCH($A69,Movimientos!$M$5:$M$3004,0))) | C69: =IF($A69="","",INDEX(Movimientos!$B$5:$B$3004,MATCH($A69,Movimientos!$M$5:$M$3004,0))) | D69: =IF($A69="","",INDEX(Movimientos!$J$5:$J$3004,MATCH($A69,Movimientos!$M$5:$M$3004,0))&"") | E69: =IF($A69="","",IF(C69="Entrada",INDEX(Movimientos!$F$5:$F$3004,MATCH($A69,Movimientos!$M$5:$M$3004,0)),"")) | F69: =IF($A69="","",IF(C69="Salida",INDEX(Movimientos!$F$5:$F$3004,MATCH($A69,Movimientos!$M$5:$M$3004,0)),"")) | G69: =IF($A69="","",INDEX(Movimientos!$I$5:$I$3004,MATCH($A69,Movimientos!$M$5:$M$3004,0))) | H69: =IF($A69="","",INDEX(Movimientos!$G$5:$G$3004,MATCH($A69,Movimientos!$M$5:$M$3004,0))) | I69: =IF($A69="","",INDEX(Movimientos!$H$5:$H$3004,MATCH($A69,Movimientos!$M$5:$M$3004,0))) | J69: =IF($A69="","",INDEX(Movimientos!$K$5:$K$3004,MATCH($A69,Movimientos!$M$5:$M$3004,0))&"")
A70: =IF(62<=COUNTIF(Movimientos!$M$5:$M$3004,">0"),62,"") | B70: =IF($A70="","",INDEX(Movimientos!$A$5:$A$3004,MATCH($A70,Movimientos!$M$5:$M$3004,0))) | C70: =IF($A70="","",INDEX(Movimientos!$B$5:$B$3004,MATCH($A70,Movimientos!$M$5:$M$3004,0))) | D70: =IF($A70="","",INDEX(Movimientos!$J$5:$J$3004,MATCH($A70,Movimientos!$M$5:$M$3004,0))&"") | E70: =IF($A70="","",IF(C70="Entrada",INDEX(Movimientos!$F$5:$F$3004,MATCH($A70,Movimientos!$M$5:$M$3004,0)),"")) | F70: =IF($A70="","",IF(C70="Salida",INDEX(Movimientos!$F$5:$F$3004,MATCH($A70,Movimientos!$M$5:$M$3004,0)),"")) | G70: =IF($A70="","",INDEX(Movimientos!$I$5:$I$3004,MATCH($A70,Movimientos!$M$5:$M$3004,0))) | H70: =IF($A70="","",INDEX(Movimientos!$G$5:$G$3004,MATCH($A70,Movimientos!$M$5:$M$3004,0))) | I70: =IF($A70="","",INDEX(Movimientos!$H$5:$H$3004,MATCH($A70,Movimientos!$M$5:$M$3004,0))) | J70: =IF($A70="","",INDEX(Movimientos!$K$5:$K$3004,MATCH($A70,Movimientos!$M$5:$M$3004,0))&"")
A71: =IF(63<=COUNTIF(Movimientos!$M$5:$M$3004,">0"),63,"") | B71: =IF($A71="","",INDEX(Movimientos!$A$5:$A$3004,MATCH($A71,Movimientos!$M$5:$M$3004,0))) | C71: =IF($A71="","",INDEX(Movimientos!$B$5:$B$3004,MATCH($A71,Movimientos!$M$5:$M$3004,0))) | D71: =IF($A71="","",INDEX(Movimientos!$J$5:$J$3004,MATCH($A71,Movimientos!$M$5:$M$3004,0))&"") | E71: =IF($A71="","",IF(C71="Entrada",INDEX(Movimientos!$F$5:$F$3004,MATCH($A71,Movimientos!$M$5:$M$3004,0)),"")) | F71: =IF($A71="","",IF(C71="Salida",INDEX(Movimientos!$F$5:$F$3004,MATCH($A71,Movimientos!$M$5:$M$3004,0)),"")) | G71: =IF($A71="","",INDEX(Movimientos!$I$5:$I$3004,MATCH($A71,Movimientos!$M$5:$M$3004,0))) | H71: =IF($A71="","",INDEX(Movimientos!$G$5:$G$3004,MATCH($A71,Movimientos!$M$5:$M$3004,0))) | I71: =IF($A71="","",INDEX(Movimientos!$H$5:$H$3004,MATCH($A71,Movimientos!$M$5:$M$3004,0))) | J71: =IF($A71="","",INDEX(Movimientos!$K$5:$K$3004,MATCH($A71,Movimientos!$M$5:$M$3004,0))&"")
A72: =IF(64<=COUNTIF(Movimientos!$M$5:$M$3004,">0"),64,"") | B72: =IF($A72="","",INDEX(Movimientos!$A$5:$A$3004,MATCH($A72,Movimientos!$M$5:$M$3004,0))) | C72: =IF($A72="","",INDEX(Movimientos!$B$5:$B$3004,MATCH($A72,Movimientos!$M$5:$M$3004,0))) | D72: =IF($A72="","",INDEX(Movimientos!$J$5:$J$3004,MATCH($A72,Movimientos!$M$5:$M$3004,0))&"") | E72: =IF($A72="","",IF(C72="Entrada",INDEX(Movimientos!$F$5:$F$3004,MATCH($A72,Movimientos!$M$5:$M$3004,0)),"")) | F72: =IF($A72="","",IF(C72="Salida",INDEX(Movimientos!$F$5:$F$3004,MATCH($A72,Movimientos!$M$5:$M$3004,0)),"")) | G72: =IF($A72="","",INDEX(Movimientos!$I$5:$I$3004,MATCH($A72,Movimientos!$M$5:$M$3004,0))) | H72: =IF($A72="","",INDEX(Movimientos!$G$5:$G$3004,MATCH($A72,Movimientos!$M$5:$M$3004,0))) | I72: =IF($A72="","",INDEX(Movimientos!$H$5:$H$3004,MATCH($A72,Movimientos!$M$5:$M$3004,0))) | J72: =IF($A72="","",INDEX(Movimientos!$K$5:$K$3004,MATCH($A72,Movimientos!$M$5:$M$3004,0))&"")
A73: =IF(65<=COUNTIF(Movimientos!$M$5:$M$3004,">0"),65,"") | B73: =IF($A73="","",INDEX(Movimientos!$A$5:$A$3004,MATCH($A73,Movimientos!$M$5:$M$3004,0))) | C73: =IF($A73="","",INDEX(Movimientos!$B$5:$B$3004,MATCH($A73,Movimientos!$M$5:$M$3004,0))) | D73: =IF($A73="","",INDEX(Movimientos!$J$5:$J$3004,MATCH($A73,Movimientos!$M$5:$M$3004,0))&"") | E73: =IF($A73="","",IF(C73="Entrada",INDEX(Movimientos!$F$5:$F$3004,MATCH($A73,Movimientos!$M$5:$M$3004,0)),"")) | F73: =IF($A73="","",IF(C73="Salida",INDEX(Movimientos!$F$5:$F$3004,MATCH($A73,Movimientos!$M$5:$M$3004,0)),"")) | G73: =IF($A73="","",INDEX(Movimientos!$I$5:$I$3004,MATCH($A73,Movimientos!$M$5:$M$3004,0))) | H73: =IF($A73="","",INDEX(Movimientos!$G$5:$G$3004,MATCH($A73,Movimientos!$M$5:$M$3004,0))) | I73: =IF($A73="","",INDEX(Movimientos!$H$5:$H$3004,MATCH($A73,Movimientos!$M$5:$M$3004,0))) | J73: =IF($A73="","",INDEX(Movimientos!$K$5:$K$3004,MATCH($A73,Movimientos!$M$5:$M$3004,0))&"")
A74: =IF(66<=COUNTIF(Movimientos!$M$5:$M$3004,">0"),66,"") | B74: =IF($A74="","",INDEX(Movimientos!$A$5:$A$3004,MATCH($A74,Movimientos!$M$5:$M$3004,0))) | C74: =IF($A74="","",INDEX(Movimientos!$B$5:$B$3004,MATCH($A74,Movimientos!$M$5:$M$3004,0))) | D74: =IF($A74="","",INDEX(Movimientos!$J$5:$J$3004,MATCH($A74,Movimientos!$M$5:$M$3004,0))&"") | E74: =IF($A74="","",IF(C74="Entrada",INDEX(Movimientos!$F$5:$F$3004,MATCH($A74,Movimientos!$M$5:$M$3004,0)),"")) | F74: =IF($A74="","",IF(C74="Salida",INDEX(Movimientos!$F$5:$F$3004,MATCH($A74,Movimientos!$M$5:$M$3004,0)),"")) | G74: =IF($A74="","",INDEX(Movimientos!$I$5:$I$3004,MATCH($A74,Movimientos!$M$5:$M$3004,0))) | H74: =IF($A74="","",INDEX(Movimientos!$G$5:$G$3004,MATCH($A74,Movimientos!$M$5:$M$3004,0))) | I74: =IF($A74="","",INDEX(Movimientos!$H$5:$H$3004,MATCH($A74,Movimientos!$M$5:$M$3004,0))) | J74: =IF($A74="","",INDEX(Movimientos!$K$5:$K$3004,MATCH($A74,Movimientos!$M$5:$M$3004,0))&"")
A75: =IF(67<=COUNTIF(Movimientos!$M$5:$M$3004,">0"),67,"") | B75: =IF($A75="","",INDEX(Movimientos!$A$5:$A$3004,MATCH($A75,Movimientos!$M$5:$M$3004,0))) | C75: =IF($A75="","",INDEX(Movimientos!$B$5:$B$3004,MATCH($A75,Movimientos!$M$5:$M$3004,0))) | D75: =IF($A75="","",INDEX(Movimientos!$J$5:$J$3004,MATCH($A75,Movimientos!$M$5:$M$3004,0))&"") | E75: =IF($A75="","",IF(C75="Entrada",INDEX(Movimientos!$F$5:$F$3004,MATCH($A75,Movimientos!$M$5:$M$3004,0)),"")) | F75: =IF($A75="","",IF(C75="Salida",INDEX(Movimientos!$F$5:$F$3004,MATCH($A75,Movimientos!$M$5:$M$3004,0)),"")) | G75: =IF($A75="","",INDEX(Movimientos!$I$5:$I$3004,MATCH($A75,Movimientos!$M$5:$M$3004,0))) | H75: =IF($A75="","",INDEX(Movimientos!$G$5:$G$3004,MATCH($A75,Movimientos!$M$5:$M$3004,0))) | I75: =IF($A75="","",INDEX(Movimientos!$H$5:$H$3004,MATCH($A75,Movimientos!$M$5:$M$3004,0))) | J75: =IF($A75="","",INDEX(Movimientos!$K$5:$K$3004,MATCH($A75,Movimientos!$M$5:$M$3004,0))&"")
A76: =IF(68<=COUNTIF(Movimientos!$M$5:$M$3004,">0"),68,"") | B76: =IF($A76="","",INDEX(Movimientos!$A$5:$A$3004,MATCH($A76,Movimientos!$M$5:$M$3004,0))) | C76: =IF($A76="","",INDEX(Movimientos!$B$5:$B$3004,MATCH($A76,Movimientos!$M$5:$M$3004,0))) | D76: =IF($A76="","",INDEX(Movimientos!$J$5:$J$3004,MATCH($A76,Movimientos!$M$5:$M$3004,0))&"") | E76: =IF($A76="","",IF(C76="Entrada",INDEX(Movimientos!$F$5:$F$3004,MATCH($A76,Movimientos!$M$5:$M$3004,0)),"")) | F76: =IF($A76="","",IF(C76="Salida",INDEX(Movimientos!$F$5:$F$3004,MATCH($A76,Movimientos!$M$5:$M$3004,0)),"")) | G76: =IF($A76="","",INDEX(Movimientos!$I$5:$I$3004,MATCH($A76,Movimientos!$M$5:$M$3004,0))) | H76: =IF($A76="","",INDEX(Movimientos!$G$5:$G$3004,MATCH($A76,Movimientos!$M$5:$M$3004,0))) | I76: =IF($A76="","",INDEX(Movimientos!$H$5:$H$3004,MATCH($A76,Movimientos!$M$5:$M$3004,0))) | J76: =IF($A76="","",INDEX(Movimientos!$K$5:$K$3004,MATCH($A76,Movimientos!$M$5:$M$3004,0))&"")
A77: =IF(69<=COUNTIF(Movimientos!$M$5:$M$3004,">0"),69,"") | B77: =IF($A77="","",INDEX(Movimientos!$A$5:$A$3004,MATCH($A77,Movimientos!$M$5:$M$3004,0))) | C77: =IF($A77="","",INDEX(Movimientos!$B$5:$B$3004,MATCH($A77,Movimientos!$M$5:$M$3004,0))) | D77: =IF($A77="","",INDEX(Movimientos!$J$5:$J$3004,MATCH($A77,Movimientos!$M$5:$M$3004,0))&"") | E77: =IF($A77="","",IF(C77="Entrada",INDEX(Movimientos!$F$5:$F$3004,MATCH($A77,Movimientos!$M$5:$M$3004,0)),"")) | F77: =IF($A77="","",IF(C77="Salida",INDEX(Movimientos!$F$5:$F$3004,MATCH($A77,Movimientos!$M$5:$M$3004,0)),"")) | G77: =IF($A77="","",INDEX(Movimientos!$I$5:$I$3004,MATCH($A77,Movimientos!$M$5:$M$3004,0))) | H77: =IF($A77="","",INDEX(Movimientos!$G$5:$G$3004,MATCH($A77,Movimientos!$M$5:$M$3004,0))) | I77: =IF($A77="","",INDEX(Movimientos!$H$5:$H$3004,MATCH($A77,Movimientos!$M$5:$M$3004,0))) | J77: =IF($A77="","",INDEX(Movimientos!$K$5:$K$3004,MATCH($A77,Movimientos!$M$5:$M$3004,0))&"")
A78: =IF(70<=COUNTIF(Movimientos!$M$5:$M$3004,">0"),70,"") | B78: =IF($A78="","",INDEX(Movimientos!$A$5:$A$3004,MATCH($A78,Movimientos!$M$5:$M$3004,0))) | C78: =IF($A78="","",INDEX(Movimientos!$B$5:$B$3004,MATCH($A78,Movimientos!$M$5:$M$3004,0))) | D78: =IF($A78="","",INDEX(Movimientos!$J$5:$J$3004,MATCH($A78,Movimientos!$M$5:$M$3004,0))&"") | E78: =IF($A78="","",IF(C78="Entrada",INDEX(Movimientos!$F$5:$F$3004,MATCH($A78,Movimientos!$M$5:$M$3004,0)),"")) | F78: =IF($A78="","",IF(C78="Salida",INDEX(Movimientos!$F$5:$F$3004,MATCH($A78,Movimientos!$M$5:$M$3004,0)),"")) | G78: =IF($A78="","",INDEX(Movimientos!$I$5:$I$3004,MATCH($A78,Movimientos!$M$5:$M$3004,0))) | H78: =IF($A78="","",INDEX(Movimientos!$G$5:$G$3004,MATCH($A78,Movimientos!$M$5:$M$3004,0))) | I78: =IF($A78="","",INDEX(Movimientos!$H$5:$H$3004,MATCH($A78,Movimientos!$M$5:$M$3004,0))) | J78: =IF($A78="","",INDEX(Movimientos!$K$5:$K$3004,MATCH($A78,Movimientos!$M$5:$M$3004,0))&"")
A79: =IF(71<=COUNTIF(Movimientos!$M$5:$M$3004,">0"),71,"") | B79: =IF($A79="","",INDEX(Movimientos!$A$5:$A$3004,MATCH($A79,Movimientos!$M$5:$M$3004,0))) | C79: =IF($A79="","",INDEX(Movimientos!$B$5:$B$3004,MATCH($A79,Movimientos!$M$5:$M$3004,0))) | D79: =IF($A79="","",INDEX(Movimientos!$J$5:$J$3004,MATCH($A79,Movimientos!$M$5:$M$3004,0))&"") | E79: =IF($A79="","",IF(C79="Entrada",INDEX(Movimientos!$F$5:$F$3004,MATCH($A79,Movimientos!$M$5:$M$3004,0)),"")) | F79: =IF($A79="","",IF(C79="Salida",INDEX(Movimientos!$F$5:$F$3004,MATCH($A79,Movimientos!$M$5:$M$3004,0)),"")) | G79: =IF($A79="","",INDEX(Movimientos!$I$5:$I$3004,MATCH($A79,Movimientos!$M$5:$M$3004,0))) | H79: =IF($A79="","",INDEX(Movimientos!$G$5:$G$3004,MATCH($A79,Movimientos!$M$5:$M$3004,0))) | I79: =IF($A79="","",INDEX(Movimientos!$H$5:$H$3004,MATCH($A79,Movimientos!$M$5:$M$3004,0))) | J79: =IF($A79="","",INDEX(Movimientos!$K$5:$K$3004,MATCH($A79,Movimientos!$M$5:$M$3004,0))&"")
A80: =IF(72<=COUNTIF(Movimientos!$M$5:$M$3004,">0"),72,"") | B80: =IF($A80="","",INDEX(Movimientos!$A$5:$A$3004,MATCH($A80,Movimientos!$M$5:$M$3004,0))) | C80: =IF($A80="","",INDEX(Movimientos!$B$5:$B$3004,MATCH($A80,Movimientos!$M$5:$M$3004,0))) | D80: =IF($A80="","",INDEX(Movimientos!$J$5:$J$3004,MATCH($A80,Movimientos!$M$5:$M$3004,0))&"") | E80: =IF($A80="","",IF(C80="Entrada",INDEX(Movimientos!$F$5:$F$3004,MATCH($A80,Movimientos!$M$5:$M$3004,0)),"")) | F80: =IF($A80="","",IF(C80="Salida",INDEX(Movimientos!$F$5:$F$3004,MATCH($A80,Movimientos!$M$5:$M$3004,0)),"")) | G80: =IF($A80="","",INDEX(Movimientos!$I$5:$I$3004,MATCH($A80,Movimientos!$M$5:$M$3004,0))) | H80: =IF($A80="","",INDEX(Movimientos!$G$5:$G$3004,MATCH($A80,Movimientos!$M$5:$M$3004,0))) | I80: =IF($A80="","",INDEX(Movimientos!$H$5:$H$3004,MATCH($A80,Movimientos!$M$5:$M$3004,0))) | J80: =IF($A80="","",INDEX(Movimientos!$K$5:$K$3004,MATCH($A80,Movimientos!$M$5:$M$3004,0))&"")
A81: =IF(73<=COUNTIF(Movimientos!$M$5:$M$3004,">0"),73,"") | B81: =IF($A81="","",INDEX(Movimientos!$A$5:$A$3004,MATCH($A81,Movimientos!$M$5:$M$3004,0))) | C81: =IF($A81="","",INDEX(Movimientos!$B$5:$B$3004,MATCH($A81,Movimientos!$M$5:$M$3004,0))) | D81: =IF($A81="","",INDEX(Movimientos!$J$5:$J$3004,MATCH($A81,Movimientos!$M$5:$M$3004,0))&"") | E81: =IF($A81="","",IF(C81="Entrada",INDEX(Movimientos!$F$5:$F$3004,MATCH($A81,Movimientos!$M$5:$M$3004,0)),"")) | F81: =IF($A81="","",IF(C81="Salida",INDEX(Movimientos!$F$5:$F$3004,MATCH($A81,Movimientos!$M$5:$M$3004,0)),"")) | G81: =IF($A81="","",INDEX(Movimientos!$I$5:$I$3004,MATCH($A81,Movimientos!$M$5:$M$3004,0))) | H81: =IF($A81="","",INDEX(Movimientos!$G$5:$G$3004,MATCH($A81,Movimientos!$M$5:$M$3004,0))) | I81: =IF($A81="","",INDEX(Movimientos!$H$5:$H$3004,MATCH($A81,Movimientos!$M$5:$M$3004,0))) | J81: =IF($A81="","",INDEX(Movimientos!$K$5:$K$3004,MATCH($A81,Movimientos!$M$5:$M$3004,0))&"")
A82: =IF(74<=COUNTIF(Movimientos!$M$5:$M$3004,">0"),74,"") | B82: =IF($A82="","",INDEX(Movimientos!$A$5:$A$3004,MATCH($A82,Movimientos!$M$5:$M$3004,0))) | C82: =IF($A82="","",INDEX(Movimientos!$B$5:$B$3004,MATCH($A82,Movimientos!$M$5:$M$3004,0))) | D82: =IF($A82="","",INDEX(Movimientos!$J$5:$J$3004,MATCH($A82,Movimientos!$M$5:$M$3004,0))&"") | E82: =IF($A82="","",IF(C82="Entrada",INDEX(Movimientos!$F$5:$F$3004,MATCH($A82,Movimientos!$M$5:$M$3004,0)),"")) | F82: =IF($A82="","",IF(C82="Salida",INDEX(Movimientos!$F$5:$F$3004,MATCH($A82,Movimientos!$M$5:$M$3004,0)),"")) | G82: =IF($A82="","",INDEX(Movimientos!$I$5:$I$3004,MATCH($A82,Movimientos!$M$5:$M$3004,0))) | H82: =IF($A82="","",INDEX(Movimientos!$G$5:$G$3004,MATCH($A82,Movimientos!$M$5:$M$3004,0))) | I82: =IF($A82="","",INDEX(Movimientos!$H$5:$H$3004,MATCH($A82,Movimientos!$M$5:$M$3004,0))) | J82: =IF($A82="","",INDEX(Movimientos!$K$5:$K$3004,MATCH($A82,Movimientos!$M$5:$M$3004,0))&"")
A83: =IF(75<=COUNTIF(Movimientos!$M$5:$M$3004,">0"),75,"") | B83: =IF($A83="","",INDEX(Movimientos!$A$5:$A$3004,MATCH($A83,Movimientos!$M$5:$M$3004,0))) | C83: =IF($A83="","",INDEX(Movimientos!$B$5:$B$3004,MATCH($A83,Movimientos!$M$5:$M$3004,0))) | D83: =IF($A83="","",INDEX(Movimientos!$J$5:$J$3004,MATCH($A83,Movimientos!$M$5:$M$3004,0))&"") | E83: =IF($A83="","",IF(C83="Entrada",INDEX(Movimientos!$F$5:$F$3004,MATCH($A83,Movimientos!$M$5:$M$3004,0)),"")) | F83: =IF($A83="","",IF(C83="Salida",INDEX(Movimientos!$F$5:$F$3004,MATCH($A83,Movimientos!$M$5:$M$3004,0)),"")) | G83: =IF($A83="","",INDEX(Movimientos!$I$5:$I$3004,MATCH($A83,Movimientos!$M$5:$M$3004,0))) | H83: =IF($A83="","",INDEX(Movimientos!$G$5:$G$3004,MATCH($A83,Movimientos!$M$5:$M$3004,0))) | I83: =IF($A83="","",INDEX(Movimientos!$H$5:$H$3004,MATCH($A83,Movimientos!$M$5:$M$3004,0))) | J83: =IF($A83="","",INDEX(Movimientos!$K$5:$K$3004,MATCH($A83,Movimientos!$M$5:$M$3004,0))&"")
A84: =IF(76<=COUNTIF(Movimientos!$M$5:$M$3004,">0"),76,"") | B84: =IF($A84="","",INDEX(Movimientos!$A$5:$A$3004,MATCH($A84,Movimientos!$M$5:$M$3004,0))) | C84: =IF($A84="","",INDEX(Movimientos!$B$5:$B$3004,MATCH($A84,Movimientos!$M$5:$M$3004,0))) | D84: =IF($A84="","",INDEX(Movimientos!$J$5:$J$3004,MATCH($A84,Movimientos!$M$5:$M$3004,0))&"") | E84: =IF($A84="","",IF(C84="Entrada",INDEX(Movimientos!$F$5:$F$3004,MATCH($A84,Movimientos!$M$5:$M$3004,0)),"")) | F84: =IF($A84="","",IF(C84="Salida",INDEX(Movimientos!$F$5:$F$3004,MATCH($A84,Movimientos!$M$5:$M$3004,0)),"")) | G84: =IF($A84="","",INDEX(Movimientos!$I$5:$I$3004,MATCH($A84,Movimientos!$M$5:$M$3004,0))) | H84: =IF($A84="","",INDEX(Movimientos!$G$5:$G$3004,MATCH($A84,Movimientos!$M$5:$M$3004,0))) | I84: =IF($A84="","",INDEX(Movimientos!$H$5:$H$3004,MATCH($A84,Movimientos!$M$5:$M$3004,0))) | J84: =IF($A84="","",INDEX(Movimientos!$K$5:$K$3004,MATCH($A84,Movimientos!$M$5:$M$3004,0))&"")
A85: =IF(77<=COUNTIF(Movimientos!$M$5:$M$3004,">0"),77,"") | B85: =IF($A85="","",INDEX(Movimientos!$A$5:$A$3004,MATCH($A85,Movimientos!$M$5:$M$3004,0))) | C85: =IF($A85="","",INDEX(Movimientos!$B$5:$B$3004,MATCH($A85,Movimientos!$M$5:$M$3004,0))) | D85: =IF($A85="","",INDEX(Movimientos!$J$5:$J$3004,MATCH($A85,Movimientos!$M$5:$M$3004,0))&"") | E85: =IF($A85="","",IF(C85="Entrada",INDEX(Movimientos!$F$5:$F$3004,MATCH($A85,Movimientos!$M$5:$M$3004,0)),"")) | F85: =IF($A85="","",IF(C85="Salida",INDEX(Movimientos!$F$5:$F$3004,MATCH($A85,Movimientos!$M$5:$M$3004,0)),"")) | G85: =IF($A85="","",INDEX(Movimientos!$I$5:$I$3004,MATCH($A85,Movimientos!$M$5:$M$3004,0))) | H85: =IF($A85="","",INDEX(Movimientos!$G$5:$G$3004,MATCH($A85,Movimientos!$M$5:$M$3004,0))) | I85: =IF($A85="","",INDEX(Movimientos!$H$5:$H$3004,MATCH($A85,Movimientos!$M$5:$M$3004,0))) | J85: =IF($A85="","",INDEX(Movimientos!$K$5:$K$3004,MATCH($A85,Movimientos!$M$5:$M$3004,0))&"")
A86: =IF(78<=COUNTIF(Movimientos!$M$5:$M$3004,">0"),78,"") | B86: =IF($A86="","",INDEX(Movimientos!$A$5:$A$3004,MATCH($A86,Movimientos!$M$5:$M$3004,0))) | C86: =IF($A86="","",INDEX(Movimientos!$B$5:$B$3004,MATCH($A86,Movimientos!$M$5:$M$3004,0))) | D86: =IF($A86="","",INDEX(Movimientos!$J$5:$J$3004,MATCH($A86,Movimientos!$M$5:$M$3004,0))&"") | E86: =IF($A86="","",IF(C86="Entrada",INDEX(Movimientos!$F$5:$F$3004,MATCH($A86,Movimientos!$M$5:$M$3004,0)),"")) | F86: =IF($A86="","",IF(C86="Salida",INDEX(Movimientos!$F$5:$F$3004,MATCH($A86,Movimientos!$M$5:$M$3004,0)),"")) | G86: =IF($A86="","",INDEX(Movimientos!$I$5:$I$3004,MATCH($A86,Movimientos!$M$5:$M$3004,0))) | H86: =IF($A86="","",INDEX(Movimientos!$G$5:$G$3004,MATCH($A86,Movimientos!$M$5:$M$3004,0))) | I86: =IF($A86="","",INDEX(Movimientos!$H$5:$H$3004,MATCH($A86,Movimientos!$M$5:$M$3004,0))) | J86: =IF($A86="","",INDEX(Movimientos!$K$5:$K$3004,MATCH($A86,Movimientos!$M$5:$M$3004,0))&"")
A87: =IF(79<=COUNTIF(Movimientos!$M$5:$M$3004,">0"),79,"") | B87: =IF($A87="","",INDEX(Movimientos!$A$5:$A$3004,MATCH($A87,Movimientos!$M$5:$M$3004,0))) | C87: =IF($A87="","",INDEX(Movimientos!$B$5:$B$3004,MATCH($A87,Movimientos!$M$5:$M$3004,0))) | D87: =IF($A87="","",INDEX(Movimientos!$J$5:$J$3004,MATCH($A87,Movimientos!$M$5:$M$3004,0))&"") | E87: =IF($A87="","",IF(C87="Entrada",INDEX(Movimientos!$F$5:$F$3004,MATCH($A87,Movimientos!$M$5:$M$3004,0)),"")) | F87: =IF($A87="","",IF(C87="Salida",INDEX(Movimientos!$F$5:$F$3004,MATCH($A87,Movimientos!$M$5:$M$3004,0)),"")) | G87: =IF($A87="","",INDEX(Movimientos!$I$5:$I$3004,MATCH($A87,Movimientos!$M$5:$M$3004,0))) | H87: =IF($A87="","",INDEX(Movimientos!$G$5:$G$3004,MATCH($A87,Movimientos!$M$5:$M$3004,0))) | I87: =IF($A87="","",INDEX(Movimientos!$H$5:$H$3004,MATCH($A87,Movimientos!$M$5:$M$3004,0))) | J87: =IF($A87="","",INDEX(Movimientos!$K$5:$K$3004,MATCH($A87,Movimientos!$M$5:$M$3004,0))&"")
A88: =IF(80<=COUNTIF(Movimientos!$M$5:$M$3004,">0"),80,"") | B88: =IF($A88="","",INDEX(Movimientos!$A$5:$A$3004,MATCH($A88,Movimientos!$M$5:$M$3004,0))) | C88: =IF($A88="","",INDEX(Movimientos!$B$5:$B$3004,MATCH($A88,Movimientos!$M$5:$M$3004,0))) | D88: =IF($A88="","",INDEX(Movimientos!$J$5:$J$3004,MATCH($A88,Movimientos!$M$5:$M$3004,0))&"") | E88: =IF($A88="","",IF(C88="Entrada",INDEX(Movimientos!$F$5:$F$3004,MATCH($A88,Movimientos!$M$5:$M$3004,0)),"")) | F88: =IF($A88="","",IF(C88="Salida",INDEX(Movimientos!$F$5:$F$3004,MATCH($A88,Movimientos!$M$5:$M$3004,0)),"")) | G88: =IF($A88="","",INDEX(Movimientos!$I$5:$I$3004,MATCH($A88,Movimientos!$M$5:$M$3004,0))) | H88: =IF($A88="","",INDEX(Movimientos!$G$5:$G$3004,MATCH($A88,Movimientos!$M$5:$M$3004,0))) | I88: =IF($A88="","",INDEX(Movimientos!$H$5:$H$3004,MATCH($A88,Movimientos!$M$5:$M$3004,0))) | J88: =IF($A88="","",INDEX(Movimientos!$K$5:$K$3004,MATCH($A88,Movimientos!$M$5:$M$3004,0))&"")
A89: =IF(81<=COUNTIF(Movimientos!$M$5:$M$3004,">0"),81,"") | B89: =IF($A89="","",INDEX(Movimientos!$A$5:$A$3004,MATCH($A89,Movimientos!$M$5:$M$3004,0))) | C89: =IF($A89="","",INDEX(Movimientos!$B$5:$B$3004,MATCH($A89,Movimientos!$M$5:$M$3004,0))) | D89: =IF($A89="","",INDEX(Movimientos!$J$5:$J$3004,MATCH($A89,Movimientos!$M$5:$M$3004,0))&"") | E89: =IF($A89="","",IF(C89="Entrada",INDEX(Movimientos!$F$5:$F$3004,MATCH($A89,Movimientos!$M$5:$M$3004,0)),"")) | F89: =IF($A89="","",IF(C89="Salida",INDEX(Movimientos!$F$5:$F$3004,MATCH($A89,Movimientos!$M$5:$M$3004,0)),"")) | G89: =IF($A89="","",INDEX(Movimientos!$I$5:$I$3004,MATCH($A89,Movimientos!$M$5:$M$3004,0))) | H89: =IF($A89="","",INDEX(Movimientos!$G$5:$G$3004,MATCH($A89,Movimientos!$M$5:$M$3004,0))) | I89: =IF($A89="","",INDEX(Movimientos!$H$5:$H$3004,MATCH($A89,Movimientos!$M$5:$M$3004,0))) | J89: =IF($A89="","",INDEX(Movimientos!$K$5:$K$3004,MATCH($A89,Movimientos!$M$5:$M$3004,0))&"")
A90: =IF(82<=COUNTIF(Movimientos!$M$5:$M$3004,">0"),82,"") | B90: =IF($A90="","",INDEX(Movimientos!$A$5:$A$3004,MATCH($A90,Movimientos!$M$5:$M$3004,0))) | C90: =IF($A90="","",INDEX(Movimientos!$B$5:$B$3004,MATCH($A90,Movimientos!$M$5:$M$3004,0))) | D90: =IF($A90="","",INDEX(Movimientos!$J$5:$J$3004,MATCH($A90,Movimientos!$M$5:$M$3004,0))&"") | E90: =IF($A90="","",IF(C90="Entrada",INDEX(Movimientos!$F$5:$F$3004,MATCH($A90,Movimientos!$M$5:$M$3004,0)),"")) | F90: =IF($A90="","",IF(C90="Salida",INDEX(Movimientos!$F$5:$F$3004,MATCH($A90,Movimientos!$M$5:$M$3004,0)),"")) | G90: =IF($A90="","",INDEX(Movimientos!$I$5:$I$3004,MATCH($A90,Movimientos!$M$5:$M$3004,0))) | H90: =IF($A90="","",INDEX(Movimientos!$G$5:$G$3004,MATCH($A90,Movimientos!$M$5:$M$3004,0))) | I90: =IF($A90="","",INDEX(Movimientos!$H$5:$H$3004,MATCH($A90,Movimientos!$M$5:$M$3004,0))) | J90: =IF($A90="","",INDEX(Movimientos!$K$5:$K$3004,MATCH($A90,Movimientos!$M$5:$M$3004,0))&"")
A91: =IF(83<=COUNTIF(Movimientos!$M$5:$M$3004,">0"),83,"") | B91: =IF($A91="","",INDEX(Movimientos!$A$5:$A$3004,MATCH($A91,Movimientos!$M$5:$M$3004,0))) | C91: =IF($A91="","",INDEX(Movimientos!$B$5:$B$3004,MATCH($A91,Movimientos!$M$5:$M$3004,0))) | D91: =IF($A91="","",INDEX(Movimientos!$J$5:$J$3004,MATCH($A91,Movimientos!$M$5:$M$3004,0))&"") | E91: =IF($A91="","",IF(C91="Entrada",INDEX(Movimientos!$F$5:$F$3004,MATCH($A91,Movimientos!$M$5:$M$3004,0)),"")) | F91: =IF($A91="","",IF(C91="Salida",INDEX(Movimientos!$F$5:$F$3004,MATCH($A91,Movimientos!$M$5:$M$3004,0)),"")) | G91: =IF($A91="","",INDEX(Movimientos!$I$5:$I$3004,MATCH($A91,Movimientos!$M$5:$M$3004,0))) | H91: =IF($A91="","",INDEX(Movimientos!$G$5:$G$3004,MATCH($A91,Movimientos!$M$5:$M$3004,0))) | I91: =IF($A91="","",INDEX(Movimientos!$H$5:$H$3004,MATCH($A91,Movimientos!$M$5:$M$3004,0))) | J91: =IF($A91="","",INDEX(Movimientos!$K$5:$K$3004,MATCH($A91,Movimientos!$M$5:$M$3004,0))&"")
A92: =IF(84<=COUNTIF(Movimientos!$M$5:$M$3004,">0"),84,"") | B92: =IF($A92="","",INDEX(Movimientos!$A$5:$A$3004,MATCH($A92,Movimientos!$M$5:$M$3004,0))) | C92: =IF($A92="","",INDEX(Movimientos!$B$5:$B$3004,MATCH($A92,Movimientos!$M$5:$M$3004,0))) | D92: =IF($A92="","",INDEX(Movimientos!$J$5:$J$3004,MATCH($A92,Movimientos!$M$5:$M$3004,0))&"") | E92: =IF($A92="","",IF(C92="Entrada",INDEX(Movimientos!$F$5:$F$3004,MATCH($A92,Movimientos!$M$5:$M$3004,0)),"")) | F92: =IF($A92="","",IF(C92="Salida",INDEX(Movimientos!$F$5:$F$3004,MATCH($A92,Movimientos!$M$5:$M$3004,0)),"")) | G92: =IF($A92="","",INDEX(Movimientos!$I$5:$I$3004,MATCH($A92,Movimientos!$M$5:$M$3004,0))) | H92: =IF($A92="","",INDEX(Movimientos!$G$5:$G$3004,MATCH($A92,Movimientos!$M$5:$M$3004,0))) | I92: =IF($A92="","",INDEX(Movimientos!$H$5:$H$3004,MATCH($A92,Movimientos!$M$5:$M$3004,0))) | J92: =IF($A92="","",INDEX(Movimientos!$K$5:$K$3004,MATCH($A92,Movimientos!$M$5:$M$3004,0))&"")
A93: =IF(85<=COUNTIF(Movimientos!$M$5:$M$3004,">0"),85,"") | B93: =IF($A93="","",INDEX(Movimientos!$A$5:$A$3004,MATCH($A93,Movimientos!$M$5:$M$3004,0))) | C93: =IF($A93="","",INDEX(Movimientos!$B$5:$B$3004,MATCH($A93,Movimientos!$M$5:$M$3004,0))) | D93: =IF($A93="","",INDEX(Movimientos!$J$5:$J$3004,MATCH($A93,Movimientos!$M$5:$M$3004,0))&"") | E93: =IF($A93="","",IF(C93="Entrada",INDEX(Movimientos!$F$5:$F$3004,MATCH($A93,Movimientos!$M$5:$M$3004,0)),"")) | F93: =IF($A93="","",IF(C93="Salida",INDEX(Movimientos!$F$5:$F$3004,MATCH($A93,Movimientos!$M$5:$M$3004,0)),"")) | G93: =IF($A93="","",INDEX(Movimientos!$I$5:$I$3004,MATCH($A93,Movimientos!$M$5:$M$3004,0))) | H93: =IF($A93="","",INDEX(Movimientos!$G$5:$G$3004,MATCH($A93,Movimientos!$M$5:$M$3004,0))) | I93: =IF($A93="","",INDEX(Movimientos!$H$5:$H$3004,MATCH($A93,Movimientos!$M$5:$M$3004,0))) | J93: =IF($A93="","",INDEX(Movimientos!$K$5:$K$3004,MATCH($A93,Movimientos!$M$5:$M$3004,0))&"")
A94: =IF(86<=COUNTIF(Movimientos!$M$5:$M$3004,">0"),86,"") | B94: =IF($A94="","",INDEX(Movimientos!$A$5:$A$3004,MATCH($A94,Movimientos!$M$5:$M$3004,0))) | C94: =IF($A94="","",INDEX(Movimientos!$B$5:$B$3004,MATCH($A94,Movimientos!$M$5:$M$3004,0))) | D94: =IF($A94="","",INDEX(Movimientos!$J$5:$J$3004,MATCH($A94,Movimientos!$M$5:$M$3004,0))&"") | E94: =IF($A94="","",IF(C94="Entrada",INDEX(Movimientos!$F$5:$F$3004,MATCH($A94,Movimientos!$M$5:$M$3004,0)),"")) | F94: =IF($A94="","",IF(C94="Salida",INDEX(Movimientos!$F$5:$F$3004,MATCH($A94,Movimientos!$M$5:$M$3004,0)),"")) | G94: =IF($A94="","",INDEX(Movimientos!$I$5:$I$3004,MATCH($A94,Movimientos!$M$5:$M$3004,0))) | H94: =IF($A94="","",INDEX(Movimientos!$G$5:$G$3004,MATCH($A94,Movimientos!$M$5:$M$3004,0))) | I94: =IF($A94="","",INDEX(Movimientos!$H$5:$H$3004,MATCH($A94,Movimientos!$M$5:$M$3004,0))) | J94: =IF($A94="","",INDEX(Movimientos!$K$5:$K$3004,MATCH($A94,Movimientos!$M$5:$M$3004,0))&"")
A95: =IF(87<=COUNTIF(Movimientos!$M$5:$M$3004,">0"),87,"") | B95: =IF($A95="","",INDEX(Movimientos!$A$5:$A$3004,MATCH($A95,Movimientos!$M$5:$M$3004,0))) | C95: =IF($A95="","",INDEX(Movimientos!$B$5:$B$3004,MATCH($A95,Movimientos!$M$5:$M$3004,0))) | D95: =IF($A95="","",INDEX(Movimientos!$J$5:$J$3004,MATCH($A95,Movimientos!$M$5:$M$3004,0))&"") | E95: =IF($A95="","",IF(C95="Entrada",INDEX(Movimientos!$F$5:$F$3004,MATCH($A95,Movimientos!$M$5:$M$3004,0)),"")) | F95: =IF($A95="","",IF(C95="Salida",INDEX(Movimientos!$F$5:$F$3004,MATCH($A95,Movimientos!$M$5:$M$3004,0)),"")) | G95: =IF($A95="","",INDEX(Movimientos!$I$5:$I$3004,MATCH($A95,Movimientos!$M$5:$M$3004,0))) | H95: =IF($A95="","",INDEX(Movimientos!$G$5:$G$3004,MATCH($A95,Movimientos!$M$5:$M$3004,0))) | I95: =IF($A95="","",INDEX(Movimientos!$H$5:$H$3004,MATCH($A95,Movimientos!$M$5:$M$3004,0))) | J95: =IF($A95="","",INDEX(Movimientos!$K$5:$K$3004,MATCH($A95,Movimientos!$M$5:$M$3004,0))&"")
A96: =IF(88<=COUNTIF(Movimientos!$M$5:$M$3004,">0"),88,"") | B96: =IF($A96="","",INDEX(Movimientos!$A$5:$A$3004,MATCH($A96,Movimientos!$M$5:$M$3004,0))) | C96: =IF($A96="","",INDEX(Movimientos!$B$5:$B$3004,MATCH($A96,Movimientos!$M$5:$M$3004,0))) | D96: =IF($A96="","",INDEX(Movimientos!$J$5:$J$3004,MATCH($A96,Movimientos!$M$5:$M$3004,0))&"") | E96: =IF($A96="","",IF(C96="Entrada",INDEX(Movimientos!$F$5:$F$3004,MATCH($A96,Movimientos!$M$5:$M$3004,0)),"")) | F96: =IF($A96="","",IF(C96="Salida",INDEX(Movimientos!$F$5:$F$3004,MATCH($A96,Movimientos!$M$5:$M$3004,0)),"")) | G96: =IF($A96="","",INDEX(Movimientos!$I$5:$I$3004,MATCH($A96,Movimientos!$M$5:$M$3004,0))) | H96: =IF($A96="","",INDEX(Movimientos!$G$5:$G$3004,MATCH($A96,Movimientos!$M$5:$M$3004,0))) | I96: =IF($A96="","",INDEX(Movimientos!$H$5:$H$3004,MATCH($A96,Movimientos!$M$5:$M$3004,0))) | J96: =IF($A96="","",INDEX(Movimientos!$K$5:$K$3004,MATCH($A96,Movimientos!$M$5:$M$3004,0))&"")
A97: =IF(89<=COUNTIF(Movimientos!$M$5:$M$3004,">0"),89,"") | B97: =IF($A97="","",INDEX(Movimientos!$A$5:$A$3004,MATCH($A97,Movimientos!$M$5:$M$3004,0))) | C97: =IF($A97="","",INDEX(Movimientos!$B$5:$B$3004,MATCH($A97,Movimientos!$M$5:$M$3004,0))) | D97: =IF($A97="","",INDEX(Movimientos!$J$5:$J$3004,MATCH($A97,Movimientos!$M$5:$M$3004,0))&"") | E97: =IF($A97="","",IF(C97="Entrada",INDEX(Movimientos!$F$5:$F$3004,MATCH($A97,Movimientos!$M$5:$M$3004,0)),"")) | F97: =IF($A97="","",IF(C97="Salida",INDEX(Movimientos!$F$5:$F$3004,MATCH($A97,Movimientos!$M$5:$M$3004,0)),"")) | G97: =IF($A97="","",INDEX(Movimientos!$I$5:$I$3004,MATCH($A97,Movimientos!$M$5:$M$3004,0))) | H97: =IF($A97="","",INDEX(Movimientos!$G$5:$G$3004,MATCH($A97,Movimientos!$M$5:$M$3004,0))) | I97: =IF($A97="","",INDEX(Movimientos!$H$5:$H$3004,MATCH($A97,Movimientos!$M$5:$M$3004,0))) | J97: =IF($A97="","",INDEX(Movimientos!$K$5:$K$3004,MATCH($A97,Movimientos!$M$5:$M$3004,0))&"")
A98: =IF(90<=COUNTIF(Movimientos!$M$5:$M$3004,">0"),90,"") | B98: =IF($A98="","",INDEX(Movimientos!$A$5:$A$3004,MATCH($A98,Movimientos!$M$5:$M$3004,0))) | C98: =IF($A98="","",INDEX(Movimientos!$B$5:$B$3004,MATCH($A98,Movimientos!$M$5:$M$3004,0))) | D98: =IF($A98="","",INDEX(Movimientos!$J$5:$J$3004,MATCH($A98,Movimientos!$M$5:$M$3004,0))&"") | E98: =IF($A98="","",IF(C98="Entrada",INDEX(Movimientos!$F$5:$F$3004,MATCH($A98,Movimientos!$M$5:$M$3004,0)),"")) | F98: =IF($A98="","",IF(C98="Salida",INDEX(Movimientos!$F$5:$F$3004,MATCH($A98,Movimientos!$M$5:$M$3004,0)),"")) | G98: =IF($A98="","",INDEX(Movimientos!$I$5:$I$3004,MATCH($A98,Movimientos!$M$5:$M$3004,0))) | H98: =IF($A98="","",INDEX(Movimientos!$G$5:$G$3004,MATCH($A98,Movimientos!$M$5:$M$3004,0))) | I98: =IF($A98="","",INDEX(Movimientos!$H$5:$H$3004,MATCH($A98,Movimientos!$M$5:$M$3004,0))) | J98: =IF($A98="","",INDEX(Movimientos!$K$5:$K$3004,MATCH($A98,Movimientos!$M$5:$M$3004,0))&"")
A99: =IF(91<=COUNTIF(Movimientos!$M$5:$M$3004,">0"),91,"") | B99: =IF($A99="","",INDEX(Movimientos!$A$5:$A$3004,MATCH($A99,Movimientos!$M$5:$M$3004,0))) | C99: =IF($A99="","",INDEX(Movimientos!$B$5:$B$3004,MATCH($A99,Movimientos!$M$5:$M$3004,0))) | D99: =IF($A99="","",INDEX(Movimientos!$J$5:$J$3004,MATCH($A99,Movimientos!$M$5:$M$3004,0))&"") | E99: =IF($A99="","",IF(C99="Entrada",INDEX(Movimientos!$F$5:$F$3004,MATCH($A99,Movimientos!$M$5:$M$3004,0)),"")) | F99: =IF($A99="","",IF(C99="Salida",INDEX(Movimientos!$F$5:$F$3004,MATCH($A99,Movimientos!$M$5:$M$3004,0)),"")) | G99: =IF($A99="","",INDEX(Movimientos!$I$5:$I$3004,MATCH($A99,Movimientos!$M$5:$M$3004,0))) | H99: =IF($A99="","",INDEX(Movimientos!$G$5:$G$3004,MATCH($A99,Movimientos!$M$5:$M$3004,0))) | I99: =IF($A99="","",INDEX(Movimientos!$H$5:$H$3004,MATCH($A99,Movimientos!$M$5:$M$3004,0))) | J99: =IF($A99="","",INDEX(Movimientos!$K$5:$K$3004,MATCH($A99,Movimientos!$M$5:$M$3004,0))&"")
A100: =IF(92<=COUNTIF(Movimientos!$M$5:$M$3004,">0"),92,"") | B100: =IF($A100="","",INDEX(Movimientos!$A$5:$A$3004,MATCH($A100,Movimientos!$M$5:$M$3004,0))) | C100: =IF($A100="","",INDEX(Movimientos!$B$5:$B$3004,MATCH($A100,Movimientos!$M$5:$M$3004,0))) | D100: =IF($A100="","",INDEX(Movimientos!$J$5:$J$3004,MATCH($A100,Movimientos!$M$5:$M$3004,0))&"") | E100: =IF($A100="","",IF(C100="Entrada",INDEX(Movimientos!$F$5:$F$3004,MATCH($A100,Movimientos!$M$5:$M$3004,0)),"")) | F100: =IF($A100="","",IF(C100="Salida",INDEX(Movimientos!$F$5:$F$3004,MATCH($A100,Movimientos!$M$5:$M$3004,0)),"")) | G100: =IF($A100="","",INDEX(Movimientos!$I$5:$I$3004,MATCH($A100,Movimientos!$M$5:$M$3004,0))) | H100: =IF($A100="","",INDEX(Movimientos!$G$5:$G$3004,MATCH($A100,Movimientos!$M$5:$M$3004,0))) | I100: =IF($A100="","",INDEX(Movimientos!$H$5:$H$3004,MATCH($A100,Movimientos!$M$5:$M$3004,0))) | J100: =IF($A100="","",INDEX(Movimientos!$K$5:$K$3004,MATCH($A100,Movimientos!$M$5:$M$3004,0))&"")
A101: =IF(93<=COUNTIF(Movimientos!$M$5:$M$3004,">0"),93,"") | B101: =IF($A101="","",INDEX(Movimientos!$A$5:$A$3004,MATCH($A101,Movimientos!$M$5:$M$3004,0))) | C101: =IF($A101="","",INDEX(Movimientos!$B$5:$B$3004,MATCH($A101,Movimientos!$M$5:$M$3004,0))) | D101: =IF($A101="","",INDEX(Movimientos!$J$5:$J$3004,MATCH($A101,Movimientos!$M$5:$M$3004,0))&"") | E101: =IF($A101="","",IF(C101="Entrada",INDEX(Movimientos!$F$5:$F$3004,MATCH($A101,Movimientos!$M$5:$M$3004,0)),"")) | F101: =IF($A101="","",IF(C101="Salida",INDEX(Movimientos!$F$5:$F$3004,MATCH($A101,Movimientos!$M$5:$M$3004,0)),"")) | G101: =IF($A101="","",INDEX(Movimientos!$I$5:$I$3004,MATCH($A101,Movimientos!$M$5:$M$3004,0))) | H101: =IF($A101="","",INDEX(Movimientos!$G$5:$G$3004,MATCH($A101,Movimientos!$M$5:$M$3004,0))) | I101: =IF($A101="","",INDEX(Movimientos!$H$5:$H$3004,MATCH($A101,Movimientos!$M$5:$M$3004,0))) | J101: =IF($A101="","",INDEX(Movimientos!$K$5:$K$3004,MATCH($A101,Movimientos!$M$5:$M$3004,0))&"")
A102: =IF(94<=COUNTIF(Movimientos!$M$5:$M$3004,">0"),94,"") | B102: =IF($A102="","",INDEX(Movimientos!$A$5:$A$3004,MATCH($A102,Movimientos!$M$5:$M$3004,0))) | C102: =IF($A102="","",INDEX(Movimientos!$B$5:$B$3004,MATCH($A102,Movimientos!$M$5:$M$3004,0))) | D102: =IF($A102="","",INDEX(Movimientos!$J$5:$J$3004,MATCH($A102,Movimientos!$M$5:$M$3004,0))&"") | E102: =IF($A102="","",IF(C102="Entrada",INDEX(Movimientos!$F$5:$F$3004,MATCH($A102,Movimientos!$M$5:$M$3004,0)),"")) | F102: =IF($A102="","",IF(C102="Salida",INDEX(Movimientos!$F$5:$F$3004,MATCH($A102,Movimientos!$M$5:$M$3004,0)),"")) | G102: =IF($A102="","",INDEX(Movimientos!$I$5:$I$3004,MATCH($A102,Movimientos!$M$5:$M$3004,0))) | H102: =IF($A102="","",INDEX(Movimientos!$G$5:$G$3004,MATCH($A102,Movimientos!$M$5:$M$3004,0))) | I102: =IF($A102="","",INDEX(Movimientos!$H$5:$H$3004,MATCH($A102,Movimientos!$M$5:$M$3004,0))) | J102: =IF($A102="","",INDEX(Movimientos!$K$5:$K$3004,MATCH($A102,Movimientos!$M$5:$M$3004,0))&"")
...
